Workbook

Sheet ESCENARIO 1
A1: ESCENARIO 1 | B1: 01-feb | C1: 02-feb | D1: 03-feb | E1: 04-feb | F1: 05-feb | G1: 06-feb | H1: 07-feb | I1: 08-feb | J1: 09-feb | K1: 10-feb | L1: 11-feb | M1: 12-feb | N1: 13-feb | O1: 14-feb | P1: 15-feb | Q1: 16-feb | R1: 17-feb | S1: 18-feb | T1: 19-feb | U1: 20-feb | V1: 21-feb | W1: 22-feb | X1: 23-feb | Y1: 24-feb | Z1: 25-feb | AA1: 26-feb | AB1: 27-feb | AC1: 28-feb | AD1: 01-mar | AE1: 02-mar | AF1: 03-mar | AG1: 04-mar | AH1: 05-mar | AI1: 06-mar | AJ1: 07-mar | AK1: 08-mar | AL1: 09-mar | AM1: 10-mar | AN1: 11-mar | AO1: 12-mar | AP1: 13-mar | AQ1: 14-mar | AR1: 15-mar | AS1: 16-mar | AT1: 17-mar | AU1: 18-mar | AV1: 19-mar | AW1: 20-mar | AX1: 21-mar | AY1: 22-mar | AZ1: 23-mar | BA1: 24-mar | BB1: 25-mar | BC1: 26-mar | BD1: 27-mar | BE1: 28-mar | BF1: 29-mar | BG1: 30-mar | BH1: 31-mar | BI1: 01-abr | BJ1: 02-abr | BK1: 03-abr | BL1: 04-abr | BM1: 05-abr | BN1: 06-abr | BO1: 07-abr | BP1: 08-abr | BQ1: 09-abr | BR1: 10-abr | BS1: 11-abr | BT1: 12-abr | BU1: 13-abr | BV1: 14-abr | BW1: 15-abr | BX1: 16-abr | BY1: 17-abr | BZ1: 18-abr | CA1: 19-abr | CB1: 20-abr | CC1: 21-abr | CD1: 22-abr | CE1: 23-abr | CF1: 24-abr | CG1: 25-abr | CH1: 26-abr | CI1: 27-abr | CJ1: 28-abr | CK1: 29-abr | CL1: 30-abr | CM1: 01-may | CN1: 02-may | CO1: 03-may | CP1: 04-may | CQ1: 05-may | CR1: 06-may | CS1: 07-may | CT1: 08-may | CU1: 09-may | CV1: 10-may | CW1: 11-may | CX1: 12-may | CY1: 13-may | CZ1: 14-may | DA1: 15-may | DB1: 16-may | DC1: 17-may | DD1: 18-may | DE1: 19-may | DF1: 20-may | DG1: 21-may | DH1: 22-may | DI1: 23-may | DJ1: 24-may | DK1: 25-may | DL1: 26-may | DM1: 27-may | DN1: 28-may | DO1: 29-may | DP1: 30-may | DQ1: 31-may | DR1: 01-jun | DS1: 02-jun | DT1: 03-jun | DU1: 04-jun | DV1: 05-jun | DW1: 06-jun | DX1: 07-jun | DY1: 08-jun | DZ1: 09-jun | EA1: 10-jun | EB1: 11-jun | EC1: 12-jun | ED1: 13-jun | EE1: 14-jun | EF1: 15-jun | EG1: 16-jun | EH1: 17-jun | EI1: 18-jun | EJ1: 19-jun | EK1: 20-jun | EL1: 21-jun | EM1: 22-jun | EN1: 23-jun | EO1: 24-jun | EP1: 25-jun | EQ1: 26-jun | ER1: 27-jun | ES1: 28-jun | ET1: 29-jun | EU1: 30-jun | EV1: 01-jul | EW1: 02-jul | EX1: 03-jul | EY1: 04-jul | EZ1: 05-jul | FA1: 06-jul | FB1: 07-jul | FC1: 08-jul | FD1: 09-jul | FE1: 10-jul | FF1: 11-jul | FG1: 12-jul | FH1: 13-jul | FI1: 14-jul | FJ1: 15-jul | FK1: 16-jul | FL1: 17-jul | FM1: 18-jul | FN1: 19-jul | FO1: 20-jul | FP1: 21-jul | FQ1: 22-jul | FR1: 23-jul | FS1: 24-jul | FT1: 25-jul | FU1: 26-jul | FV1: 27-jul | FW1: 28-jul | FX1: 29-jul | FY1: 30-jul | FZ1: 31-jul | GA1: 01-ago | GB1: 02-ago | GC1: 03-ago | GD1: 04-ago | GE1: 05-ago | GF1: 06-ago | GG1: 07-ago | GH1: 08-ago | GI1: 09-ago | GJ1: 10-ago | GK1: 11-ago | GL1: 12-ago | GM1: 13-ago | GN1: 14-ago | GO1: 15-ago | GP1: 16-ago | GQ1: 17-ago | GR1: 18-ago | GS1: 19-ago | GT1: 20-ago | GU1: 21-ago | GV1: 22-ago | GW1: 23-ago | GX1: 24-ago | GY1: 25-ago | GZ1: 26-ago | HA1: 27-ago | HB1: 28-ago | HC1: 29-ago | HD1: 30-ago | HE1: 31-ago | HF1: 01-sep | HG1: 02-sep | HH1: 03-sep | HI1: 04-sep | HJ1: 05-sep | HK1: 06-sep | HL1: 07-sep | HM1: 08-sep | HN1: 09-sep | HO1: 10-sep | HP1: 11-sep | HQ1: 12-sep | HR1: 13-sep | HS1: 14-sep | HT1: 15-sep | HU1: 16-sep | HV1: 17-sep | HW1: 18-sep | HX1: 19-sep | HY1: 20-sep | HZ1: 21-sep | IA1: 22-sep | IB1: 23-sep | IC1: 24-sep | ID1: 25-sep | IE1: 26-sep | IF1: 27-sep | IG1: 28-sep | IH1: 29-sep | II1: 30-sep | IJ1: 01-oct | IK1: 02-oct | IL1: 03-oct | IM1: 04-oct | IN1: 05-oct | IO1: 06-oct | IP1: 07-oct | IQ1: 08-oct | IR1: 09-oct | IS1: 10-oct | IT1: 11-oct | IU1: 12-oct | IV1: 13-oct | IW1: 14-oct | IX1: 15-oct | IY1: 16-oct | IZ1: 17-oct | JA1: 18-oct | JB1: 19-oct | JC1: 20-oct | JD1: 21-oct | JE1: 22-oct | JF1: 23-oct | JG1: 24-oct | JH1: 25-oct | JI1: 26-oct | JJ1: 27-oct | JK1: 28-oct | JL1: 29-oct | JM1: 30-oct | JN1: 31-oct | JO1: 01-nov | JP1: 02-nov | JQ1: 03-nov | JR1: 04-nov | JS1: 05-nov | JT1: 06-nov | JU1: 07-nov | JV1: 08-nov | JW1: 09-nov | JX1: 10-nov | JY1: 11-nov | JZ1: 12-nov | KA1: 13-nov | KB1: 14-nov | KC1: 15-nov | KD1: 16-nov | KE1: 17-nov | KF1: 18-nov | KG1: 19-nov | KH1: 20-nov | KI1: 21-nov | KJ1: 22-nov | KK1: 23-nov | KL1: 24-nov | KM1: 25-nov | KN1: 26-nov | KO1: 27-nov | KP1: 28-nov | KQ1: 29-nov | KR1: 30-nov | KS1: 01-dic | KT1: 02-dic | KU1: 03-dic | KV1: 04-dic | KW1: 05-dic | KX1: 06-dic | KY1: 07-dic | KZ1: 08-dic | LA1: 09-dic | LB1: 10-dic | LC1: 11-dic | LD1: 12-dic | LE1: 13-dic | LF1: 14-dic | LG1: 15-dic | LH1: 16-dic | LI1: 17-dic | LJ1: 18-dic | LK1: 19-dic | LL1: 20-dic | LM1: 21-dic | LN1: 22-dic | LO1: 23-dic | LP1: 24-dic | LQ1: 25-dic | LR1: 26-dic | LS1: 27-dic | LT1: 28-dic | LU1: 29-dic | LV1: 30-dic | LW1: 31-dic | LX1: TOTAL
A2: CAJA INICIAL | B2: 2.376101e+09 | C2: =B4 -> 0 | D2: =C4 -> 6.3994528e+08 | E2: =D4+D9 -> 8.7380819e+08 | F2: =E4+E9 -> 4.9731141e+08 | G2: =F4+F9 -> 6.2814917e+08 | H2: =G4+G9 -> 8.1579303e+08 | I2: =H4+H9 -> 0 | J2: =I4+I9 -> 0 | K2: =J4+J9 -> 1.4233244e+09 | L2: =K4+K9 -> 7.2399112e+09 | ... AC2: =AB4+AB9 -> 5.6100402e+08 | AD2: 538000000 | AE2: =AD4+AD9 -> 0 | AF2: =AE4+AE9 -> 6.5203271e+08 | AG2: =AF4+AF9 -> 8.8995777e+08 | AH2: =AG4+AG9 -> 5.0670475e+08 | AI2: =AH4+AH9 -> 6.400138e+08 | AJ2: =AI4+AI9 -> 8.3120192e+08 | AK2: =AJ4+AJ9 -> 0 | AL2: =AK4+AK9 -> 0 | ... LW2: =LV4+LV9 -> 2.0280094e+09 | LX2: =SUM(ESCENARIO[[#This Row],[01-mar]:[31-dic]]) -> 4.0273471e+11
A3: GASTOS PROYECTADOS | B3: =SUMIFS(Gastos!$H:$H,Gastos!$I:$I,'ESCENARIO 1'!B$1) -> 0 | C3: =SUMIFS(Gastos!$H:$H,Gastos!$I:$I,'ESCENARIO 1'!C$1) -> 235000000 | D3: =SUMIFS(Gastos!$H:$H,Gastos!$I:$I,'ESCENARIO 1'!D$1) -> 1.4470035e+09 | E3: =SUMIFS(Gastos!$H:$H,Gastos!$I:$I,'ESCENARIO 1'!E$1) -> 0 | F3: =SUMIFS(Gastos!$H:$H,Gastos!$I:$I,'ESCENARIO 1'!F$1) -> 0 | G3: =SUMIFS(Gastos!$H:$H,Gastos!$I:$I,'ESCENARIO 1'!G$1) -> 0 | H3: =SUMIFS(Gastos!$H:$H,Gastos!$I:$I,'ESCENARIO 1'!H$1) -> 0 | I3: =SUMIFS(Gastos!$H:$H,Gastos!$I:$I,'ESCENARIO 1'!I$1) -> 0 | ... AC3: =SUMIFS(Gastos!$H:$H,Gastos!$I:$I,'ESCENARIO 1'!AC$1) -> 5.1450202e+08 | AD3: =SUMIFS(Gastos!$J:$J,Gastos!$K:$K,'ESCENARIO 1'!AD$1) -> 0 | AE3: =SUMIFS(Gastos!$J:$J,Gastos!$K:$K,'ESCENARIO 1'!AE$1) -> 0 | AF3: =SUMIFS(Gastos!$J:$J,Gastos!$K:$K,'ESCENARIO 1'!AF$1) -> 1107100000 | AG3: =SUMIFS(Gastos!$J:$J,Gastos!$K:$K,'ESCENARIO 1'!AG$1) -> 0 | AH3: =SUMIFS(Gastos!$J:$J,Gastos!$K:$K,'ESCENARIO 1'!AH$1) -> 0 | AI3: =SUMIFS(Gastos!$J:$J,Gastos!$K:$K,'ESCENARIO 1'!AI$1) -> 0 | AJ3: =SUMIFS(Gastos!$J:$J,Gastos!$K:$K,'ESCENARIO 1'!AJ$1) -> 0 | AK3: =SUMIFS(Gastos!$J:$J,Gastos!$K:$K,'ESCENARIO 1'!AK$1) -> 0 | ... BH3: =SUMIFS(Gastos!$J:$J,Gastos!$K:$K,'ESCENARIO 1'!BH$1) -> 2.0099429e+10 | BI3: =SUMIFS(Gastos!$L:$L,Gastos!$M:$M,'ESCENARIO 1'!BI$1) -> 0 | BJ3: =SUMIFS(Gastos!$L:$L,Gastos!$M:$M,'ESCENARIO 1'!BJ$1) -> 0 | BK3: =SUMIFS(Gastos!$L:$L,Gastos!$M:$M,'ESCENARIO 1'!BK$1) -> 0 | BL3: =SUMIFS(Gastos!$L:$L,Gastos!$M:$M,'ESCENARIO 1'!BL$1) -> 0 | BM3: =SUMIFS(Gastos!$L:$L,Gastos!$M:$M,'ESCENARIO 1'!BM$1) -> 0 | BN3: =SUMIFS(Gastos!$L:$L,Gastos!$M:$M,'ESCENARIO 1'!BN$1) -> 0 | BO3: =SUMIFS(Gastos!$L:$L,Gastos!$M:$M,'ESCENARIO 1'!BO$1) -> 1107100000 | BP3: =SUMIFS(Gastos!$L:$L,Gastos!$M:$M,'ESCENARIO 1'!BP$1) -> 0 | ... CL3: =SUMIFS(Gastos!$L:$L,Gastos!$M:$M,'ESCENARIO 1'!CL$1) -> 2.4010737e+10 | CM3: =SUMIFS(Gastos!$N:$N,Gastos!$O:$O,'ESCENARIO 1'!CM$1) -> 0 | CN3: =SUMIFS(Gastos!$N:$N,Gastos!$O:$O,'ESCENARIO 1'!CN$1) -> 0 | CO3: =SUMIFS(Gastos!$N:$N,Gastos!$O:$O,'ESCENARIO 1'!CO$1) -> 0 | CP3: =SUMIFS(Gastos!$N:$N,Gastos!$O:$O,'ESCENARIO 1'!CP$1) -> 0 | CQ3: =SUMIFS(Gastos!$N:$N,Gastos!$O:$O,'ESCENARIO 1'!CQ$1) -> 1107100000 | CR3: =SUMIFS(Gastos!$N:$N,Gastos!$O:$O,'ESCENARIO 1'!CR$1) -> 0 | CS3: =SUMIFS(Gastos!$N:$N,Gastos!$O:$O,'ESCENARIO 1'!CS$1) -> 0 | CT3: =SUMIFS(Gastos!$N:$N,Gastos!$O:$O,'ESCENARIO 1'!CT$1) -> 0 | ... DQ3: =SUMIFS(Gastos!$N:$N,Gastos!$O:$O,'ESCENARIO 1'!DQ$1) -> 0 | DR3: =SUMIFS(Gastos!$P:$P,Gastos!$Q:$Q,'ESCENARIO 1'!DR$1) -> 0 | DS3: =SUMIFS(Gastos!$P:$P,Gastos!$Q:$Q,'ESCENARIO 1'!DS$1) -> 1107100000 | DT3: =SUMIFS(Gastos!$P:$P,Gastos!$Q:$Q,'ESCENARIO 1'!DT$1) -> 0 | DU3: =SUMIFS(Gastos!$P:$P,Gastos!$Q:$Q,'ESCENARIO 1'!DU$1) -> 0 | DV3: =SUMIFS(Gastos!$P:$P,Gastos!$Q:$Q,'ESCENARIO 1'!DV$1) -> 0 | DW3: =SUMIFS(Gastos!$P:$P,Gastos!$Q:$Q,'ESCENARIO 1'!DW$1) -> 0 | DX3: =SUMIFS(Gastos!$P:$P,Gastos!$Q:$Q,'ESCENARIO 1'!DX$1) -> 0 | DY3: =SUMIFS(Gastos!$P:$P,Gastos!$Q:$Q,'ESCENARIO 1'!DY$1) -> 0 | ... EU3: =SUMIFS(Gastos!$P:$P,Gastos!$Q:$Q,'ESCENARIO 1'!EU$1) -> 2.8164597e+10 | EV3: =SUMIFS(Gastos!$R:$R,Gastos!$S:$S,'ESCENARIO 1'!EV$1) -> 0 | EW3: =SUMIFS(Gastos!$R:$R,Gastos!$S:$S,'ESCENARIO 1'!EW$1) -> 0 | EX3: =SUMIFS(Gastos!$R:$R,Gastos!$S:$S,'ESCENARIO 1'!EX$1) -> 0 | EY3: =SUMIFS(Gastos!$R:$R,Gastos!$S:$S,'ESCENARIO 1'!EY$1) -> 0 | EZ3: =SUMIFS(Gastos!$R:$R,Gastos!$S:$S,'ESCENARIO 1'!EZ$1) -> 0 | FA3: =SUMIFS(Gastos!$R:$R,Gastos!$S:$S,'ESCENARIO 1'!FA$1) -> 0 | FB3: =SUMIFS(Gastos!$R:$R,Gastos!$S:$S,'ESCENARIO 1'!FB$1) -> 1107100000 | FC3: =SUMIFS(Gastos!$R:$R,Gastos!$S:$S,'ESCENARIO 1'!FC$1) -> 0 | ... FZ3: =SUMIFS(Gastos!$R:$R,Gastos!$S:$S,'ESCENARIO 1'!FZ$1) -> 2.4685649e+10 | GA3: =SUMIFS(Gastos!$T:$T,Gastos!$U:$U,'ESCENARIO 1'!GA$1) -> 0 | GB3: =SUMIFS(Gastos!$T:$T,Gastos!$U:$U,'ESCENARIO 1'!GB$1) -> 0 | GC3: =SUMIFS(Gastos!$T:$T,Gastos!$U:$U,'ESCENARIO 1'!GC$1) -> 0 | GD3: =SUMIFS(Gastos!$T:$T,Gastos!$U:$U,'ESCENARIO 1'!GD$1) -> 1107100000 | GE3: =SUMIFS(Gastos!$T:$T,Gastos!$U:$U,'ESCENARIO 1'!GE$1) -> 0 | GF3: =SUMIFS(Gastos!$T:$T,Gastos!$U:$U,'ESCENARIO 1'!GF$1) -> 0 | GG3: =SUMIFS(Gastos!$T:$T,Gastos!$U:$U,'ESCENARIO 1'!GG$1) -> 0 | GH3: =SUMIFS(Gastos!$T:$T,Gastos!$U:$U,'ESCENARIO 1'!GH$1) -> 0 | ... HE3: =SUMIFS(Gastos!$T:$T,Gastos!$U:$U,'ESCENARIO 1'!HE$1) -> 2.1782913e+10 | HF3: =SUMIFS(Gastos!$V:$V,Gastos!$W:$W,'ESCENARIO 1'!HF$1) -> 1107100000 | HG3: =SUMIFS(Gastos!$V:$V,Gastos!$W:$W,'ESCENARIO 1'!HG$1) -> 0 | HH3: =SUMIFS(Gastos!$V:$V,Gastos!$W:$W,'ESCENARIO 1'!HH$1) -> 0 | HI3: =SUMIFS(Gastos!$V:$V,Gastos!$W:$W,'ESCENARIO 1'!HI$1) -> 0 | HJ3: =SUMIFS(Gastos!$V:$V,Gastos!$W:$W,'ESCENARIO 1'!HJ$1) -> 0 | HK3: =SUMIFS(Gastos!$V:$V,Gastos!$W:$W,'ESCENARIO 1'!HK$1) -> 0 | HL3: =SUMIFS(Gastos!$V:$V,Gastos!$W:$W,'ESCENARIO 1'!HL$1) -> 0 | HM3: =SUMIFS(Gastos!$V:$V,Gastos!$W:$W,'ESCENARIO 1'!HM$1) -> 1102000000 | ... II3: =SUMIFS(Gastos!$V:$V,Gastos!$W:$W,'ESCENARIO 1'!II$1) -> 2.116373e+10 | IJ3: =SUMIFS(Gastos!$X:$X,Gastos!$Y:$Y,'ESCENARIO 1'!IJ$1) -> 0 | IK3: =SUMIFS(Gastos!$X:$X,Gastos!$Y:$Y,'ESCENARIO 1'!IK$1) -> 0 | IL3: =SUMIFS(Gastos!$X:$X,Gastos!$Y:$Y,'ESCENARIO 1'!IL$1) -> 0 | IM3: =SUMIFS(Gastos!$X:$X,Gastos!$Y:$Y,'ESCENARIO 1'!IM$1) -> 0 | IN3: =SUMIFS(Gastos!$X:$X,Gastos!$Y:$Y,'ESCENARIO 1'!IN$1) -> 0 | IO3: =SUMIFS(Gastos!$X:$X,Gastos!$Y:$Y,'ESCENARIO 1'!IO$1) -> 1107100000 | IP3: =SUMIFS(Gastos!$X:$X,Gastos!$Y:$Y,'ESCENARIO 1'!IP$1) -> 0 | IQ3: =SUMIFS(Gastos!$X:$X,Gastos!$Y:$Y,'ESCENARIO 1'!IQ$1) -> 0 | ... JN3: =SUMIFS(Gastos!$X:$X,Gastos!$Y:$Y,'ESCENARIO 1'!JN$1) -> 0 | JO3: =SUMIFS(Gastos!$Z:$Z,Gastos!$AA:$AA,'ESCENARIO 1'!JO$1) -> 0 | JP3: =SUMIFS(Gastos!$Z:$Z,Gastos!$AA:$AA,'ESCENARIO 1'!JP$1) -> 0 | JQ3: =SUMIFS(Gastos!$Z:$Z,Gastos!$AA:$AA,'ESCENARIO 1'!JQ$1) -> 1107100000 | JR3: =SUMIFS(Gastos!$Z:$Z,Gastos!$AA:$AA,'ESCENARIO 1'!JR$1) -> 0 | JS3: =SUMIFS(Gastos!$Z:$Z,Gastos!$AA:$AA,'ESCENARIO 1'!JS$1) -> 0 | JT3: =SUMIFS(Gastos!$Z:$Z,Gastos!$AA:$AA,'ESCENARIO 1'!JT$1) -> 0 | JU3: =SUMIFS(Gastos!$Z:$Z,Gastos!$AA:$AA,'ESCENARIO 1'!JU$1) -> 0 | JV3: =SUMIFS(Gastos!$Z:$Z,Gastos!$AA:$AA,'ESCENARIO 1'!JV$1) -> 0 | ... KR3: =SUMIFS(Gastos!$Z:$Z,Gastos!$AA:$AA,'ESCENARIO 1'!KR$1) -> 2.0549133e+10 | KS3: =SUMIFS(Gastos!$AB:$AB,Gastos!$AC:$AC,'ESCENARIO 1'!KS$1) -> 1107100000 | KT3: =SUMIFS(Gastos!$AB:$AB,Gastos!$AC:$AC,'ESCENARIO 1'!KT$1) -> 0 | KU3: =SUMIFS(Gastos!$AB:$AB,Gastos!$AC:$AC,'ESCENARIO 1'!KU$1) -> 0 | KV3: =SUMIFS(Gastos!$AB:$AB,Gastos!$AC:$AC,'ESCENARIO 1'!KV$1) -> 0 | KW3: =SUMIFS(Gastos!$AB:$AB,Gastos!$AC:$AC,'ESCENARIO 1'!KW$1) -> 0 | KX3: =SUMIFS(Gastos!$AB:$AB,Gastos!$AC:$AC,'ESCENARIO 1'!KX$1) -> 0 | KY3: =SUMIFS(Gastos!$AB:$AB,Gastos!$AC:$AC,'ESCENARIO 1'!KY$1) -> 0 | KZ3: =SUMIFS(Gastos!$AB:$AB,Gastos!$AC:$AC,'ESCENARIO 1'!KZ$1) -> 0 | ... LW3: =SUMIFS(Gastos!$AB:$AB,Gastos!$AC:$AC,'ESCENARIO 1'!LW$1) -> 0 | LX3: =SUM(ESCENARIO[[#This Row],[01-mar]:[31-dic]]) -> 3.4402217e+11
A4: INGRESOS FINANCIEROS PROYECTADOS | B4: =SUMIFS('INGRESOSXDIA-HABIL'!$D:$D,'INGRESOSXDIA-HABIL'!$C:$C,ESCENARIO[[#Headers],[01-feb]]) -> 0 | C4: =SUMIFS('INGRESOSXDIA-HABIL'!$D:$D,'INGRESOSXDIA-HABIL'!$C:$C,ESCENARIO[[#Headers],[02-feb]]) -> 6.3994528e+08 | D4: =SUMIFS('INGRESOSXDIA-HABIL'!$D:$D,'INGRESOSXDIA-HABIL'!$C:$C,ESCENARIO[[#Headers],[03-feb]]) -> 8.7302777e+08 | E4: =SUMIFS('INGRESOSXDIA-HABIL'!$D:$D,'INGRESOSXDIA-HABIL'!$C:$C,ESCENARIO[[#Headers],[04-feb]]) -> 4.9731141e+08 | F4: =SUMIFS('INGRESOSXDIA-HABIL'!$D:$D,'INGRESOSXDIA-HABIL'!$C:$C,ESCENARIO[[#Headers],[05-feb]]) -> 6.2814917e+08 | G4: =SUMIFS('INGRESOSXDIA-HABIL'!$D:$D,'INGRESOSXDIA-HABIL'!$C:$C,ESCENARIO[[#Headers],[06-feb]]) -> 8.1579303e+08 | H4: =SUMIFS('INGRESOSXDIA-HABIL'!$D:$D,'INGRESOSXDIA-HABIL'!$C:$C,ESCENARIO[[#Headers],[07-feb]]) -> 0 | I4: =SUMIFS('INGRESOSXDIA-HABIL'!$D:$D,'INGRESOSXDIA-HABIL'!$C:$C,ESCENARIO[[#Headers],[08-feb]]) -> 0 | J4: =SUMIFS('INGRESOSXDIA-HABIL'!$D:$D,'INGRESOSXDIA-HABIL'!$C:$C,ESCENARIO[[#Headers],[09-feb]]) -> 1.4233244e+09 | K4: =SUMIFS('INGRESOSXDIA-HABIL'!$D:$D,'INGRESOSXDIA-HABIL'!$C:$C,ESCENARIO[[#Headers],[10-feb]]) -> 7.2399112e+09 | L4: =SUMIFS('INGRESOSXDIA-HABIL'!$D:$D,'INGRESOSXDIA-HABIL'!$C:$C,ESCENARIO[[#Headers],[11-feb]]) -> 1.4022844e+09 | M4: =SUMIFS('INGRESOSXDIA-HABIL'!$D:$D,'INGRESOSXDIA-HABIL'!$C:$C,ESCENARIO[[#Headers],[12-feb]]) -> 9.4060295e+08 | N4: =SUMIFS('INGRESOSXDIA-HABIL'!$D:$D,'INGRESOSXDIA-HABIL'!$C:$C,ESCENARIO[[#Headers],[13-feb]]) -> 2.6451394e+09 | O4: =SUMIFS('INGRESOSXDIA-HABIL'!$D:$D,'INGRESOSXDIA-HABIL'!$C:$C,ESCENARIO[[#Headers],[14-feb]]) -> 0 | P4: =SUMIFS('INGRESOSXDIA-HABIL'!$D:$D,'INGRESOSXDIA-HABIL'!$C:$C,ESCENARIO[[#Headers],[15-feb]]) -> 0 | Q4: =SUMIFS('INGRESOSXDIA-HABIL'!$D:$D,'INGRESOSXDIA-HABIL'!$C:$C,ESCENARIO[[#Headers],[16-feb]]) -> 2.4180253e+09 | R4: =SUMIFS('INGRESOSXDIA-HABIL'!$D:$D,'INGRESOSXDIA-HABIL'!$C:$C,ESCENARIO[[#Headers],[17-feb]]) -> 1.2890997e+09 | S4: =SUMIFS('INGRESOSXDIA-HABIL'!$D:$D,'INGRESOSXDIA-HABIL'!$C:$C,ESCENARIO[[#Headers],[18-feb]]) -> 1.5886214e+09 | T4: =SUMIFS('INGRESOSXDIA-HABIL'!$D:$D,'INGRESOSXDIA-HABIL'!$C:$C,ESCENARIO[[#Headers],[19-feb]]) -> 2.5939073e+09 | U4: =SUMIFS('INGRESOSXDIA-HABIL'!$D:$D,'INGRESOSXDIA-HABIL'!$C:$C,ESCENARIO[[#Headers],[20-feb]]) -> 2.6878119e+09 | V4: =SUMIFS('INGRESOSXDIA-HABIL'!$D:$D,'INGRESOSXDIA-HABIL'!$C:$C,ESCENARIO[[#Headers],[21-feb]]) -> 0 | W4: =SUMIFS('INGRESOSXDIA-HABIL'!$D:$D,'INGRESOSXDIA-HABIL'!$C:$C,ESCENARIO[[#Headers],[22-feb]]) -> 0 | X4: =SUMIFS('INGRESOSXDIA-HABIL'!$D:$D,'INGRESOSXDIA-HABIL'!$C:$C,ESCENARIO[[#Headers],[23-feb]]) -> 1.5125643e+09 | Y4: =SUMIFS('INGRESOSXDIA-HABIL'!$D:$D,'INGRESOSXDIA-HABIL'!$C:$C,ESCENARIO[[#Headers],[24-feb]]) -> 2.8732619e+09 | Z4: =SUMIFS('INGRESOSXDIA-HABIL'!$D:$D,'INGRESOSXDIA-HABIL'!$C:$C,ESCENARIO[[#Headers],[25-feb]]) -> 1.1742255e+09 | AA4: =SUMIFS('INGRESOSXDIA-HABIL'!$D:$D,'INGRESOSXDIA-HABIL'!$C:$C,ESCENARIO[[#Headers],[26-feb]]) -> 1.6219583e+09 | AB4: =SUMIFS('INGRESOSXDIA-HABIL'!$D:$D,'INGRESOSXDIA-HABIL'!$C:$C,ESCENARIO[[#Headers],[27-feb]]) -> 5.4434981e+08 | AC4: =SUMIFS('INGRESOSXDIA-HABIL'!$D:$D,'INGRESOSXDIA-HABIL'!$C:$C,ESCENARIO[[#Headers],[28-feb]]) -> 1.0930054e+09 | AD4: =SUMIFS('INGRESOSXDIA-HABIL'!$F$4:$F$25,'INGRESOSXDIA-HABIL'!$E$4:$E$25,ESCENARIO[[#Headers],[01-mar]]) -> 0 | AE4: =SUMIFS('INGRESOSXDIA-HABIL'!$F$4:$F$25,'INGRESOSXDIA-HABIL'!$E$4:$E$25,ESCENARIO[[#Headers],[02-mar]]) -> 6.5203271e+08 | AF4: =SUMIFS('INGRESOSXDIA-HABIL'!$F$4:$F$25,'INGRESOSXDIA-HABIL'!$E$4:$E$25,ESCENARIO[[#Headers],[03-mar]]) -> 8.8951772e+08 | AG4: =SUMIFS('INGRESOSXDIA-HABIL'!$F$4:$F$25,'INGRESOSXDIA-HABIL'!$E$4:$E$25,ESCENARIO[[#Headers],[04-mar]]) -> 5.0670475e+08 | AH4: =SUMIFS('INGRESOSXDIA-HABIL'!$F$4:$F$25,'INGRESOSXDIA-HABIL'!$E$4:$E$25,ESCENARIO[[#Headers],[05-mar]]) -> 6.400138e+08 | AI4: =SUMIFS('INGRESOSXDIA-HABIL'!$F$4:$F$25,'INGRESOSXDIA-HABIL'!$E$4:$E$25,ESCENARIO[[#Headers],[06-mar]]) -> 8.3120192e+08 | AJ4: =SUMIFS('INGRESOSXDIA-HABIL'!$F$4:$F$25,'INGRESOSXDIA-HABIL'!$E$4:$E$25,ESCENARIO[[#Headers],[07-mar]]) -> 0 | AK4: =SUMIFS('INGRESOSXDIA-HABIL'!$F$4:$F$25,'INGRESOSXDIA-HABIL'!$E$4:$E$25,ESCENARIO[[#Headers],[08-mar]]) -> 0 | AL4: =SUMIFS('INGRESOSXDIA-HABIL'!$F$4:$F$25,'INGRESOSXDIA-HABIL'!$E$4:$E$25,ESCENARIO[[#Headers],[09-mar]]) -> 1.4502085e+09 | AM4: =SUMIFS('INGRESOSXDIA-HABIL'!$F$4:$F$25,'INGRESOSXDIA-HABIL'!$E$4:$E$25,ESCENARIO[[#Headers],[10-mar]]) -> 7.3766604e+09 | AN4: =SUMIFS('INGRESOSXDIA-HABIL'!$F$4:$F$25,'INGRESOSXDIA-HABIL'!$E$4:$E$25,ESCENARIO[[#Headers],[11-mar]]) -> 1.428771e+09 | AO4: =SUMIFS('INGRESOSXDIA-HABIL'!$F$4:$F$25,'INGRESOSXDIA-HABIL'!$E$4:$E$25,ESCENARIO[[#Headers],[12-mar]]) -> 9.5836928e+08 | AP4: =SUMIFS('INGRESOSXDIA-HABIL'!$F$4:$F$25,'INGRESOSXDIA-HABIL'!$E$4:$E$25,ESCENARIO[[#Headers],[13-mar]]) -> 2.6951014e+09 | AQ4: =SUMIFS('INGRESOSXDIA-HABIL'!$F$4:$F$25,'INGRESOSXDIA-HABIL'!$E$4:$E$25,ESCENARIO[[#Headers],[14-mar]]) -> 0 | AR4: =SUMIFS('INGRESOSXDIA-HABIL'!$F$4:$F$25,'INGRESOSXDIA-HABIL'!$E$4:$E$25,ESCENARIO[[#Headers],[15-mar]]) -> 0 | AS4: =SUMIFS('INGRESOSXDIA-HABIL'!$F$4:$F$25,'INGRESOSXDIA-HABIL'!$E$4:$E$25,ESCENARIO[[#Headers],[16-mar]]) -> 2.4636976e+09 | AT4: =SUMIFS('INGRESOSXDIA-HABIL'!$F$4:$F$25,'INGRESOSXDIA-HABIL'!$E$4:$E$25,ESCENARIO[[#Headers],[17-mar]]) -> 1.3134485e+09 | AU4: =SUMIFS('INGRESOSXDIA-HABIL'!$F$4:$F$25,'INGRESOSXDIA-HABIL'!$E$4:$E$25,ESCENARIO[[#Headers],[18-mar]]) -> 1.6186277e+09 | AV4: =SUMIFS('INGRESOSXDIA-HABIL'!$F$4:$F$25,'INGRESOSXDIA-HABIL'!$E$4:$E$25,ESCENARIO[[#Headers],[19-mar]]) -> 2.6429016e+09 | AW4: =SUMIFS('INGRESOSXDIA-HABIL'!$F$4:$F$25,'INGRESOSXDIA-HABIL'!$E$4:$E$25,ESCENARIO[[#Headers],[20-mar]]) -> 2.7385799e+09 | AX4: =SUMIFS('INGRESOSXDIA-HABIL'!$F$4:$F$25,'INGRESOSXDIA-HABIL'!$E$4:$E$25,ESCENARIO[[#Headers],[21-mar]]) -> 1.5411339e+09 | AY4: =SUMIFS('INGRESOSXDIA-HABIL'!$F$4:$F$25,'INGRESOSXDIA-HABIL'!$E$4:$E$25,ESCENARIO[[#Headers],[22-mar]]) -> 2.9275327e+09 | AZ4: =SUMIFS('INGRESOSXDIA-HABIL'!$F$4:$F$25,'INGRESOSXDIA-HABIL'!$E$4:$E$25,ESCENARIO[[#Headers],[23-mar]]) -> 0 | BA4: =SUMIFS('INGRESOSXDIA-HABIL'!$F$4:$F$25,'INGRESOSXDIA-HABIL'!$E$4:$E$25,ESCENARIO[[#Headers],[24-mar]]) -> 0 | BB4: =SUMIFS('INGRESOSXDIA-HABIL'!$F$4:$F$25,'INGRESOSXDIA-HABIL'!$E$4:$E$25,ESCENARIO[[#Headers],[25-mar]]) -> 1.1964045e+09 | BC4: =SUMIFS('INGRESOSXDIA-HABIL'!$F$4:$F$25,'INGRESOSXDIA-HABIL'!$E$4:$E$25,ESCENARIO[[#Headers],[26-mar]]) -> 1.6525942e+09 | BD4: =SUMIFS('INGRESOSXDIA-HABIL'!$F$4:$F$25,'INGRESOSXDIA-HABIL'!$E$4:$E$25,ESCENARIO[[#Headers],[27-mar]]) -> 5.5463161e+08 | BE4: =SUMIFS('INGRESOSXDIA-HABIL'!$F$4:$F$25,'INGRESOSXDIA-HABIL'!$E$4:$E$25,ESCENARIO[[#Headers],[28-mar]]) -> 0 | BF4: =SUMIFS('INGRESOSXDIA-HABIL'!$F$4:$F$25,'INGRESOSXDIA-HABIL'!$E$4:$E$25,ESCENARIO[[#Headers],[29-mar]]) -> 0 | BG4: =SUMIFS('INGRESOSXDIA-HABIL'!$F$4:$F$25,'INGRESOSXDIA-HABIL'!$E$4:$E$25,ESCENARIO[[#Headers],[30-mar]]) -> 1.1136504e+09 | BH4: =SUMIFS('INGRESOSXDIA-HABIL'!$F$4:$F$25,'INGRESOSXDIA-HABIL'!$E$4:$E$25,ESCENARIO[[#Headers],[31-mar]]) -> 0 | BI4: =SUMIFS('INGRESOSXDIA-HABIL'!$H$4:$H$25,'INGRESOSXDIA-HABIL'!$G$4:$G$25,ESCENARIO[[#Headers],[01-abr]]) -> 6.6195686e+08 | BJ4: =SUMIFS('INGRESOSXDIA-HABIL'!$H$4:$H$25,'INGRESOSXDIA-HABIL'!$G$4:$G$25,ESCENARIO[[#Headers],[02-abr]]) -> 0 | BK4: =SUMIFS('INGRESOSXDIA-HABIL'!$H$4:$H$25,'INGRESOSXDIA-HABIL'!$G$4:$G$25,ESCENARIO[[#Headers],[03-abr]]) -> 0 | BL4: =SUMIFS('INGRESOSXDIA-HABIL'!$H$4:$H$25,'INGRESOSXDIA-HABIL'!$G$4:$G$25,ESCENARIO[[#Headers],[04-abr]]) -> 0 | BM4: =SUMIFS('INGRESOSXDIA-HABIL'!$H$4:$H$25,'INGRESOSXDIA-HABIL'!$G$4:$G$25,ESCENARIO[[#Headers],[05-abr]]) -> 0 | BN4: =SUMIFS('INGRESOSXDIA-HABIL'!$H$4:$H$25,'INGRESOSXDIA-HABIL'!$G$4:$G$25,ESCENARIO[[#Headers],[06-abr]]) -> 9.0305647e+08 | BO4: =SUMIFS('INGRESOSXDIA-HABIL'!$H$4:$H$25,'INGRESOSXDIA-HABIL'!$G$4:$G$25,ESCENARIO[[#Headers],[07-abr]]) -> 5.1441696e+08 | BP4: =SUMIFS('INGRESOSXDIA-HABIL'!$H$4:$H$25,'INGRESOSXDIA-HABIL'!$G$4:$G$25,ESCENARIO[[#Headers],[08-abr]]) -> 6.4975502e+08 | BQ4: =SUMIFS('INGRESOSXDIA-HABIL'!$H$4:$H$25,'INGRESOSXDIA-HABIL'!$G$4:$G$25,ESCENARIO[[#Headers],[09-abr]]) -> 8.4385308e+08 | BR4: =SUMIFS('INGRESOSXDIA-HABIL'!$H$4:$H$25,'INGRESOSXDIA-HABIL'!$G$4:$G$25,ESCENARIO[[#Headers],[10-abr]]) -> 1.4722811e+09 | BS4: =SUMIFS('INGRESOSXDIA-HABIL'!$H$4:$H$25,'INGRESOSXDIA-HABIL'!$G$4:$G$25,ESCENARIO[[#Headers],[11-abr]]) -> 0 | BT4: =SUMIFS('INGRESOSXDIA-HABIL'!$H$4:$H$25,'INGRESOSXDIA-HABIL'!$G$4:$G$25,ESCENARIO[[#Headers],[12-abr]]) -> 0 | BU4: =SUMIFS('INGRESOSXDIA-HABIL'!$H$4:$H$25,'INGRESOSXDIA-HABIL'!$G$4:$G$25,ESCENARIO[[#Headers],[13-abr]]) -> 7.4889355e+09 | BV4: =SUMIFS('INGRESOSXDIA-HABIL'!$H$4:$H$25,'INGRESOSXDIA-HABIL'!$G$4:$G$25,ESCENARIO[[#Headers],[14-abr]]) -> 1.4505174e+09 | BW4: =SUMIFS('INGRESOSXDIA-HABIL'!$H$4:$H$25,'INGRESOSXDIA-HABIL'!$G$4:$G$25,ESCENARIO[[#Headers],[15-abr]]) -> 9.7295596e+08 | BX4: =SUMIFS('INGRESOSXDIA-HABIL'!$H$4:$H$25,'INGRESOSXDIA-HABIL'!$G$4:$G$25,ESCENARIO[[#Headers],[16-abr]]) -> 2.7361217e+09 | BY4: =SUMIFS('INGRESOSXDIA-HABIL'!$H$4:$H$25,'INGRESOSXDIA-HABIL'!$G$4:$G$25,ESCENARIO[[#Headers],[17-abr]]) -> 2.5011958e+09 | BZ4: =SUMIFS('INGRESOSXDIA-HABIL'!$H$4:$H$25,'INGRESOSXDIA-HABIL'!$G$4:$G$25,ESCENARIO[[#Headers],[18-abr]]) -> 0 | CA4: =SUMIFS('INGRESOSXDIA-HABIL'!$H$4:$H$25,'INGRESOSXDIA-HABIL'!$G$4:$G$25,ESCENARIO[[#Headers],[19-abr]]) -> 0 | CB4: =SUMIFS('INGRESOSXDIA-HABIL'!$H$4:$H$25,'INGRESOSXDIA-HABIL'!$G$4:$G$25,ESCENARIO[[#Headers],[20-abr]]) -> 1.3334396e+09 | CC4: =SUMIFS('INGRESOSXDIA-HABIL'!$H$4:$H$25,'INGRESOSXDIA-HABIL'!$G$4:$G$25,ESCENARIO[[#Headers],[21-abr]]) -> 1.6432637e+09 | CD4: =SUMIFS('INGRESOSXDIA-HABIL'!$H$4:$H$25,'INGRESOSXDIA-HABIL'!$G$4:$G$25,ESCENARIO[[#Headers],[22-abr]]) -> 2.6831274e+09 | CE4: =SUMIFS('INGRESOSXDIA-HABIL'!$H$4:$H$25,'INGRESOSXDIA-HABIL'!$G$4:$G$25,ESCENARIO[[#Headers],[23-abr]]) -> 2.7802619e+09 | CF4: =SUMIFS('INGRESOSXDIA-HABIL'!$H$4:$H$25,'INGRESOSXDIA-HABIL'!$G$4:$G$25,ESCENARIO[[#Headers],[24-abr]]) -> 1.5645905e+09 | CG4: =SUMIFS('INGRESOSXDIA-HABIL'!$H$4:$H$25,'INGRESOSXDIA-HABIL'!$G$4:$G$25,ESCENARIO[[#Headers],[25-abr]]) -> 0 | CH4: =SUMIFS('INGRESOSXDIA-HABIL'!$H$4:$H$25,'INGRESOSXDIA-HABIL'!$G$4:$G$25,ESCENARIO[[#Headers],[26-abr]]) -> 0 | CI4: =SUMIFS('INGRESOSXDIA-HABIL'!$H$4:$H$25,'INGRESOSXDIA-HABIL'!$G$4:$G$25,ESCENARIO[[#Headers],[27-abr]]) -> 2.9720907e+09 | CJ4: =SUMIFS('INGRESOSXDIA-HABIL'!$H$4:$H$25,'INGRESOSXDIA-HABIL'!$G$4:$G$25,ESCENARIO[[#Headers],[28-abr]]) -> 1.2146142e+09 | CK4: =SUMIFS('INGRESOSXDIA-HABIL'!$H$4:$H$25,'INGRESOSXDIA-HABIL'!$G$4:$G$25,ESCENARIO[[#Headers],[29-abr]]) -> 1.6777472e+09 | CL4: =SUMIFS('INGRESOSXDIA-HABIL'!$H$4:$H$25,'INGRESOSXDIA-HABIL'!$G$4:$G$25,ESCENARIO[[#Headers],[30-abr]]) -> 1.6936738e+09 | CM4: =SUMIFS('INGRESOSXDIA-HABIL'!$J$4:$J$25,'INGRESOSXDIA-HABIL'!$I$4:$I$25,ESCENARIO[[#Headers],[01-may]]) -> 0 | CN4: =SUMIFS('INGRESOSXDIA-HABIL'!$J$4:$J$25,'INGRESOSXDIA-HABIL'!$I$4:$I$25,ESCENARIO[[#Headers],[02-may]]) -> 0 | CO4: =SUMIFS('INGRESOSXDIA-HABIL'!$J$4:$J$25,'INGRESOSXDIA-HABIL'!$I$4:$I$25,ESCENARIO[[#Headers],[03-may]]) -> 0 | CP4: =SUMIFS('INGRESOSXDIA-HABIL'!$J$4:$J$25,'INGRESOSXDIA-HABIL'!$I$4:$I$25,ESCENARIO[[#Headers],[04-may]]) -> 7.0108957e+08 | CQ4: =SUMIFS('INGRESOSXDIA-HABIL'!$J$4:$J$25,'INGRESOSXDIA-HABIL'!$I$4:$I$25,ESCENARIO[[#Headers],[05-may]]) -> 9.5644219e+08 | CR4: =SUMIFS('INGRESOSXDIA-HABIL'!$J$4:$J$25,'INGRESOSXDIA-HABIL'!$I$4:$I$25,ESCENARIO[[#Headers],[06-may]]) -> 5.4482759e+08 | CS4: =SUMIFS('INGRESOSXDIA-HABIL'!$J$4:$J$25,'INGRESOSXDIA-HABIL'!$I$4:$I$25,ESCENARIO[[#Headers],[07-may]]) -> 6.8816639e+08 | CT4: =SUMIFS('INGRESOSXDIA-HABIL'!$J$4:$J$25,'INGRESOSXDIA-HABIL'!$I$4:$I$25,ESCENARIO[[#Headers],[08-may]]) -> 8.9373889e+08 | CU4: =SUMIFS('INGRESOSXDIA-HABIL'!$J$4:$J$25,'INGRESOSXDIA-HABIL'!$I$4:$I$25,ESCENARIO[[#Headers],[09-may]]) -> 0 | CV4: =SUMIFS('INGRESOSXDIA-HABIL'!$J$4:$J$25,'INGRESOSXDIA-HABIL'!$I$4:$I$25,ESCENARIO[[#Headers],[10-may]]) -> 0 | CW4: =SUMIFS('INGRESOSXDIA-HABIL'!$J$4:$J$25,'INGRESOSXDIA-HABIL'!$I$4:$I$25,ESCENARIO[[#Headers],[11-may]]) -> 1.5593175e+09 | CX4: =SUMIFS('INGRESOSXDIA-HABIL'!$J$4:$J$25,'INGRESOSXDIA-HABIL'!$I$4:$I$25,ESCENARIO[[#Headers],[12-may]]) -> 7.9316567e+09 | CY4: =SUMIFS('INGRESOSXDIA-HABIL'!$J$4:$J$25,'INGRESOSXDIA-HABIL'!$I$4:$I$25,ESCENARIO[[#Headers],[13-may]]) -> 1.5362672e+09 | CZ4: =SUMIFS('INGRESOSXDIA-HABIL'!$J$4:$J$25,'INGRESOSXDIA-HABIL'!$I$4:$I$25,ESCENARIO[[#Headers],[14-may]]) -> 1.0304739e+09 | DA4: =SUMIFS('INGRESOSXDIA-HABIL'!$J$4:$J$25,'INGRESOSXDIA-HABIL'!$I$4:$I$25,ESCENARIO[[#Headers],[15-may]]) -> 2.8978722e+09 | DB4: =SUMIFS('INGRESOSXDIA-HABIL'!$J$4:$J$25,'INGRESOSXDIA-HABIL'!$I$4:$I$25,ESCENARIO[[#Headers],[16-may]]) -> 0 | DC4: =SUMIFS('INGRESOSXDIA-HABIL'!$J$4:$J$25,'INGRESOSXDIA-HABIL'!$I$4:$I$25,ESCENARIO[[#Headers],[17-may]]) -> 0 | DD4: =SUMIFS('INGRESOSXDIA-HABIL'!$J$4:$J$25,'INGRESOSXDIA-HABIL'!$I$4:$I$25,ESCENARIO[[#Headers],[18-may]]) -> 2.6490583e+09 | DE4: =SUMIFS('INGRESOSXDIA-HABIL'!$J$4:$J$25,'INGRESOSXDIA-HABIL'!$I$4:$I$25,ESCENARIO[[#Headers],[19-may]]) -> 1.4122682e+09 | DF4: =SUMIFS('INGRESOSXDIA-HABIL'!$J$4:$J$25,'INGRESOSXDIA-HABIL'!$I$4:$I$25,ESCENARIO[[#Headers],[20-may]]) -> 1.740408e+09 | DG4: =SUMIFS('INGRESOSXDIA-HABIL'!$J$4:$J$25,'INGRESOSXDIA-HABIL'!$I$4:$I$25,ESCENARIO[[#Headers],[21-may]]) -> 2.8417451e+09 | DH4: =SUMIFS('INGRESOSXDIA-HABIL'!$J$4:$J$25,'INGRESOSXDIA-HABIL'!$I$4:$I$25,ESCENARIO[[#Headers],[22-may]]) -> 2.9446219e+09 | DI4: =SUMIFS('INGRESOSXDIA-HABIL'!$J$4:$J$25,'INGRESOSXDIA-HABIL'!$I$4:$I$25,ESCENARIO[[#Headers],[23-may]]) -> 0 | DJ4: =SUMIFS('INGRESOSXDIA-HABIL'!$J$4:$J$25,'INGRESOSXDIA-HABIL'!$I$4:$I$25,ESCENARIO[[#Headers],[24-may]]) -> 0 | DK4: =SUMIFS('INGRESOSXDIA-HABIL'!$J$4:$J$25,'INGRESOSXDIA-HABIL'!$I$4:$I$25,ESCENARIO[[#Headers],[25-may]]) -> 0 | DL4: =SUMIFS('INGRESOSXDIA-HABIL'!$J$4:$J$25,'INGRESOSXDIA-HABIL'!$I$4:$I$25,ESCENARIO[[#Headers],[26-may]]) -> 1.6570839e+09 | DM4: =SUMIFS('INGRESOSXDIA-HABIL'!$J$4:$J$25,'INGRESOSXDIA-HABIL'!$I$4:$I$25,ESCENARIO[[#Headers],[27-may]]) -> 3.1477909e+09 | DN4: =SUMIFS('INGRESOSXDIA-HABIL'!$J$4:$J$25,'INGRESOSXDIA-HABIL'!$I$4:$I$25,ESCENARIO[[#Headers],[28-may]]) -> 1.2864182e+09 | DO4: =SUMIFS('INGRESOSXDIA-HABIL'!$J$4:$J$25,'INGRESOSXDIA-HABIL'!$I$4:$I$25,ESCENARIO[[#Headers],[29-may]]) -> 1.7769301e+09 | DP4: =SUMIFS('INGRESOSXDIA-HABIL'!$J$4:$J$25,'INGRESOSXDIA-HABIL'!$I$4:$I$25,ESCENARIO[[#Headers],[30-may]]) -> 5.9636032e+08 | DQ4: =SUMIFS('INGRESOSXDIA-HABIL'!$J$4:$J$25,'INGRESOSXDIA-HABIL'!$I$4:$I$25,ESCENARIO[[#Headers],[31-may]]) -> 1.1974379e+09 | DR4: =SUMIFS('INGRESOSXDIA-HABIL'!$L$4:$L$25,'INGRESOSXDIA-HABIL'!$K$4:$K$25,ESCENARIO[[#Headers],[01-jun]]) -> 0 | DS4: =SUMIFS('INGRESOSXDIA-HABIL'!$L$4:$L$25,'INGRESOSXDIA-HABIL'!$K$4:$K$25,ESCENARIO[[#Headers],[02-jun]]) -> 6.8187852e+08 | DT4: =SUMIFS('INGRESOSXDIA-HABIL'!$L$4:$L$25,'INGRESOSXDIA-HABIL'!$K$4:$K$25,ESCENARIO[[#Headers],[03-jun]]) -> 9.3023404e+08 | DU4: =SUMIFS('INGRESOSXDIA-HABIL'!$L$4:$L$25,'INGRESOSXDIA-HABIL'!$K$4:$K$25,ESCENARIO[[#Headers],[04-jun]]) -> 5.2989838e+08 | DV4: =SUMIFS('INGRESOSXDIA-HABIL'!$L$4:$L$25,'INGRESOSXDIA-HABIL'!$K$4:$K$25,ESCENARIO[[#Headers],[05-jun]]) -> 6.6930945e+08 | DW4: =SUMIFS('INGRESOSXDIA-HABIL'!$L$4:$L$25,'INGRESOSXDIA-HABIL'!$K$4:$K$25,ESCENARIO[[#Headers],[06-jun]]) -> 0 | DX4: =SUMIFS('INGRESOSXDIA-HABIL'!$L$4:$L$25,'INGRESOSXDIA-HABIL'!$K$4:$K$25,ESCENARIO[[#Headers],[07-jun]]) -> 0 | DY4: =SUMIFS('INGRESOSXDIA-HABIL'!$L$4:$L$25,'INGRESOSXDIA-HABIL'!$K$4:$K$25,ESCENARIO[[#Headers],[08-jun]]) -> 8.6924891e+08 | DZ4: =SUMIFS('INGRESOSXDIA-HABIL'!$L$4:$L$25,'INGRESOSXDIA-HABIL'!$K$4:$K$25,ESCENARIO[[#Headers],[09-jun]]) -> 1.5165895e+09 | EA4: =SUMIFS('INGRESOSXDIA-HABIL'!$L$4:$L$25,'INGRESOSXDIA-HABIL'!$K$4:$K$25,ESCENARIO[[#Headers],[10-jun]]) -> 7.7143157e+09 | EB4: =SUMIFS('INGRESOSXDIA-HABIL'!$L$4:$L$25,'INGRESOSXDIA-HABIL'!$K$4:$K$25,ESCENARIO[[#Headers],[11-jun]]) -> 1.4941709e+09 | EC4: =SUMIFS('INGRESOSXDIA-HABIL'!$L$4:$L$25,'INGRESOSXDIA-HABIL'!$K$4:$K$25,ESCENARIO[[#Headers],[12-jun]]) -> 1.0022372e+09 | ED4: =SUMIFS('INGRESOSXDIA-HABIL'!$L$4:$L$25,'INGRESOSXDIA-HABIL'!$K$4:$K$25,ESCENARIO[[#Headers],[13-jun]]) -> 0 | EE4: =SUMIFS('INGRESOSXDIA-HABIL'!$L$4:$L$25,'INGRESOSXDIA-HABIL'!$K$4:$K$25,ESCENARIO[[#Headers],[14-jun]]) -> 0 | EF4: =SUMIFS('INGRESOSXDIA-HABIL'!$L$4:$L$25,'INGRESOSXDIA-HABIL'!$K$4:$K$25,ESCENARIO[[#Headers],[15-jun]]) -> 0 | EG4: =SUMIFS('INGRESOSXDIA-HABIL'!$L$4:$L$25,'INGRESOSXDIA-HABIL'!$K$4:$K$25,ESCENARIO[[#Headers],[16-jun]]) -> 2.8184655e+09 | EH4: =SUMIFS('INGRESOSXDIA-HABIL'!$L$4:$L$25,'INGRESOSXDIA-HABIL'!$K$4:$K$25,ESCENARIO[[#Headers],[17-jun]]) -> 2.5764696e+09 | EI4: =SUMIFS('INGRESOSXDIA-HABIL'!$L$4:$L$25,'INGRESOSXDIA-HABIL'!$K$4:$K$25,ESCENARIO[[#Headers],[18-jun]]) -> 1.3735696e+09 | EJ4: =SUMIFS('INGRESOSXDIA-HABIL'!$L$4:$L$25,'INGRESOSXDIA-HABIL'!$K$4:$K$25,ESCENARIO[[#Headers],[19-jun]]) -> 1.6927179e+09 | EK4: =SUMIFS('INGRESOSXDIA-HABIL'!$L$4:$L$25,'INGRESOSXDIA-HABIL'!$K$4:$K$25,ESCENARIO[[#Headers],[20-jun]]) -> 0 | EL4: =SUMIFS('INGRESOSXDIA-HABIL'!$L$4:$L$25,'INGRESOSXDIA-HABIL'!$K$4:$K$25,ESCENARIO[[#Headers],[21-jun]]) -> 0 | EM4: =SUMIFS('INGRESOSXDIA-HABIL'!$L$4:$L$25,'INGRESOSXDIA-HABIL'!$K$4:$K$25,ESCENARIO[[#Headers],[22-jun]]) -> 2.7638764e+09 | EN4: =SUMIFS('INGRESOSXDIA-HABIL'!$L$4:$L$25,'INGRESOSXDIA-HABIL'!$K$4:$K$25,ESCENARIO[[#Headers],[23-jun]]) -> 2.8639342e+09 | EO4: =SUMIFS('INGRESOSXDIA-HABIL'!$L$4:$L$25,'INGRESOSXDIA-HABIL'!$K$4:$K$25,ESCENARIO[[#Headers],[24-jun]]) -> 1.611677e+09 | EP4: =SUMIFS('INGRESOSXDIA-HABIL'!$L$4:$L$25,'INGRESOSXDIA-HABIL'!$K$4:$K$25,ESCENARIO[[#Headers],[25-jun]]) -> 3.0615361e+09 | EQ4: =SUMIFS('INGRESOSXDIA-HABIL'!$L$4:$L$25,'INGRESOSXDIA-HABIL'!$K$4:$K$25,ESCENARIO[[#Headers],[26-jun]]) -> 1.2511681e+09 | ER4: =SUMIFS('INGRESOSXDIA-HABIL'!$L$4:$L$25,'INGRESOSXDIA-HABIL'!$K$4:$K$25,ESCENARIO[[#Headers],[27-jun]]) -> 0 | ES4: =SUMIFS('INGRESOSXDIA-HABIL'!$L$4:$L$25,'INGRESOSXDIA-HABIL'!$K$4:$K$25,ESCENARIO[[#Headers],[28-jun]]) -> 0 | ET4: =SUMIFS('INGRESOSXDIA-HABIL'!$L$4:$L$25,'INGRESOSXDIA-HABIL'!$K$4:$K$25,ESCENARIO[[#Headers],[29-jun]]) -> 1.7282392e+09 | EU4: =SUMIFS('INGRESOSXDIA-HABIL'!$L$4:$L$25,'INGRESOSXDIA-HABIL'!$K$4:$K$25,ESCENARIO[[#Headers],[30-jun]]) -> 1.744645e+09 | EV4: =SUMIFS('INGRESOSXDIA-HABIL'!$N$4:$N$25,'INGRESOSXDIA-HABIL'!$M$4:$M$25,ESCENARIO[[#Headers],[01-jul]]) -> 6.8415136e+08 | EW4: =SUMIFS('INGRESOSXDIA-HABIL'!$N$4:$N$25,'INGRESOSXDIA-HABIL'!$M$4:$M$25,ESCENARIO[[#Headers],[02-jul]]) -> 9.333347e+08 | EX4: =SUMIFS('INGRESOSXDIA-HABIL'!$N$4:$N$25,'INGRESOSXDIA-HABIL'!$M$4:$M$25,ESCENARIO[[#Headers],[03-jul]]) -> 5.3166465e+08 | EY4: =SUMIFS('INGRESOSXDIA-HABIL'!$N$4:$N$25,'INGRESOSXDIA-HABIL'!$M$4:$M$25,ESCENARIO[[#Headers],[04-jul]]) -> 0 | EZ4: =SUMIFS('INGRESOSXDIA-HABIL'!$N$4:$N$25,'INGRESOSXDIA-HABIL'!$M$4:$M$25,ESCENARIO[[#Headers],[05-jul]]) -> 0 | FA4: =SUMIFS('INGRESOSXDIA-HABIL'!$N$4:$N$25,'INGRESOSXDIA-HABIL'!$M$4:$M$25,ESCENARIO[[#Headers],[06-jul]]) -> 6.715404e+08 | FB4: =SUMIFS('INGRESOSXDIA-HABIL'!$N$4:$N$25,'INGRESOSXDIA-HABIL'!$M$4:$M$25,ESCENARIO[[#Headers],[07-jul]]) -> 8.721463e+08 | FC4: =SUMIFS('INGRESOSXDIA-HABIL'!$N$4:$N$25,'INGRESOSXDIA-HABIL'!$M$4:$M$25,ESCENARIO[[#Headers],[08-jul]]) -> 1.5216446e+09 | FD4: =SUMIFS('INGRESOSXDIA-HABIL'!$N$4:$N$25,'INGRESOSXDIA-HABIL'!$M$4:$M$25,ESCENARIO[[#Headers],[09-jul]]) -> 0 | FE4: =SUMIFS('INGRESOSXDIA-HABIL'!$N$4:$N$25,'INGRESOSXDIA-HABIL'!$M$4:$M$25,ESCENARIO[[#Headers],[10-jul]]) -> 0 | FF4: =SUMIFS('INGRESOSXDIA-HABIL'!$N$4:$N$25,'INGRESOSXDIA-HABIL'!$M$4:$M$25,ESCENARIO[[#Headers],[11-jul]]) -> 0 | FG4: =SUMIFS('INGRESOSXDIA-HABIL'!$N$4:$N$25,'INGRESOSXDIA-HABIL'!$M$4:$M$25,ESCENARIO[[#Headers],[12-jul]]) -> 0 | FH4: =SUMIFS('INGRESOSXDIA-HABIL'!$N$4:$N$25,'INGRESOSXDIA-HABIL'!$M$4:$M$25,ESCENARIO[[#Headers],[13-jul]]) -> 7.7400292e+09 | FI4: =SUMIFS('INGRESOSXDIA-HABIL'!$N$4:$N$25,'INGRESOSXDIA-HABIL'!$M$4:$M$25,ESCENARIO[[#Headers],[14-jul]]) -> 1.4991512e+09 | FJ4: =SUMIFS('INGRESOSXDIA-HABIL'!$N$4:$N$25,'INGRESOSXDIA-HABIL'!$M$4:$M$25,ESCENARIO[[#Headers],[15-jul]]) -> 1.0055778e+09 | FK4: =SUMIFS('INGRESOSXDIA-HABIL'!$N$4:$N$25,'INGRESOSXDIA-HABIL'!$M$4:$M$25,ESCENARIO[[#Headers],[16-jul]]) -> 2.8278601e+09 | FL4: =SUMIFS('INGRESOSXDIA-HABIL'!$N$4:$N$25,'INGRESOSXDIA-HABIL'!$M$4:$M$25,ESCENARIO[[#Headers],[17-jul]]) -> 2.5850575e+09 | FM4: =SUMIFS('INGRESOSXDIA-HABIL'!$N$4:$N$25,'INGRESOSXDIA-HABIL'!$M$4:$M$25,ESCENARIO[[#Headers],[18-jul]]) -> 0 | FN4: =SUMIFS('INGRESOSXDIA-HABIL'!$N$4:$N$25,'INGRESOSXDIA-HABIL'!$M$4:$M$25,ESCENARIO[[#Headers],[19-jul]]) -> 0 | FO4: =SUMIFS('INGRESOSXDIA-HABIL'!$N$4:$N$25,'INGRESOSXDIA-HABIL'!$M$4:$M$25,ESCENARIO[[#Headers],[20-jul]]) -> 1.378148e+09 | FP4: =SUMIFS('INGRESOSXDIA-HABIL'!$N$4:$N$25,'INGRESOSXDIA-HABIL'!$M$4:$M$25,ESCENARIO[[#Headers],[21-jul]]) -> 1.6983601e+09 | FQ4: =SUMIFS('INGRESOSXDIA-HABIL'!$N$4:$N$25,'INGRESOSXDIA-HABIL'!$M$4:$M$25,ESCENARIO[[#Headers],[22-jul]]) -> 2.773089e+09 | FR4: =SUMIFS('INGRESOSXDIA-HABIL'!$N$4:$N$25,'INGRESOSXDIA-HABIL'!$M$4:$M$25,ESCENARIO[[#Headers],[23-jul]]) -> 2.8734803e+09 | FS4: =SUMIFS('INGRESOSXDIA-HABIL'!$N$4:$N$25,'INGRESOSXDIA-HABIL'!$M$4:$M$25,ESCENARIO[[#Headers],[24-jul]]) -> 1.617049e+09 | FT4: =SUMIFS('INGRESOSXDIA-HABIL'!$N$4:$N$25,'INGRESOSXDIA-HABIL'!$M$4:$M$25,ESCENARIO[[#Headers],[25-jul]]) -> 0 | FU4: =SUMIFS('INGRESOSXDIA-HABIL'!$N$4:$N$25,'INGRESOSXDIA-HABIL'!$M$4:$M$25,ESCENARIO[[#Headers],[26-jul]]) -> 0 | FV4: =SUMIFS('INGRESOSXDIA-HABIL'!$N$4:$N$25,'INGRESOSXDIA-HABIL'!$M$4:$M$25,ESCENARIO[[#Headers],[27-jul]]) -> 3.0717408e+09 | FW4: =SUMIFS('INGRESOSXDIA-HABIL'!$N$4:$N$25,'INGRESOSXDIA-HABIL'!$M$4:$M$25,ESCENARIO[[#Headers],[28-jul]]) -> 1.2553385e+09 | FX4: =SUMIFS('INGRESOSXDIA-HABIL'!$N$4:$N$25,'INGRESOSXDIA-HABIL'!$M$4:$M$25,ESCENARIO[[#Headers],[29-jul]]) -> 1.7339997e+09 | FY4: =SUMIFS('INGRESOSXDIA-HABIL'!$N$4:$N$25,'INGRESOSXDIA-HABIL'!$M$4:$M$25,ESCENARIO[[#Headers],[30-jul]]) -> 5.8195235e+08 | FZ4: =SUMIFS('INGRESOSXDIA-HABIL'!$N$4:$N$25,'INGRESOSXDIA-HABIL'!$M$4:$M$25,ESCENARIO[[#Headers],[31-jul]]) -> 1.1685079e+09 | GA4: =SUMIFS('INGRESOSXDIA-HABIL'!$P$4:$P$25,'INGRESOSXDIA-HABIL'!$O$4:$O$25,ESCENARIO[[#Headers],[01-ago]]) -> 0 | GB4: =SUMIFS('INGRESOSXDIA-HABIL'!$P$4:$P$25,'INGRESOSXDIA-HABIL'!$O$4:$O$25,ESCENARIO[[#Headers],[02-ago]]) -> 0 | GC4: =SUMIFS('INGRESOSXDIA-HABIL'!$P$4:$P$25,'INGRESOSXDIA-HABIL'!$O$4:$O$25,ESCENARIO[[#Headers],[03-ago]]) -> 6.9230868e+08 | GD4: =SUMIFS('INGRESOSXDIA-HABIL'!$P$4:$P$25,'INGRESOSXDIA-HABIL'!$O$4:$O$25,ESCENARIO[[#Headers],[04-ago]]) -> 9.444631e+08 | GE4: =SUMIFS('INGRESOSXDIA-HABIL'!$P$4:$P$25,'INGRESOSXDIA-HABIL'!$O$4:$O$25,ESCENARIO[[#Headers],[05-ago]]) -> 5.3800383e+08 | GF4: =SUMIFS('INGRESOSXDIA-HABIL'!$P$4:$P$25,'INGRESOSXDIA-HABIL'!$O$4:$O$25,ESCENARIO[[#Headers],[06-ago]]) -> 6.7954736e+08 | GG4: =SUMIFS('INGRESOSXDIA-HABIL'!$P$4:$P$25,'INGRESOSXDIA-HABIL'!$O$4:$O$25,ESCENARIO[[#Headers],[07-ago]]) -> 8.8254514e+08 | GH4: =SUMIFS('INGRESOSXDIA-HABIL'!$P$4:$P$25,'INGRESOSXDIA-HABIL'!$O$4:$O$25,ESCENARIO[[#Headers],[08-ago]]) -> 0 | GI4: =SUMIFS('INGRESOSXDIA-HABIL'!$P$4:$P$25,'INGRESOSXDIA-HABIL'!$O$4:$O$25,ESCENARIO[[#Headers],[09-ago]]) -> 0 | GJ4: =SUMIFS('INGRESOSXDIA-HABIL'!$P$4:$P$25,'INGRESOSXDIA-HABIL'!$O$4:$O$25,ESCENARIO[[#Headers],[10-ago]]) -> 1.5397876e+09 | GK4: =SUMIFS('INGRESOSXDIA-HABIL'!$P$4:$P$25,'INGRESOSXDIA-HABIL'!$O$4:$O$25,ESCENARIO[[#Headers],[11-ago]]) -> 7.8323156e+09 | GL4: =SUMIFS('INGRESOSXDIA-HABIL'!$P$4:$P$25,'INGRESOSXDIA-HABIL'!$O$4:$O$25,ESCENARIO[[#Headers],[12-ago]]) -> 1.517026e+09 | GM4: =SUMIFS('INGRESOSXDIA-HABIL'!$P$4:$P$25,'INGRESOSXDIA-HABIL'!$O$4:$O$25,ESCENARIO[[#Headers],[13-ago]]) -> 1.0175676e+09 | GN4: =SUMIFS('INGRESOSXDIA-HABIL'!$P$4:$P$25,'INGRESOSXDIA-HABIL'!$O$4:$O$25,ESCENARIO[[#Headers],[14-ago]]) -> 2.8615774e+09 | GO4: =SUMIFS('INGRESOSXDIA-HABIL'!$P$4:$P$25,'INGRESOSXDIA-HABIL'!$O$4:$O$25,ESCENARIO[[#Headers],[15-ago]]) -> 0 | GP4: =SUMIFS('INGRESOSXDIA-HABIL'!$P$4:$P$25,'INGRESOSXDIA-HABIL'!$O$4:$O$25,ESCENARIO[[#Headers],[16-ago]]) -> 0 | GQ4: =SUMIFS('INGRESOSXDIA-HABIL'!$P$4:$P$25,'INGRESOSXDIA-HABIL'!$O$4:$O$25,ESCENARIO[[#Headers],[17-ago]]) -> 2.6158798e+09 | GR4: =SUMIFS('INGRESOSXDIA-HABIL'!$P$4:$P$25,'INGRESOSXDIA-HABIL'!$O$4:$O$25,ESCENARIO[[#Headers],[18-ago]]) -> 1.39458e+09 | GS4: =SUMIFS('INGRESOSXDIA-HABIL'!$P$4:$P$25,'INGRESOSXDIA-HABIL'!$O$4:$O$25,ESCENARIO[[#Headers],[19-ago]]) -> 1.7186101e+09 | GT4: =SUMIFS('INGRESOSXDIA-HABIL'!$P$4:$P$25,'INGRESOSXDIA-HABIL'!$O$4:$O$25,ESCENARIO[[#Headers],[20-ago]]) -> 2.8061533e+09 | GU4: =SUMIFS('INGRESOSXDIA-HABIL'!$P$4:$P$25,'INGRESOSXDIA-HABIL'!$O$4:$O$25,ESCENARIO[[#Headers],[21-ago]]) -> 2.9077416e+09 | GV4: =SUMIFS('INGRESOSXDIA-HABIL'!$P$4:$P$25,'INGRESOSXDIA-HABIL'!$O$4:$O$25,ESCENARIO[[#Headers],[22-ago]]) -> 0 | GW4: =SUMIFS('INGRESOSXDIA-HABIL'!$P$4:$P$25,'INGRESOSXDIA-HABIL'!$O$4:$O$25,ESCENARIO[[#Headers],[23-ago]]) -> 0 | GX4: =SUMIFS('INGRESOSXDIA-HABIL'!$P$4:$P$25,'INGRESOSXDIA-HABIL'!$O$4:$O$25,ESCENARIO[[#Headers],[24-ago]]) -> 1.6363296e+09 | GY4: =SUMIFS('INGRESOSXDIA-HABIL'!$P$4:$P$25,'INGRESOSXDIA-HABIL'!$O$4:$O$25,ESCENARIO[[#Headers],[25-ago]]) -> 3.108366e+09 | GZ4: =SUMIFS('INGRESOSXDIA-HABIL'!$P$4:$P$25,'INGRESOSXDIA-HABIL'!$O$4:$O$25,ESCENARIO[[#Headers],[26-ago]]) -> 1.2703062e+09 | HA4: =SUMIFS('INGRESOSXDIA-HABIL'!$P$4:$P$25,'INGRESOSXDIA-HABIL'!$O$4:$O$25,ESCENARIO[[#Headers],[27-ago]]) -> 1.7546747e+09 | HB4: =SUMIFS('INGRESOSXDIA-HABIL'!$P$4:$P$25,'INGRESOSXDIA-HABIL'!$O$4:$O$25,ESCENARIO[[#Headers],[28-ago]]) -> 5.8889113e+08 | HC4: =SUMIFS('INGRESOSXDIA-HABIL'!$P$4:$P$25,'INGRESOSXDIA-HABIL'!$O$4:$O$25,ESCENARIO[[#Headers],[29-ago]]) -> 0 | HD4: =SUMIFS('INGRESOSXDIA-HABIL'!$P$4:$P$25,'INGRESOSXDIA-HABIL'!$O$4:$O$25,ESCENARIO[[#Headers],[30-ago]]) -> 0 | HE4: =SUMIFS('INGRESOSXDIA-HABIL'!$P$4:$P$25,'INGRESOSXDIA-HABIL'!$O$4:$O$25,ESCENARIO[[#Headers],[31-ago]]) -> 1.1824404e+09 | HF4: =SUMIFS('INGRESOSXDIA-HABIL'!$R$4:$R$25,'INGRESOSXDIA-HABIL'!$Q$4:$Q$25,ESCENARIO[[#Headers],[01-sep]]) -> 0 | HG4: =SUMIFS('INGRESOSXDIA-HABIL'!$R$4:$R$25,'INGRESOSXDIA-HABIL'!$Q$4:$Q$25,ESCENARIO[[#Headers],[02-sep]]) -> 7.1543221e+08 | HH4: =SUMIFS('INGRESOSXDIA-HABIL'!$R$4:$R$25,'INGRESOSXDIA-HABIL'!$Q$4:$Q$25,ESCENARIO[[#Headers],[03-sep]]) -> 9.7600874e+08 | HI4: =SUMIFS('INGRESOSXDIA-HABIL'!$R$4:$R$25,'INGRESOSXDIA-HABIL'!$Q$4:$Q$25,ESCENARIO[[#Headers],[04-sep]]) -> 5.5597348e+08 | HJ4: =SUMIFS('INGRESOSXDIA-HABIL'!$R$4:$R$25,'INGRESOSXDIA-HABIL'!$Q$4:$Q$25,ESCENARIO[[#Headers],[05-sep]]) -> 0 | HK4: =SUMIFS('INGRESOSXDIA-HABIL'!$R$4:$R$25,'INGRESOSXDIA-HABIL'!$Q$4:$Q$25,ESCENARIO[[#Headers],[06-sep]]) -> 0 | HL4: =SUMIFS('INGRESOSXDIA-HABIL'!$R$4:$R$25,'INGRESOSXDIA-HABIL'!$Q$4:$Q$25,ESCENARIO[[#Headers],[07-sep]]) -> 7.0224465e+08 | HM4: =SUMIFS('INGRESOSXDIA-HABIL'!$R$4:$R$25,'INGRESOSXDIA-HABIL'!$Q$4:$Q$25,ESCENARIO[[#Headers],[08-sep]]) -> 9.1202268e+08 | HN4: =SUMIFS('INGRESOSXDIA-HABIL'!$R$4:$R$25,'INGRESOSXDIA-HABIL'!$Q$4:$Q$25,ESCENARIO[[#Headers],[09-sep]]) -> 1.5912175e+09 | HO4: =SUMIFS('INGRESOSXDIA-HABIL'!$R$4:$R$25,'INGRESOSXDIA-HABIL'!$Q$4:$Q$25,ESCENARIO[[#Headers],[10-sep]]) -> 8.0939197e+09 | HP4: =SUMIFS('INGRESOSXDIA-HABIL'!$R$4:$R$25,'INGRESOSXDIA-HABIL'!$Q$4:$Q$25,ESCENARIO[[#Headers],[11-sep]]) -> 1.5676956e+09 | HQ4: =SUMIFS('INGRESOSXDIA-HABIL'!$R$4:$R$25,'INGRESOSXDIA-HABIL'!$Q$4:$Q$25,ESCENARIO[[#Headers],[12-sep]]) -> 0 | HR4: =SUMIFS('INGRESOSXDIA-HABIL'!$R$4:$R$25,'INGRESOSXDIA-HABIL'!$Q$4:$Q$25,ESCENARIO[[#Headers],[13-sep]]) -> 0 | HS4: =SUMIFS('INGRESOSXDIA-HABIL'!$R$4:$R$25,'INGRESOSXDIA-HABIL'!$Q$4:$Q$25,ESCENARIO[[#Headers],[14-sep]]) -> 1.051555e+09 | HT4: =SUMIFS('INGRESOSXDIA-HABIL'!$R$4:$R$25,'INGRESOSXDIA-HABIL'!$Q$4:$Q$25,ESCENARIO[[#Headers],[15-sep]]) -> 2.9571558e+09 | HU4: =SUMIFS('INGRESOSXDIA-HABIL'!$R$4:$R$25,'INGRESOSXDIA-HABIL'!$Q$4:$Q$25,ESCENARIO[[#Headers],[16-sep]]) -> 2.7032518e+09 | HV4: =SUMIFS('INGRESOSXDIA-HABIL'!$R$4:$R$25,'INGRESOSXDIA-HABIL'!$Q$4:$Q$25,ESCENARIO[[#Headers],[17-sep]]) -> 1.4411599e+09 | HW4: =SUMIFS('INGRESOSXDIA-HABIL'!$R$4:$R$25,'INGRESOSXDIA-HABIL'!$Q$4:$Q$25,ESCENARIO[[#Headers],[18-sep]]) -> 1.7760127e+09 | HX4: =SUMIFS('INGRESOSXDIA-HABIL'!$R$4:$R$25,'INGRESOSXDIA-HABIL'!$Q$4:$Q$25,ESCENARIO[[#Headers],[19-sep]]) -> 0 | HY4: =SUMIFS('INGRESOSXDIA-HABIL'!$R$4:$R$25,'INGRESOSXDIA-HABIL'!$Q$4:$Q$25,ESCENARIO[[#Headers],[20-sep]]) -> 0 | HZ4: =SUMIFS('INGRESOSXDIA-HABIL'!$R$4:$R$25,'INGRESOSXDIA-HABIL'!$Q$4:$Q$25,ESCENARIO[[#Headers],[21-sep]]) -> 2.8998805e+09 | IA4: =SUMIFS('INGRESOSXDIA-HABIL'!$R$4:$R$25,'INGRESOSXDIA-HABIL'!$Q$4:$Q$25,ESCENARIO[[#Headers],[22-sep]]) -> 3.0048619e+09 | IB4: =SUMIFS('INGRESOSXDIA-HABIL'!$R$4:$R$25,'INGRESOSXDIA-HABIL'!$Q$4:$Q$25,ESCENARIO[[#Headers],[23-sep]]) -> 1.6909839e+09 | IC4: =SUMIFS('INGRESOSXDIA-HABIL'!$R$4:$R$25,'INGRESOSXDIA-HABIL'!$Q$4:$Q$25,ESCENARIO[[#Headers],[24-sep]]) -> 3.2121873e+09 | ID4: =SUMIFS('INGRESOSXDIA-HABIL'!$R$4:$R$25,'INGRESOSXDIA-HABIL'!$Q$4:$Q$25,ESCENARIO[[#Headers],[25-sep]]) -> 1.3127352e+09 | IE4: =SUMIFS('INGRESOSXDIA-HABIL'!$R$4:$R$25,'INGRESOSXDIA-HABIL'!$Q$4:$Q$25,ESCENARIO[[#Headers],[26-sep]]) -> 0 | IF4: =SUMIFS('INGRESOSXDIA-HABIL'!$R$4:$R$25,'INGRESOSXDIA-HABIL'!$Q$4:$Q$25,ESCENARIO[[#Headers],[27-sep]]) -> 0 | IG4: =SUMIFS('INGRESOSXDIA-HABIL'!$R$4:$R$25,'INGRESOSXDIA-HABIL'!$Q$4:$Q$25,ESCENARIO[[#Headers],[28-sep]]) -> 1.8132819e+09 | IH4: =SUMIFS('INGRESOSXDIA-HABIL'!$R$4:$R$25,'INGRESOSXDIA-HABIL'!$Q$4:$Q$25,ESCENARIO[[#Headers],[29-sep]]) -> 6.0856044e+08 | II4: =SUMIFS('INGRESOSXDIA-HABIL'!$R$4:$R$25,'INGRESOSXDIA-HABIL'!$Q$4:$Q$25,ESCENARIO[[#Headers],[30-sep]]) -> 1.2219346e+09 | IJ4: =SUMIFS('INGRESOSXDIA-HABIL'!$T$4:$T$25,'INGRESOSXDIA-HABIL'!$S$4:$S$25,ESCENARIO[[#Headers],[01-oct]]) -> 7.4531187e+08 | IK4: =SUMIFS('INGRESOSXDIA-HABIL'!$T$4:$T$25,'INGRESOSXDIA-HABIL'!$S$4:$S$25,ESCENARIO[[#Headers],[02-oct]]) -> 1.0167712e+09 | IL4: =SUMIFS('INGRESOSXDIA-HABIL'!$T$4:$T$25,'INGRESOSXDIA-HABIL'!$S$4:$S$25,ESCENARIO[[#Headers],[03-oct]]) -> 0 | IM4: =SUMIFS('INGRESOSXDIA-HABIL'!$T$4:$T$25,'INGRESOSXDIA-HABIL'!$S$4:$S$25,ESCENARIO[[#Headers],[04-oct]]) -> 0 | IN4: =SUMIFS('INGRESOSXDIA-HABIL'!$T$4:$T$25,'INGRESOSXDIA-HABIL'!$S$4:$S$25,ESCENARIO[[#Headers],[05-oct]]) -> 5.7919343e+08 | IO4: =SUMIFS('INGRESOSXDIA-HABIL'!$T$4:$T$25,'INGRESOSXDIA-HABIL'!$S$4:$S$25,ESCENARIO[[#Headers],[06-oct]]) -> 7.3157354e+08 | IP4: =SUMIFS('INGRESOSXDIA-HABIL'!$T$4:$T$25,'INGRESOSXDIA-HABIL'!$S$4:$S$25,ESCENARIO[[#Headers],[07-oct]]) -> 9.5011284e+08 | IQ4: =SUMIFS('INGRESOSXDIA-HABIL'!$T$4:$T$25,'INGRESOSXDIA-HABIL'!$S$4:$S$25,ESCENARIO[[#Headers],[08-oct]]) -> 1.6576738e+09 | IR4: =SUMIFS('INGRESOSXDIA-HABIL'!$T$4:$T$25,'INGRESOSXDIA-HABIL'!$S$4:$S$25,ESCENARIO[[#Headers],[09-oct]]) -> 8.4319581e+09 | IS4: =SUMIFS('INGRESOSXDIA-HABIL'!$T$4:$T$25,'INGRESOSXDIA-HABIL'!$S$4:$S$25,ESCENARIO[[#Headers],[10-oct]]) -> 0 | IT4: =SUMIFS('INGRESOSXDIA-HABIL'!$T$4:$T$25,'INGRESOSXDIA-HABIL'!$S$4:$S$25,ESCENARIO[[#Headers],[11-oct]]) -> 0 | IU4: =SUMIFS('INGRESOSXDIA-HABIL'!$T$4:$T$25,'INGRESOSXDIA-HABIL'!$S$4:$S$25,ESCENARIO[[#Headers],[12-oct]]) -> 0 | IV4: =SUMIFS('INGRESOSXDIA-HABIL'!$T$4:$T$25,'INGRESOSXDIA-HABIL'!$S$4:$S$25,ESCENARIO[[#Headers],[13-oct]]) -> 1.6331696e+09 | IW4: =SUMIFS('INGRESOSXDIA-HABIL'!$T$4:$T$25,'INGRESOSXDIA-HABIL'!$S$4:$S$25,ESCENARIO[[#Headers],[14-oct]]) -> 1.0954726e+09 | IX4: =SUMIFS('INGRESOSXDIA-HABIL'!$T$4:$T$25,'INGRESOSXDIA-HABIL'!$S$4:$S$25,ESCENARIO[[#Headers],[15-oct]]) -> 3.0806599e+09 | IY4: =SUMIFS('INGRESOSXDIA-HABIL'!$T$4:$T$25,'INGRESOSXDIA-HABIL'!$S$4:$S$25,ESCENARIO[[#Headers],[16-oct]]) -> 2.8161517e+09 | IZ4: =SUMIFS('INGRESOSXDIA-HABIL'!$T$4:$T$25,'INGRESOSXDIA-HABIL'!$S$4:$S$25,ESCENARIO[[#Headers],[17-oct]]) -> 0 | JA4: =SUMIFS('INGRESOSXDIA-HABIL'!$T$4:$T$25,'INGRESOSXDIA-HABIL'!$S$4:$S$25,ESCENARIO[[#Headers],[18-oct]]) -> 0 | JB4: =SUMIFS('INGRESOSXDIA-HABIL'!$T$4:$T$25,'INGRESOSXDIA-HABIL'!$S$4:$S$25,ESCENARIO[[#Headers],[19-oct]]) -> 1.5013492e+09 | JC4: =SUMIFS('INGRESOSXDIA-HABIL'!$T$4:$T$25,'INGRESOSXDIA-HABIL'!$S$4:$S$25,ESCENARIO[[#Headers],[20-oct]]) -> 1.8501869e+09 | JD4: =SUMIFS('INGRESOSXDIA-HABIL'!$T$4:$T$25,'INGRESOSXDIA-HABIL'!$S$4:$S$25,ESCENARIO[[#Headers],[21-oct]]) -> 3.0209925e+09 | JE4: =SUMIFS('INGRESOSXDIA-HABIL'!$T$4:$T$25,'INGRESOSXDIA-HABIL'!$S$4:$S$25,ESCENARIO[[#Headers],[22-oct]]) -> 3.1303584e+09 | JF4: =SUMIFS('INGRESOSXDIA-HABIL'!$T$4:$T$25,'INGRESOSXDIA-HABIL'!$S$4:$S$25,ESCENARIO[[#Headers],[23-oct]]) -> 1.761607e+09 | JG4: =SUMIFS('INGRESOSXDIA-HABIL'!$T$4:$T$25,'INGRESOSXDIA-HABIL'!$S$4:$S$25,ESCENARIO[[#Headers],[24-oct]]) -> 0 | JH4: =SUMIFS('INGRESOSXDIA-HABIL'!$T$4:$T$25,'INGRESOSXDIA-HABIL'!$S$4:$S$25,ESCENARIO[[#Headers],[25-oct]]) -> 0 | JI4: =SUMIFS('INGRESOSXDIA-HABIL'!$T$4:$T$25,'INGRESOSXDIA-HABIL'!$S$4:$S$25,ESCENARIO[[#Headers],[26-oct]]) -> 3.3463426e+09 | JJ4: =SUMIFS('INGRESOSXDIA-HABIL'!$T$4:$T$25,'INGRESOSXDIA-HABIL'!$S$4:$S$25,ESCENARIO[[#Headers],[27-oct]]) -> 1.3675609e+09 | JK4: =SUMIFS('INGRESOSXDIA-HABIL'!$T$4:$T$25,'INGRESOSXDIA-HABIL'!$S$4:$S$25,ESCENARIO[[#Headers],[28-oct]]) -> 1.8890127e+09 | JL4: =SUMIFS('INGRESOSXDIA-HABIL'!$T$4:$T$25,'INGRESOSXDIA-HABIL'!$S$4:$S$25,ESCENARIO[[#Headers],[29-oct]]) -> 6.3397666e+08 | JM4: =SUMIFS('INGRESOSXDIA-HABIL'!$T$4:$T$25,'INGRESOSXDIA-HABIL'!$S$4:$S$25,ESCENARIO[[#Headers],[30-oct]]) -> 1.2729681e+09 | JN4: =SUMIFS('INGRESOSXDIA-HABIL'!$T$4:$T$25,'INGRESOSXDIA-HABIL'!$S$4:$S$25,ESCENARIO[[#Headers],[31-oct]]) -> 0 | JO4: =SUMIFS('INGRESOSXDIA-HABIL'!$V$4:$V$23,'INGRESOSXDIA-HABIL'!$U$4:$U$23,ESCENARIO[[#Headers],[01-nov]]) -> 0 | JP4: =SUMIFS('INGRESOSXDIA-HABIL'!$V$4:$V$23,'INGRESOSXDIA-HABIL'!$U$4:$U$23,ESCENARIO[[#Headers],[02-nov]]) -> 7.5625571e+08 | JQ4: =SUMIFS('INGRESOSXDIA-HABIL'!$V$4:$V$23,'INGRESOSXDIA-HABIL'!$U$4:$U$23,ESCENARIO[[#Headers],[03-nov]]) -> 1.0317011e+09 | JR4: =SUMIFS('INGRESOSXDIA-HABIL'!$V$4:$V$23,'INGRESOSXDIA-HABIL'!$U$4:$U$23,ESCENARIO[[#Headers],[04-nov]]) -> 5.8769805e+08 | JS4: =SUMIFS('INGRESOSXDIA-HABIL'!$V$4:$V$23,'INGRESOSXDIA-HABIL'!$U$4:$U$23,ESCENARIO[[#Headers],[05-nov]]) -> 7.4231565e+08 | JT4: =SUMIFS('INGRESOSXDIA-HABIL'!$V$4:$V$23,'INGRESOSXDIA-HABIL'!$U$4:$U$23,ESCENARIO[[#Headers],[06-nov]]) -> 9.6406388e+08 | JU4: =SUMIFS('INGRESOSXDIA-HABIL'!$V$4:$V$23,'INGRESOSXDIA-HABIL'!$U$4:$U$23,ESCENARIO[[#Headers],[07-nov]]) -> 0 | JV4: =SUMIFS('INGRESOSXDIA-HABIL'!$V$4:$V$23,'INGRESOSXDIA-HABIL'!$U$4:$U$23,ESCENARIO[[#Headers],[08-nov]]) -> 0 | JW4: =SUMIFS('INGRESOSXDIA-HABIL'!$V$4:$V$23,'INGRESOSXDIA-HABIL'!$U$4:$U$23,ESCENARIO[[#Headers],[09-nov]]) -> 1.6820144e+09 | JX4: =SUMIFS('INGRESOSXDIA-HABIL'!$V$4:$V$23,'INGRESOSXDIA-HABIL'!$U$4:$U$23,ESCENARIO[[#Headers],[10-nov]]) -> 8.5557693e+09 | JY4: =SUMIFS('INGRESOSXDIA-HABIL'!$V$4:$V$23,'INGRESOSXDIA-HABIL'!$U$4:$U$23,ESCENARIO[[#Headers],[11-nov]]) -> 1.6571504e+09 | JZ4: =SUMIFS('INGRESOSXDIA-HABIL'!$V$4:$V$23,'INGRESOSXDIA-HABIL'!$U$4:$U$23,ESCENARIO[[#Headers],[12-nov]]) -> 1.1115581e+09 | KA4: =SUMIFS('INGRESOSXDIA-HABIL'!$V$4:$V$23,'INGRESOSXDIA-HABIL'!$U$4:$U$23,ESCENARIO[[#Headers],[13-nov]]) -> 3.125895e+09 | KB4: =SUMIFS('INGRESOSXDIA-HABIL'!$V$4:$V$23,'INGRESOSXDIA-HABIL'!$U$4:$U$23,ESCENARIO[[#Headers],[14-nov]]) -> 0 | KC4: =SUMIFS('INGRESOSXDIA-HABIL'!$V$4:$V$23,'INGRESOSXDIA-HABIL'!$U$4:$U$23,ESCENARIO[[#Headers],[15-nov]]) -> 0 | KD4: =SUMIFS('INGRESOSXDIA-HABIL'!$V$4:$V$23,'INGRESOSXDIA-HABIL'!$U$4:$U$23,ESCENARIO[[#Headers],[16-nov]]) -> 2.8575028e+09 | KE4: =SUMIFS('INGRESOSXDIA-HABIL'!$V$4:$V$23,'INGRESOSXDIA-HABIL'!$U$4:$U$23,ESCENARIO[[#Headers],[17-nov]]) -> 1.5233943e+09 | KF4: =SUMIFS('INGRESOSXDIA-HABIL'!$V$4:$V$23,'INGRESOSXDIA-HABIL'!$U$4:$U$23,ESCENARIO[[#Headers],[18-nov]]) -> 1.8773543e+09 | KG4: =SUMIFS('INGRESOSXDIA-HABIL'!$V$4:$V$23,'INGRESOSXDIA-HABIL'!$U$4:$U$23,ESCENARIO[[#Headers],[19-nov]]) -> 3.0653514e+09 | KH4: =SUMIFS('INGRESOSXDIA-HABIL'!$V$4:$V$23,'INGRESOSXDIA-HABIL'!$U$4:$U$23,ESCENARIO[[#Headers],[20-nov]]) -> 3.1763232e+09 | KI4: =SUMIFS('INGRESOSXDIA-HABIL'!$V$4:$V$23,'INGRESOSXDIA-HABIL'!$U$4:$U$23,ESCENARIO[[#Headers],[21-nov]]) -> 0 | KJ4: =SUMIFS('INGRESOSXDIA-HABIL'!$V$4:$V$23,'INGRESOSXDIA-HABIL'!$U$4:$U$23,ESCENARIO[[#Headers],[22-nov]]) -> 0 | KK4: =SUMIFS('INGRESOSXDIA-HABIL'!$V$4:$V$23,'INGRESOSXDIA-HABIL'!$U$4:$U$23,ESCENARIO[[#Headers],[23-nov]]) -> 0 | KL4: =SUMIFS('INGRESOSXDIA-HABIL'!$V$4:$V$23,'INGRESOSXDIA-HABIL'!$U$4:$U$23,ESCENARIO[[#Headers],[24-nov]]) -> 1.7874737e+09 | KM4: =SUMIFS('INGRESOSXDIA-HABIL'!$V$4:$V$23,'INGRESOSXDIA-HABIL'!$U$4:$U$23,ESCENARIO[[#Headers],[25-nov]]) -> 3.3954789e+09 | KN4: =SUMIFS('INGRESOSXDIA-HABIL'!$V$4:$V$23,'INGRESOSXDIA-HABIL'!$U$4:$U$23,ESCENARIO[[#Headers],[26-nov]]) -> 1.3876416e+09 | KO4: =SUMIFS('INGRESOSXDIA-HABIL'!$V$4:$V$23,'INGRESOSXDIA-HABIL'!$U$4:$U$23,ESCENARIO[[#Headers],[27-nov]]) -> 1.9167501e+09 | KP4: =SUMIFS('INGRESOSXDIA-HABIL'!$V$4:$V$23,'INGRESOSXDIA-HABIL'!$U$4:$U$23,ESCENARIO[[#Headers],[28-nov]]) -> 0 | KQ4: =SUMIFS('INGRESOSXDIA-HABIL'!$V$4:$V$23,'INGRESOSXDIA-HABIL'!$U$4:$U$23,ESCENARIO[[#Headers],[29-nov]]) -> 0 | KR4: =SUMIFS('INGRESOSXDIA-HABIL'!$V$4:$V$23,'INGRESOSXDIA-HABIL'!$U$4:$U$23,ESCENARIO[[#Headers],[30-nov]]) -> 1.9349455e+09 | KS4: =SUMIFS('INGRESOSXDIA-HABIL'!$X$4:$X$25,'INGRESOSXDIA-HABIL'!$W$4:$W$25,ESCENARIO[[#Headers],[01-dic]]) -> 7.9140486e+08 | KT4: =SUMIFS('INGRESOSXDIA-HABIL'!$X$4:$X$25,'INGRESOSXDIA-HABIL'!$W$4:$W$25,ESCENARIO[[#Headers],[02-dic]]) -> 1.0796523e+09 | KU4: =SUMIFS('INGRESOSXDIA-HABIL'!$X$4:$X$25,'INGRESOSXDIA-HABIL'!$W$4:$W$25,ESCENARIO[[#Headers],[03-dic]]) -> 6.1501301e+08 | KV4: =SUMIFS('INGRESOSXDIA-HABIL'!$X$4:$X$25,'INGRESOSXDIA-HABIL'!$W$4:$W$25,ESCENARIO[[#Headers],[04-dic]]) -> 7.768169e+08 | KW4: =SUMIFS('INGRESOSXDIA-HABIL'!$X$4:$X$25,'INGRESOSXDIA-HABIL'!$W$4:$W$25,ESCENARIO[[#Headers],[05-dic]]) -> 0 | KX4: =SUMIFS('INGRESOSXDIA-HABIL'!$X$4:$X$25,'INGRESOSXDIA-HABIL'!$W$4:$W$25,ESCENARIO[[#Headers],[06-dic]]) -> 0 | KY4: =SUMIFS('INGRESOSXDIA-HABIL'!$X$4:$X$25,'INGRESOSXDIA-HABIL'!$W$4:$W$25,ESCENARIO[[#Headers],[07-dic]]) -> 0 | KZ4: =SUMIFS('INGRESOSXDIA-HABIL'!$X$4:$X$25,'INGRESOSXDIA-HABIL'!$W$4:$W$25,ESCENARIO[[#Headers],[08-dic]]) -> 0 | LA4: =SUMIFS('INGRESOSXDIA-HABIL'!$X$4:$X$25,'INGRESOSXDIA-HABIL'!$W$4:$W$25,ESCENARIO[[#Headers],[09-dic]]) -> 1.0088715e+09 | LB4: =SUMIFS('INGRESOSXDIA-HABIL'!$X$4:$X$25,'INGRESOSXDIA-HABIL'!$W$4:$W$25,ESCENARIO[[#Headers],[10-dic]]) -> 1.7601909e+09 | LC4: =SUMIFS('INGRESOSXDIA-HABIL'!$X$4:$X$25,'INGRESOSXDIA-HABIL'!$W$4:$W$25,ESCENARIO[[#Headers],[11-dic]]) -> 8.9534232e+09 | LD4: =SUMIFS('INGRESOSXDIA-HABIL'!$X$4:$X$25,'INGRESOSXDIA-HABIL'!$W$4:$W$25,ESCENARIO[[#Headers],[12-dic]]) -> 0 | LE4: =SUMIFS('INGRESOSXDIA-HABIL'!$X$4:$X$25,'INGRESOSXDIA-HABIL'!$W$4:$W$25,ESCENARIO[[#Headers],[13-dic]]) -> 0 | LF4: =SUMIFS('INGRESOSXDIA-HABIL'!$X$4:$X$25,'INGRESOSXDIA-HABIL'!$W$4:$W$25,ESCENARIO[[#Headers],[14-dic]]) -> 1.7341712e+09 | LG4: =SUMIFS('INGRESOSXDIA-HABIL'!$X$4:$X$25,'INGRESOSXDIA-HABIL'!$W$4:$W$25,ESCENARIO[[#Headers],[15-dic]]) -> 1.1632209e+09 | LH4: =SUMIFS('INGRESOSXDIA-HABIL'!$X$4:$X$25,'INGRESOSXDIA-HABIL'!$W$4:$W$25,ESCENARIO[[#Headers],[16-dic]]) -> 3.2711799e+09 | LI4: =SUMIFS('INGRESOSXDIA-HABIL'!$X$4:$X$25,'INGRESOSXDIA-HABIL'!$W$4:$W$25,ESCENARIO[[#Headers],[17-dic]]) -> 2.9903135e+09 | LJ4: =SUMIFS('INGRESOSXDIA-HABIL'!$X$4:$X$25,'INGRESOSXDIA-HABIL'!$W$4:$W$25,ESCENARIO[[#Headers],[18-dic]]) -> 1.5941984e+09 | LK4: =SUMIFS('INGRESOSXDIA-HABIL'!$X$4:$X$25,'INGRESOSXDIA-HABIL'!$W$4:$W$25,ESCENARIO[[#Headers],[19-dic]]) -> 0 | LL4: =SUMIFS('INGRESOSXDIA-HABIL'!$X$4:$X$25,'INGRESOSXDIA-HABIL'!$W$4:$W$25,ESCENARIO[[#Headers],[20-dic]]) -> 0 | LM4: =SUMIFS('INGRESOSXDIA-HABIL'!$X$4:$X$25,'INGRESOSXDIA-HABIL'!$W$4:$W$25,ESCENARIO[[#Headers],[21-dic]]) -> 1.9646097e+09 | LN4: =SUMIFS('INGRESOSXDIA-HABIL'!$X$4:$X$25,'INGRESOSXDIA-HABIL'!$W$4:$W$25,ESCENARIO[[#Headers],[22-dic]]) -> 3.2078224e+09 | LO4: =SUMIFS('INGRESOSXDIA-HABIL'!$X$4:$X$25,'INGRESOSXDIA-HABIL'!$W$4:$W$25,ESCENARIO[[#Headers],[23-dic]]) -> 3.323952e+09 | LP4: =SUMIFS('INGRESOSXDIA-HABIL'!$X$4:$X$25,'INGRESOSXDIA-HABIL'!$W$4:$W$25,ESCENARIO[[#Headers],[24-dic]]) -> 1.8705517e+09 | LQ4: =SUMIFS('INGRESOSXDIA-HABIL'!$X$4:$X$25,'INGRESOSXDIA-HABIL'!$W$4:$W$25,ESCENARIO[[#Headers],[25-dic]]) -> 0 | LR4: =SUMIFS('INGRESOSXDIA-HABIL'!$X$4:$X$25,'INGRESOSXDIA-HABIL'!$W$4:$W$25,ESCENARIO[[#Headers],[26-dic]]) -> 0 | LS4: =SUMIFS('INGRESOSXDIA-HABIL'!$X$4:$X$25,'INGRESOSXDIA-HABIL'!$W$4:$W$25,ESCENARIO[[#Headers],[27-dic]]) -> 0 | LT4: =SUMIFS('INGRESOSXDIA-HABIL'!$X$4:$X$25,'INGRESOSXDIA-HABIL'!$W$4:$W$25,ESCENARIO[[#Headers],[28-dic]]) -> 3.5532935e+09 | LU4: =SUMIFS('INGRESOSXDIA-HABIL'!$X$4:$X$25,'INGRESOSXDIA-HABIL'!$W$4:$W$25,ESCENARIO[[#Headers],[29-dic]]) -> 1.4521362e+09 | LV4: =SUMIFS('INGRESOSXDIA-HABIL'!$X$4:$X$25,'INGRESOSXDIA-HABIL'!$W$4:$W$25,ESCENARIO[[#Headers],[30-dic]]) -> 2.0058366e+09 | LW4: =SUMIFS('INGRESOSXDIA-HABIL'!$X$4:$X$25,'INGRESOSXDIA-HABIL'!$W$4:$W$25,ESCENARIO[[#Headers],[31-dic]]) -> 2.0248776e+09 | LX4: =SUM(ESCENARIO[[#This Row],[01-mar]:[31-dic]]) -> 4.0394539e+11
A5: RESCATE DE FCI | B5: =IF(B2>B3,0,B2-B3) -> 0 | C5: =IF(C2>C3,0,C2-C3) -> -235000000 | D5: =IF(D2>D3,0,D2-D3) -> -8.0705818e+08 | E5: =IF(E2>E3,0,E2-E3) -> 0 | F5: =IF(F2>F3,0,F2-F3) -> 0 | G5: =IF(G2>G3,0,G2-G3) -> 0 | H5: =IF(H2>H3,0,H2-H3) -> 0 | I5: =IF(I2>I3,0,I2-I3) -> 0 | ... LW5: =IF(LW2>LW3,0,LW2-LW3) -> 0 | LX5: =SUM(ESCENARIO[[#This Row],[01-mar]:[31-dic]]) -> -2.8562925e+11
A6: INTERES DIARIO (0.0967%) | C6: =+B7*0.0967% -> 2297689.7 | D6: =+C7*0.0967% -> 2070444.7 | E6: =+D7*0.0967% -> 1290019.4 | F6: =+E7*0.0967% -> 2134991.9 | G6: =+F7*0.0967% -> 2615892.1 | H6: =+G7*0.0967% -> 3223312.3 | I6: =+H7*0.0967% -> 4012184.2 | J6: =+I7*0.0967% -> 4012184.2 | ... LW6: =+LV7*0.0967% -> 71093235 | LX6: =SUM(ESCENARIO[[#This Row],[01-mar]:[31-dic]]) -> 1.0734236e+10
A7: INVERSIONES FCI | B7: =+B2-B3+B5 -> 2.376101e+09 | C7: =IF(C5<0,ESCENARIO[[#This Row],[01-feb]]+C5,IF(C5=0,ESCENARIO[[#This Row],[01-feb]]+C5+C2)) -> 2.141101e+09 | D7: =IF(D5<0,ESCENARIO[[#This Row],[02-feb]]+D5,IF(D5=0,ESCENARIO[[#This Row],[02-feb]]+D5+D2)) -> 1.3340428e+09 | E7: =IF(E5<0,ESCENARIO[[#This Row],[03-feb]]+E5,IF(E5=0,ESCENARIO[[#This Row],[03-feb]]+E5+E2)) -> 2.207851e+09 | F7: =IF(F5<0,ESCENARIO[[#This Row],[04-feb]]+F5,IF(F5=0,ESCENARIO[[#This Row],[04-feb]]+F5+F2)) -> 2.7051624e+09 | G7: =IF(G5<0,ESCENARIO[[#This Row],[05-feb]]+G5,IF(G5=0,ESCENARIO[[#This Row],[05-feb]]+G5+G2)) -> 3.3333116e+09 | H7: =IF(H5<0,ESCENARIO[[#This Row],[06-feb]]+H5,IF(H5=0,ESCENARIO[[#This Row],[06-feb]]+H5+H2)) -> 4.1491046e+09 | I7: =IF(I5<0,ESCENARIO[[#This Row],[07-feb]]+I5,IF(I5=0,ESCENARIO[[#This Row],[07-feb]]+I5+I2)) -> 4.1491046e+09 | J7: =IF(J5<0,ESCENARIO[[#This Row],[08-feb]]+J5,IF(J5=0,ESCENARIO[[#This Row],[08-feb]]+J5+J2)) -> 4.1491046e+09 | K7: =IF(K5<0,ESCENARIO[[#This Row],[09-feb]]+K5,IF(K5=0,ESCENARIO[[#This Row],[09-feb]]+K5+K2)) -> 5.572429e+09 | L7: =IF(L5<0,ESCENARIO[[#This Row],[10-feb]]+L5,IF(L5=0,ESCENARIO[[#This Row],[10-feb]]+L5+L2)) -> 1.281234e+10 | M7: =IF(M5<0,ESCENARIO[[#This Row],[11-feb]]+M5,IF(M5=0,ESCENARIO[[#This Row],[11-feb]]+M5+M2)) -> 1.4214625e+10 | N7: =IF(N5<0,ESCENARIO[[#This Row],[12-feb]]+N5,IF(N5=0,ESCENARIO[[#This Row],[12-feb]]+N5+N2)) -> 1.3863315e+10 | O7: =IF(O5<0,ESCENARIO[[#This Row],[13-feb]]+O5,IF(O5=0,ESCENARIO[[#This Row],[13-feb]]+O5+O2)) -> 1.6508794e+10 | P7: =IF(P5<0,ESCENARIO[[#This Row],[14-feb]]+P5,IF(P5=0,ESCENARIO[[#This Row],[14-feb]]+P5+P2)) -> 1.6273794e+10 | Q7: =IF(Q5<0,ESCENARIO[[#This Row],[15-feb]]+Q5,IF(Q5=0,ESCENARIO[[#This Row],[15-feb]]+Q5+Q2)) -> 1.6274022e+10 | R7: =IF(R5<0,ESCENARIO[[#This Row],[16-feb]]+R5,IF(R5=0,ESCENARIO[[#This Row],[16-feb]]+R5+R2)) -> 1.8692047e+10 | S7: =IF(S5<0,ESCENARIO[[#This Row],[17-feb]]+S5,IF(S5=0,ESCENARIO[[#This Row],[17-feb]]+S5+S2)) -> 1.9981147e+10 | T7: =IF(T5<0,ESCENARIO[[#This Row],[18-feb]]+T5,IF(T5=0,ESCENARIO[[#This Row],[18-feb]]+T5+T2)) -> 2.1569768e+10 | U7: =IF(U5<0,ESCENARIO[[#This Row],[19-feb]]+U5,IF(U5=0,ESCENARIO[[#This Row],[19-feb]]+U5+U2)) -> 2.4163675e+10 | V7: =IF(V5<0,ESCENARIO[[#This Row],[20-feb]]+V5,IF(V5=0,ESCENARIO[[#This Row],[20-feb]]+V5+V2)) -> 2.6851487e+10 | W7: =IF(W5<0,ESCENARIO[[#This Row],[21-feb]]+W5,IF(W5=0,ESCENARIO[[#This Row],[21-feb]]+W5+W2)) -> 2.6851487e+10 | X7: =IF(X5<0,ESCENARIO[[#This Row],[22-feb]]+X5,IF(X5=0,ESCENARIO[[#This Row],[22-feb]]+X5+X2)) -> 2.6851487e+10 | Y7: =IF(Y5<0,ESCENARIO[[#This Row],[23-feb]]+Y5,IF(Y5=0,ESCENARIO[[#This Row],[23-feb]]+Y5+Y2)) -> 2.8364051e+10 | Z7: =IF(Z5<0,ESCENARIO[[#This Row],[24-feb]]+Z5,IF(Z5=0,ESCENARIO[[#This Row],[24-feb]]+Z5+Z2)) -> 2.4081417e+10 | AA7: =IF(AA5<0,ESCENARIO[[#This Row],[25-feb]]+AA5,IF(AA5=0,ESCENARIO[[#This Row],[25-feb]]+AA5+AA2)) -> 2.0817484e+10 | AB7: =IF(AB5<0,ESCENARIO[[#This Row],[26-feb]]+AB5,IF(AB5=0,ESCENARIO[[#This Row],[26-feb]]+AB5+AB2)) -> 3.5949211e+09 | AC7: 1840000000 | AD7: =IF(AD5<0,ESCENARIO[[#This Row],[28-feb]]+AD5,IF(AD5=0,ESCENARIO[[#This Row],[28-feb]]+AD5+AD2)) -> 2378000000 | AE7: =IF(AE5<0,ESCENARIO[[#This Row],[01-mar]]+AE5,IF(AE5=0,ESCENARIO[[#This Row],[01-mar]]+AE5+AE2)) -> 2378000000 | AF7: =IF(AF5<0,ESCENARIO[[#This Row],[02-mar]]+AF5,IF(AF5=0,ESCENARIO[[#This Row],[02-mar]]+AF5+AF2)) -> 1.9229327e+09 | AG7: =IF(AG5<0,ESCENARIO[[#This Row],[03-mar]]+AG5,IF(AG5=0,ESCENARIO[[#This Row],[03-mar]]+AG5+AG2)) -> 2.8128905e+09 | AH7: =IF(AH5<0,ESCENARIO[[#This Row],[04-mar]]+AH5,IF(AH5=0,ESCENARIO[[#This Row],[04-mar]]+AH5+AH2)) -> 3.3195952e+09 | AI7: =IF(AI5<0,ESCENARIO[[#This Row],[05-mar]]+AI5,IF(AI5=0,ESCENARIO[[#This Row],[05-mar]]+AI5+AI2)) -> 3.959609e+09 | AJ7: =IF(AJ5<0,ESCENARIO[[#This Row],[06-mar]]+AJ5,IF(AJ5=0,ESCENARIO[[#This Row],[06-mar]]+AJ5+AJ2)) -> 4.7908109e+09 | AK7: =IF(AK5<0,ESCENARIO[[#This Row],[07-mar]]+AK5,IF(AK5=0,ESCENARIO[[#This Row],[07-mar]]+AK5+AK2)) -> 4.7908109e+09 | AL7: =IF(AL5<0,ESCENARIO[[#This Row],[08-mar]]+AL5,IF(AL5=0,ESCENARIO[[#This Row],[08-mar]]+AL5+AL2)) -> 4.7908109e+09 | AM7: =IF(AM5<0,ESCENARIO[[#This Row],[09-mar]]+AM5,IF(AM5=0,ESCENARIO[[#This Row],[09-mar]]+AM5+AM2)) -> 6.2410194e+09 | AN7: =IF(AN5<0,ESCENARIO[[#This Row],[10-mar]]+AN5,IF(AN5=0,ESCENARIO[[#This Row],[10-mar]]+AN5+AN2)) -> 1.361768e+10 | AO7: =IF(AO5<0,ESCENARIO[[#This Row],[11-mar]]+AO5,IF(AO5=0,ESCENARIO[[#This Row],[11-mar]]+AO5+AO2)) -> 1.5046451e+10 | AP7: =IF(AP5<0,ESCENARIO[[#This Row],[12-mar]]+AP5,IF(AP5=0,ESCENARIO[[#This Row],[12-mar]]+AP5+AP2)) -> 1.480482e+10 | AQ7: =IF(AQ5<0,ESCENARIO[[#This Row],[13-mar]]+AQ5,IF(AQ5=0,ESCENARIO[[#This Row],[13-mar]]+AQ5+AQ2)) -> 1.7500155e+10 | AR7: =IF(AR5<0,ESCENARIO[[#This Row],[14-mar]]+AR5,IF(AR5=0,ESCENARIO[[#This Row],[14-mar]]+AR5+AR2)) -> 1.7250155e+10 | AS7: =IF(AS5<0,ESCENARIO[[#This Row],[15-mar]]+AS5,IF(AS5=0,ESCENARIO[[#This Row],[15-mar]]+AS5+AS2)) -> 1.7250397e+10 | AT7: =IF(AT5<0,ESCENARIO[[#This Row],[16-mar]]+AT5,IF(AT5=0,ESCENARIO[[#This Row],[16-mar]]+AT5+AT2)) -> 1.9714094e+10 | AU7: =IF(AU5<0,ESCENARIO[[#This Row],[17-mar]]+AU5,IF(AU5=0,ESCENARIO[[#This Row],[17-mar]]+AU5+AU2)) -> 2.1027543e+10 | AV7: =IF(AV5<0,ESCENARIO[[#This Row],[18-mar]]+AV5,IF(AV5=0,ESCENARIO[[#This Row],[18-mar]]+AV5+AV2)) -> 2.0646171e+10 | AW7: =IF(AW5<0,ESCENARIO[[#This Row],[19-mar]]+AW5,IF(AW5=0,ESCENARIO[[#This Row],[19-mar]]+AW5+AW2)) -> 2.3289441e+10 | AX7: =IF(AX5<0,ESCENARIO[[#This Row],[20-mar]]+AX5,IF(AX5=0,ESCENARIO[[#This Row],[20-mar]]+AX5+AX2)) -> 2.6028021e+10 | AY7: =IF(AY5<0,ESCENARIO[[#This Row],[21-mar]]+AY5,IF(AY5=0,ESCENARIO[[#This Row],[21-mar]]+AY5+AY2)) -> 2.7569155e+10 | AZ7: =IF(AZ5<0,ESCENARIO[[#This Row],[22-mar]]+AZ5,IF(AZ5=0,ESCENARIO[[#This Row],[22-mar]]+AZ5+AZ2)) -> 3.0496688e+10 | BA7: =IF(BA5<0,ESCENARIO[[#This Row],[23-mar]]+BA5,IF(BA5=0,ESCENARIO[[#This Row],[23-mar]]+BA5+BA2)) -> 2.2815442e+10 | BB7: =IF(BB5<0,ESCENARIO[[#This Row],[24-mar]]+BB5,IF(BB5=0,ESCENARIO[[#This Row],[24-mar]]+BB5+BB2)) -> 2.282287e+10 | BC7: =IF(BC5<0,ESCENARIO[[#This Row],[25-mar]]+BC5,IF(BC5=0,ESCENARIO[[#This Row],[25-mar]]+BC5+BC2)) -> 2.4019274e+10 | BD7: =IF(BD5<0,ESCENARIO[[#This Row],[26-mar]]+BD5,IF(BD5=0,ESCENARIO[[#This Row],[26-mar]]+BD5+BD2)) -> 2.5671868e+10 | BE7: =IF(BE5<0,ESCENARIO[[#This Row],[27-mar]]+BE5,IF(BE5=0,ESCENARIO[[#This Row],[27-mar]]+BE5+BE2)) -> 2.62265e+10 | BF7: =IF(BF5<0,ESCENARIO[[#This Row],[28-mar]]+BF5,IF(BF5=0,ESCENARIO[[#This Row],[28-mar]]+BF5+BF2)) -> 2.62265e+10 | BG7: =IF(BG5<0,ESCENARIO[[#This Row],[29-mar]]+BG5,IF(BG5=0,ESCENARIO[[#This Row],[29-mar]]+BG5+BG2)) -> 1.9274581e+10 | BH7: =IF(BH5<0,ESCENARIO[[#This Row],[30-mar]]+BH5,IF(BH5=0,ESCENARIO[[#This Row],[30-mar]]+BH5+BH2)) -> 2.955254e+08 | BI7: =IF(BI5<0,ESCENARIO[[#This Row],[31-mar]]+BI5,IF(BI5=0,ESCENARIO[[#This Row],[31-mar]]+BI5+BI2)) -> 3.1387814e+08 | BJ7: =IF(BJ5<0,ESCENARIO[[#This Row],[01-abr]]+BJ5,IF(BJ5=0,ESCENARIO[[#This Row],[01-abr]]+BJ5+BJ2)) -> 9.75835e+08 | BK7: =IF(BK5<0,ESCENARIO[[#This Row],[02-abr]]+BK5,IF(BK5=0,ESCENARIO[[#This Row],[02-abr]]+BK5+BK2)) -> 9.75835e+08 | BL7: =IF(BL5<0,ESCENARIO[[#This Row],[03-abr]]+BL5,IF(BL5=0,ESCENARIO[[#This Row],[03-abr]]+BL5+BL2)) -> 9.75835e+08 | BM7: =IF(BM5<0,ESCENARIO[[#This Row],[04-abr]]+BM5,IF(BM5=0,ESCENARIO[[#This Row],[04-abr]]+BM5+BM2)) -> 9.75835e+08 | BN7: =IF(BN5<0,ESCENARIO[[#This Row],[05-abr]]+BN5,IF(BN5=0,ESCENARIO[[#This Row],[05-abr]]+BN5+BN2)) -> 9.75835e+08 | BO7: =IF(BO5<0,ESCENARIO[[#This Row],[06-abr]]+BO5,IF(BO5=0,ESCENARIO[[#This Row],[06-abr]]+BO5+BO2)) -> 7.7179147e+08 | BP7: =IF(BP5<0,ESCENARIO[[#This Row],[07-abr]]+BP5,IF(BP5=0,ESCENARIO[[#This Row],[07-abr]]+BP5+BP2)) -> 1.2864057e+09 | BQ7: =IF(BQ5<0,ESCENARIO[[#This Row],[08-abr]]+BQ5,IF(BQ5=0,ESCENARIO[[#This Row],[08-abr]]+BQ5+BQ2)) -> 1.9361608e+09 | BR7: =IF(BR5<0,ESCENARIO[[#This Row],[09-abr]]+BR5,IF(BR5=0,ESCENARIO[[#This Row],[09-abr]]+BR5+BR2)) -> 2.7800138e+09 | BS7: =IF(BS5<0,ESCENARIO[[#This Row],[10-abr]]+BS5,IF(BS5=0,ESCENARIO[[#This Row],[10-abr]]+BS5+BS2)) -> 4.2522949e+09 | BT7: =IF(BT5<0,ESCENARIO[[#This Row],[11-abr]]+BT5,IF(BT5=0,ESCENARIO[[#This Row],[11-abr]]+BT5+BT2)) -> 4.2522949e+09 | BU7: =IF(BU5<0,ESCENARIO[[#This Row],[12-abr]]+BU5,IF(BU5=0,ESCENARIO[[#This Row],[12-abr]]+BU5+BU2)) -> 4.2522949e+09 | BV7: =IF(BV5<0,ESCENARIO[[#This Row],[13-abr]]+BV5,IF(BV5=0,ESCENARIO[[#This Row],[13-abr]]+BV5+BV2)) -> 1.174123e+10 | BW7: =IF(BW5<0,ESCENARIO[[#This Row],[14-abr]]+BW5,IF(BW5=0,ESCENARIO[[#This Row],[14-abr]]+BW5+BW2)) -> 1.3191748e+10 | BX7: =IF(BX5<0,ESCENARIO[[#This Row],[15-abr]]+BX5,IF(BX5=0,ESCENARIO[[#This Row],[15-abr]]+BX5+BX2)) -> 1.4164704e+10 | BY7: =IF(BY5<0,ESCENARIO[[#This Row],[16-abr]]+BY5,IF(BY5=0,ESCENARIO[[#This Row],[16-abr]]+BY5+BY2)) -> 1.6900825e+10 | BZ7: =IF(BZ5<0,ESCENARIO[[#This Row],[17-abr]]+BZ5,IF(BZ5=0,ESCENARIO[[#This Row],[17-abr]]+BZ5+BZ2)) -> 1.9402021e+10 | CA7: =IF(CA5<0,ESCENARIO[[#This Row],[18-abr]]+CA5,IF(CA5=0,ESCENARIO[[#This Row],[18-abr]]+CA5+CA2)) -> 1.9402021e+10 | CB7: =IF(CB5<0,ESCENARIO[[#This Row],[19-abr]]+CB5,IF(CB5=0,ESCENARIO[[#This Row],[19-abr]]+CB5+CB2)) -> 1.7402021e+10 | CC7: =IF(CC5<0,ESCENARIO[[#This Row],[20-abr]]+CC5,IF(CC5=0,ESCENARIO[[#This Row],[20-abr]]+CC5+CC2)) -> 1.8737395e+10 | CD7: =IF(CD5<0,ESCENARIO[[#This Row],[21-abr]]+CD5,IF(CD5=0,ESCENARIO[[#This Row],[21-abr]]+CD5+CD2)) -> 2.0380659e+10 | CE7: =IF(CE5<0,ESCENARIO[[#This Row],[22-abr]]+CE5,IF(CE5=0,ESCENARIO[[#This Row],[22-abr]]+CE5+CE2)) -> 2.3063786e+10 | CF7: =IF(CF5<0,ESCENARIO[[#This Row],[23-abr]]+CF5,IF(CF5=0,ESCENARIO[[#This Row],[23-abr]]+CF5+CF2)) -> 2.5844048e+10 | CG7: =IF(CG5<0,ESCENARIO[[#This Row],[24-abr]]+CG5,IF(CG5=0,ESCENARIO[[#This Row],[24-abr]]+CG5+CG2)) -> 2.7408638e+10 | CH7: =IF(CH5<0,ESCENARIO[[#This Row],[25-abr]]+CH5,IF(CH5=0,ESCENARIO[[#This Row],[25-abr]]+CH5+CH2)) -> 2.7408638e+10 | CI7: =IF(CI5<0,ESCENARIO[[#This Row],[26-abr]]+CI5,IF(CI5=0,ESCENARIO[[#This Row],[26-abr]]+CI5+CI2)) -> 2.7408638e+10 | CJ7: =IF(CJ5<0,ESCENARIO[[#This Row],[27-abr]]+CJ5,IF(CJ5=0,ESCENARIO[[#This Row],[27-abr]]+CJ5+CJ2)) -> 2.3856474e+10 | CK7: =IF(CK5<0,ESCENARIO[[#This Row],[28-abr]]+CK5,IF(CK5=0,ESCENARIO[[#This Row],[28-abr]]+CK5+CK2)) -> 2.5074523e+10 | CL7: =IF(CL5<0,ESCENARIO[[#This Row],[29-abr]]+CL5,IF(CL5=0,ESCENARIO[[#This Row],[29-abr]]+CL5+CL2)) -> 2.7415336e+09 | CM7: =IF(CM5<0,ESCENARIO[[#This Row],[30-abr]]+CM5,IF(CM5=0,ESCENARIO[[#This Row],[30-abr]]+CM5+CM2)) -> 4.4568034e+09 | CN7: =IF(CN5<0,ESCENARIO[[#This Row],[01-may]]+CN5,IF(CN5=0,ESCENARIO[[#This Row],[01-may]]+CN5+CN2)) -> 4.4568034e+09 | CO7: =IF(CO5<0,ESCENARIO[[#This Row],[02-may]]+CO5,IF(CO5=0,ESCENARIO[[#This Row],[02-may]]+CO5+CO2)) -> 4.4568034e+09 | CP7: =IF(CP5<0,ESCENARIO[[#This Row],[03-may]]+CP5,IF(CP5=0,ESCENARIO[[#This Row],[03-may]]+CP5+CP2)) -> 4.4568034e+09 | CQ7: =IF(CQ5<0,ESCENARIO[[#This Row],[04-may]]+CQ5,IF(CQ5=0,ESCENARIO[[#This Row],[04-may]]+CQ5+CQ2)) -> 4.0507929e+09 | CR7: =IF(CR5<0,ESCENARIO[[#This Row],[05-may]]+CR5,IF(CR5=0,ESCENARIO[[#This Row],[05-may]]+CR5+CR2)) -> 5.0076277e+09 | CS7: =IF(CS5<0,ESCENARIO[[#This Row],[06-may]]+CS5,IF(CS5=0,ESCENARIO[[#This Row],[06-may]]+CS5+CS2)) -> 5.5524553e+09 | CT7: =IF(CT5<0,ESCENARIO[[#This Row],[07-may]]+CT5,IF(CT5=0,ESCENARIO[[#This Row],[07-may]]+CT5+CT2)) -> 6.2406217e+09 | CU7: =IF(CU5<0,ESCENARIO[[#This Row],[08-may]]+CU5,IF(CU5=0,ESCENARIO[[#This Row],[08-may]]+CU5+CU2)) -> 7.1343606e+09 | CV7: =IF(CV5<0,ESCENARIO[[#This Row],[09-may]]+CV5,IF(CV5=0,ESCENARIO[[#This Row],[09-may]]+CV5+CV2)) -> 7.1343606e+09 | CW7: =IF(CW5<0,ESCENARIO[[#This Row],[10-may]]+CW5,IF(CW5=0,ESCENARIO[[#This Row],[10-may]]+CW5+CW2)) -> 7.1343606e+09 | CX7: =IF(CX5<0,ESCENARIO[[#This Row],[11-may]]+CX5,IF(CX5=0,ESCENARIO[[#This Row],[11-may]]+CX5+CX2)) -> 8.6936781e+09 | CY7: =IF(CY5<0,ESCENARIO[[#This Row],[12-may]]+CY5,IF(CY5=0,ESCENARIO[[#This Row],[12-may]]+CY5+CY2)) -> 1.6625335e+10 | CZ7: =IF(CZ5<0,ESCENARIO[[#This Row],[13-may]]+CZ5,IF(CZ5=0,ESCENARIO[[#This Row],[13-may]]+CZ5+CZ2)) -> 1.8161602e+10 | DA7: =IF(DA5<0,ESCENARIO[[#This Row],[14-may]]+DA5,IF(DA5=0,ESCENARIO[[#This Row],[14-may]]+DA5+DA2)) -> 1.7742076e+10 | DB7: =IF(DB5<0,ESCENARIO[[#This Row],[15-may]]+DB5,IF(DB5=0,ESCENARIO[[#This Row],[15-may]]+DB5+DB2)) -> 2.0640354e+10 | DC7: =IF(DC5<0,ESCENARIO[[#This Row],[16-may]]+DC5,IF(DC5=0,ESCENARIO[[#This Row],[16-may]]+DC5+DC2)) -> 2.0640354e+10 | DD7: =IF(DD5<0,ESCENARIO[[#This Row],[17-may]]+DD5,IF(DD5=0,ESCENARIO[[#This Row],[17-may]]+DD5+DD2)) -> 2.0640354e+10 | DE7: =IF(DE5<0,ESCENARIO[[#This Row],[18-may]]+DE5,IF(DE5=0,ESCENARIO[[#This Row],[18-may]]+DE5+DE2)) -> 2.3289412e+10 | DF7: =IF(DF5<0,ESCENARIO[[#This Row],[19-may]]+DF5,IF(DF5=0,ESCENARIO[[#This Row],[19-may]]+DF5+DF2)) -> 2.470168e+10 | DG7: =IF(DG5<0,ESCENARIO[[#This Row],[20-may]]+DG5,IF(DG5=0,ESCENARIO[[#This Row],[20-may]]+DG5+DG2)) -> 2.6442088e+10 | DH7: =IF(DH5<0,ESCENARIO[[#This Row],[21-may]]+DH5,IF(DH5=0,ESCENARIO[[#This Row],[21-may]]+DH5+DH2)) -> 2.9283833e+10 | DI7: =IF(DI5<0,ESCENARIO[[#This Row],[22-may]]+DI5,IF(DI5=0,ESCENARIO[[#This Row],[22-may]]+DI5+DI2)) -> 3.2228455e+10 | DJ7: =IF(DJ5<0,ESCENARIO[[#This Row],[23-may]]+DJ5,IF(DJ5=0,ESCENARIO[[#This Row],[23-may]]+DJ5+DJ2)) -> 3.2228455e+10 | DK7: =IF(DK5<0,ESCENARIO[[#This Row],[24-may]]+DK5,IF(DK5=0,ESCENARIO[[#This Row],[24-may]]+DK5+DK2)) -> 3.2228455e+10 | DL7: =IF(DL5<0,ESCENARIO[[#This Row],[25-may]]+DL5,IF(DL5=0,ESCENARIO[[#This Row],[25-may]]+DL5+DL2)) -> 2.544209e+10 | DM7: =IF(DM5<0,ESCENARIO[[#This Row],[26-may]]+DM5,IF(DM5=0,ESCENARIO[[#This Row],[26-may]]+DM5+DM2)) -> 2.7105737e+10 | DN7: =IF(DN5<0,ESCENARIO[[#This Row],[27-may]]+DN5,IF(DN5=0,ESCENARIO[[#This Row],[27-may]]+DN5+DN2)) -> 3.0253528e+10 | DO7: =IF(DO5<0,ESCENARIO[[#This Row],[28-may]]+DO5,IF(DO5=0,ESCENARIO[[#This Row],[28-may]]+DO5+DO2)) -> 6.3245124e+09 | DP7: =IF(DP5<0,ESCENARIO[[#This Row],[29-may]]+DP5,IF(DP5=0,ESCENARIO[[#This Row],[29-may]]+DP5+DP2)) -> 8.1245819e+09 | DQ7: =IF(DQ5<0,ESCENARIO[[#This Row],[30-may]]+DQ5,IF(DQ5=0,ESCENARIO[[#This Row],[30-may]]+DQ5+DQ2)) -> 8.7209422e+09 | DR7: =IF(DR5<0,ESCENARIO[[#This Row],[31-may]]+DR5,IF(DR5=0,ESCENARIO[[#This Row],[31-may]]+DR5+DR2)) -> 9.91838e+09 | DS7: =IF(DS5<0,ESCENARIO[[#This Row],[01-jun]]+DS5,IF(DS5=0,ESCENARIO[[#This Row],[01-jun]]+DS5+DS2)) -> 8.81128e+09 | DT7: =IF(DT5<0,ESCENARIO[[#This Row],[02-jun]]+DT5,IF(DT5=0,ESCENARIO[[#This Row],[02-jun]]+DT5+DT2)) -> 9.4942291e+09 | DU7: =IF(DU5<0,ESCENARIO[[#This Row],[03-jun]]+DU5,IF(DU5=0,ESCENARIO[[#This Row],[03-jun]]+DU5+DU2)) -> 1.0424463e+10 | DV7: =IF(DV5<0,ESCENARIO[[#This Row],[04-jun]]+DV5,IF(DV5=0,ESCENARIO[[#This Row],[04-jun]]+DV5+DV2)) -> 1.0954362e+10 | DW7: =IF(DW5<0,ESCENARIO[[#This Row],[05-jun]]+DW5,IF(DW5=0,ESCENARIO[[#This Row],[05-jun]]+DW5+DW2)) -> 1.1623671e+10 | DX7: =IF(DX5<0,ESCENARIO[[#This Row],[06-jun]]+DX5,IF(DX5=0,ESCENARIO[[#This Row],[06-jun]]+DX5+DX2)) -> 1.1623671e+10 | DY7: =IF(DY5<0,ESCENARIO[[#This Row],[07-jun]]+DY5,IF(DY5=0,ESCENARIO[[#This Row],[07-jun]]+DY5+DY2)) -> 1.1623671e+10 | DZ7: =IF(DZ5<0,ESCENARIO[[#This Row],[08-jun]]+DZ5,IF(DZ5=0,ESCENARIO[[#This Row],[08-jun]]+DZ5+DZ2)) -> 1.139092e+10 | EA7: =IF(EA5<0,ESCENARIO[[#This Row],[09-jun]]+EA5,IF(EA5=0,ESCENARIO[[#This Row],[09-jun]]+EA5+EA2)) -> 1.2907735e+10 | EB7: =IF(EB5<0,ESCENARIO[[#This Row],[10-jun]]+EB5,IF(EB5=0,ESCENARIO[[#This Row],[10-jun]]+EB5+EB2)) -> 2.062205e+10 | EC7: =IF(EC5<0,ESCENARIO[[#This Row],[11-jun]]+EC5,IF(EC5=0,ESCENARIO[[#This Row],[11-jun]]+EC5+EC2)) -> 2.2116221e+10 | ED7: =IF(ED5<0,ESCENARIO[[#This Row],[12-jun]]+ED5,IF(ED5=0,ESCENARIO[[#This Row],[12-jun]]+ED5+ED2)) -> 2.3118458e+10 | EE7: =IF(EE5<0,ESCENARIO[[#This Row],[13-jun]]+EE5,IF(EE5=0,ESCENARIO[[#This Row],[13-jun]]+EE5+EE2)) -> 2.3118458e+10 | EF7: =IF(EF5<0,ESCENARIO[[#This Row],[14-jun]]+EF5,IF(EF5=0,ESCENARIO[[#This Row],[14-jun]]+EF5+EF2)) -> 2.2868458e+10 | EG7: =IF(EG5<0,ESCENARIO[[#This Row],[15-jun]]+EG5,IF(EG5=0,ESCENARIO[[#This Row],[15-jun]]+EG5+EG2)) -> 2.28687e+10 | EH7: =IF(EH5<0,ESCENARIO[[#This Row],[16-jun]]+EH5,IF(EH5=0,ESCENARIO[[#This Row],[16-jun]]+EH5+EH2)) -> 2.5687166e+10 | EI7: =IF(EI5<0,ESCENARIO[[#This Row],[17-jun]]+EI5,IF(EI5=0,ESCENARIO[[#This Row],[17-jun]]+EI5+EI2)) -> 2.8263635e+10 | EJ7: =IF(EJ5<0,ESCENARIO[[#This Row],[18-jun]]+EJ5,IF(EJ5=0,ESCENARIO[[#This Row],[18-jun]]+EJ5+EJ2)) -> 2.9637205e+10 | EK7: =IF(EK5<0,ESCENARIO[[#This Row],[19-jun]]+EK5,IF(EK5=0,ESCENARIO[[#This Row],[19-jun]]+EK5+EK2)) -> 3.1329923e+10 | EL7: =IF(EL5<0,ESCENARIO[[#This Row],[20-jun]]+EL5,IF(EL5=0,ESCENARIO[[#This Row],[20-jun]]+EL5+EL2)) -> 3.1329923e+10 | EM7: =IF(EM5<0,ESCENARIO[[#This Row],[21-jun]]+EM5,IF(EM5=0,ESCENARIO[[#This Row],[21-jun]]+EM5+EM2)) -> 3.1329923e+10 | EN7: =IF(EN5<0,ESCENARIO[[#This Row],[22-jun]]+EN5,IF(EN5=0,ESCENARIO[[#This Row],[22-jun]]+EN5+EN2)) -> 2.7725544e+10 | EO7: =IF(EO5<0,ESCENARIO[[#This Row],[23-jun]]+EO5,IF(EO5=0,ESCENARIO[[#This Row],[23-jun]]+EO5+EO2)) -> 3.0592964e+10 | EP7: =IF(EP5<0,ESCENARIO[[#This Row],[24-jun]]+EP5,IF(EP5=0,ESCENARIO[[#This Row],[24-jun]]+EP5+EP2)) -> 3.2204641e+10 | EQ7: =IF(EQ5<0,ESCENARIO[[#This Row],[25-jun]]+EQ5,IF(EQ5=0,ESCENARIO[[#This Row],[25-jun]]+EQ5+EQ2)) -> 3.5266177e+10 | ER7: =IF(ER5<0,ESCENARIO[[#This Row],[26-jun]]+ER5,IF(ER5=0,ESCENARIO[[#This Row],[26-jun]]+ER5+ER2)) -> 3.6517345e+10 | ES7: =IF(ES5<0,ESCENARIO[[#This Row],[27-jun]]+ES5,IF(ES5=0,ESCENARIO[[#This Row],[27-jun]]+ES5+ES2)) -> 3.6517345e+10 | ET7: =IF(ET5<0,ESCENARIO[[#This Row],[28-jun]]+ET5,IF(ET5=0,ESCENARIO[[#This Row],[28-jun]]+ET5+ET2)) -> 3.6517345e+10 | EU7: =IF(EU5<0,ESCENARIO[[#This Row],[29-jun]]+EU5,IF(EU5=0,ESCENARIO[[#This Row],[29-jun]]+EU5+EU2)) -> 1.0080987e+10 | EV7: =IF(EV5<0,ESCENARIO[[#This Row],[30-jun]]+EV5,IF(EV5=0,ESCENARIO[[#This Row],[30-jun]]+EV5+EV2)) -> 1.1851196e+10 | EW7: =IF(EW5<0,ESCENARIO[[#This Row],[01-jul]]+EW5,IF(EW5=0,ESCENARIO[[#This Row],[01-jul]]+EW5+EW2)) -> 1.2535347e+10 | EX7: =IF(EX5<0,ESCENARIO[[#This Row],[02-jul]]+EX5,IF(EX5=0,ESCENARIO[[#This Row],[02-jul]]+EX5+EX2)) -> 1.3468682e+10 | EY7: =IF(EY5<0,ESCENARIO[[#This Row],[03-jul]]+EY5,IF(EY5=0,ESCENARIO[[#This Row],[03-jul]]+EY5+EY2)) -> 1.4000347e+10 | EZ7: =IF(EZ5<0,ESCENARIO[[#This Row],[04-jul]]+EZ5,IF(EZ5=0,ESCENARIO[[#This Row],[04-jul]]+EZ5+EZ2)) -> 1.4000347e+10 | FA7: =IF(FA5<0,ESCENARIO[[#This Row],[05-jul]]+FA5,IF(FA5=0,ESCENARIO[[#This Row],[05-jul]]+FA5+FA2)) -> 1.4000347e+10 | FB7: =IF(FB5<0,ESCENARIO[[#This Row],[06-jul]]+FB5,IF(FB5=0,ESCENARIO[[#This Row],[06-jul]]+FB5+FB2)) -> 1.3564787e+10 | FC7: =IF(FC5<0,ESCENARIO[[#This Row],[07-jul]]+FC5,IF(FC5=0,ESCENARIO[[#This Row],[07-jul]]+FC5+FC2)) -> 1.4437355e+10 | FD7: =IF(FD5<0,ESCENARIO[[#This Row],[08-jul]]+FD5,IF(FD5=0,ESCENARIO[[#This Row],[08-jul]]+FD5+FD2)) -> 1.5958999e+10 | FE7: =IF(FE5<0,ESCENARIO[[#This Row],[09-jul]]+FE5,IF(FE5=0,ESCENARIO[[#This Row],[09-jul]]+FE5+FE2)) -> 1.5958999e+10 | FF7: =IF(FF5<0,ESCENARIO[[#This Row],[10-jul]]+FF5,IF(FF5=0,ESCENARIO[[#This Row],[10-jul]]+FF5+FF2)) -> 1.5958999e+10 | FG7: =IF(FG5<0,ESCENARIO[[#This Row],[11-jul]]+FG5,IF(FG5=0,ESCENARIO[[#This Row],[11-jul]]+FG5+FG2)) -> 1.5958999e+10 | FH7: =IF(FH5<0,ESCENARIO[[#This Row],[12-jul]]+FH5,IF(FH5=0,ESCENARIO[[#This Row],[12-jul]]+FH5+FH2)) -> 1.5958999e+10 | FI7: =IF(FI5<0,ESCENARIO[[#This Row],[13-jul]]+FI5,IF(FI5=0,ESCENARIO[[#This Row],[13-jul]]+FI5+FI2)) -> 2.3699028e+10 | FJ7: =IF(FJ5<0,ESCENARIO[[#This Row],[14-jul]]+FJ5,IF(FJ5=0,ESCENARIO[[#This Row],[14-jul]]+FJ5+FJ2)) -> 2.519818e+10 | FK7: =IF(FK5<0,ESCENARIO[[#This Row],[15-jul]]+FK5,IF(FK5=0,ESCENARIO[[#This Row],[15-jul]]+FK5+FK2)) -> 2.6203758e+10 | FL7: =IF(FL5<0,ESCENARIO[[#This Row],[16-jul]]+FL5,IF(FL5=0,ESCENARIO[[#This Row],[16-jul]]+FL5+FL2)) -> 2.9031618e+10 | FM7: =IF(FM5<0,ESCENARIO[[#This Row],[17-jul]]+FM5,IF(FM5=0,ESCENARIO[[#This Row],[17-jul]]+FM5+FM2)) -> 3.1616675e+10 | FN7: =IF(FN5<0,ESCENARIO[[#This Row],[18-jul]]+FN5,IF(FN5=0,ESCENARIO[[#This Row],[18-jul]]+FN5+FN2)) -> 3.1616675e+10 | FO7: =IF(FO5<0,ESCENARIO[[#This Row],[19-jul]]+FO5,IF(FO5=0,ESCENARIO[[#This Row],[19-jul]]+FO5+FO2)) -> 3.1616675e+10 | FP7: =IF(FP5<0,ESCENARIO[[#This Row],[20-jul]]+FP5,IF(FP5=0,ESCENARIO[[#This Row],[20-jul]]+FP5+FP2)) -> 3.2994823e+10 | FQ7: =IF(FQ5<0,ESCENARIO[[#This Row],[21-jul]]+FQ5,IF(FQ5=0,ESCENARIO[[#This Row],[21-jul]]+FQ5+FQ2)) -> 3.4693183e+10 | FR7: =IF(FR5<0,ESCENARIO[[#This Row],[22-jul]]+FR5,IF(FR5=0,ESCENARIO[[#This Row],[22-jul]]+FR5+FR2)) -> 3.7466272e+10 | FS7: =IF(FS5<0,ESCENARIO[[#This Row],[23-jul]]+FS5,IF(FS5=0,ESCENARIO[[#This Row],[23-jul]]+FS5+FS2)) -> 4.0339752e+10 | FT7: =IF(FT5<0,ESCENARIO[[#This Row],[24-jul]]+FT5,IF(FT5=0,ESCENARIO[[#This Row],[24-jul]]+FT5+FT2)) -> 4.1956801e+10 | FU7: =IF(FU5<0,ESCENARIO[[#This Row],[25-jul]]+FU5,IF(FU5=0,ESCENARIO[[#This Row],[25-jul]]+FU5+FU2)) -> 4.1956801e+10 | FV7: =IF(FV5<0,ESCENARIO[[#This Row],[26-jul]]+FV5,IF(FV5=0,ESCENARIO[[#This Row],[26-jul]]+FV5+FV2)) -> 4.1956801e+10 | FW7: =IF(FW5<0,ESCENARIO[[#This Row],[27-jul]]+FW5,IF(FW5=0,ESCENARIO[[#This Row],[27-jul]]+FW5+FW2)) -> 3.8625287e+10 | FX7: =IF(FX5<0,ESCENARIO[[#This Row],[28-jul]]+FX5,IF(FX5=0,ESCENARIO[[#This Row],[28-jul]]+FX5+FX2)) -> 3.9883847e+10 | FY7: =IF(FY5<0,ESCENARIO[[#This Row],[29-jul]]+FY5,IF(FY5=0,ESCENARIO[[#This Row],[29-jul]]+FY5+FY2)) -> 4.1617847e+10 | FZ7: =IF(FZ5<0,ESCENARIO[[#This Row],[30-jul]]+FZ5,IF(FZ5=0,ESCENARIO[[#This Row],[30-jul]]+FZ5+FZ2)) -> 1.751415e+10 | GA7: =IF(GA5<0,ESCENARIO[[#This Row],[31-jul]]+GA5,IF(GA5=0,ESCENARIO[[#This Row],[31-jul]]+GA5+GA2)) -> 1.8705966e+10 | GB7: =IF(GB5<0,ESCENARIO[[#This Row],[01-ago]]+GB5,IF(GB5=0,ESCENARIO[[#This Row],[01-ago]]+GB5+GB2)) -> 1.8705966e+10 | GC7: =IF(GC5<0,ESCENARIO[[#This Row],[02-ago]]+GC5,IF(GC5=0,ESCENARIO[[#This Row],[02-ago]]+GC5+GC2)) -> 1.8705966e+10 | GD7: =IF(GD5<0,ESCENARIO[[#This Row],[03-ago]]+GD5,IF(GD5=0,ESCENARIO[[#This Row],[03-ago]]+GD5+GD2)) -> 1.8291175e+10 | GE7: =IF(GE5<0,ESCENARIO[[#This Row],[04-ago]]+GE5,IF(GE5=0,ESCENARIO[[#This Row],[04-ago]]+GE5+GE2)) -> 1.9236039e+10 | GF7: =IF(GF5<0,ESCENARIO[[#This Row],[05-ago]]+GF5,IF(GF5=0,ESCENARIO[[#This Row],[05-ago]]+GF5+GF2)) -> 1.9774043e+10 | GG7: =IF(GG5<0,ESCENARIO[[#This Row],[06-ago]]+GG5,IF(GG5=0,ESCENARIO[[#This Row],[06-ago]]+GG5+GG2)) -> 2.0453591e+10 | GH7: =IF(GH5<0,ESCENARIO[[#This Row],[07-ago]]+GH5,IF(GH5=0,ESCENARIO[[#This Row],[07-ago]]+GH5+GH2)) -> 2.1336136e+10 | GI7: =IF(GI5<0,ESCENARIO[[#This Row],[08-ago]]+GI5,IF(GI5=0,ESCENARIO[[#This Row],[08-ago]]+GI5+GI2)) -> 2.1336136e+10 | GJ7: =IF(GJ5<0,ESCENARIO[[#This Row],[09-ago]]+GJ5,IF(GJ5=0,ESCENARIO[[#This Row],[09-ago]]+GJ5+GJ2)) -> 2.1336136e+10 | GK7: =IF(GK5<0,ESCENARIO[[#This Row],[10-ago]]+GK5,IF(GK5=0,ESCENARIO[[#This Row],[10-ago]]+GK5+GK2)) -> 2.2875923e+10 | GL7: =IF(GL5<0,ESCENARIO[[#This Row],[11-ago]]+GL5,IF(GL5=0,ESCENARIO[[#This Row],[11-ago]]+GL5+GL2)) -> 3.0708239e+10 | GM7: =IF(GM5<0,ESCENARIO[[#This Row],[12-ago]]+GM5,IF(GM5=0,ESCENARIO[[#This Row],[12-ago]]+GM5+GM2)) -> 3.2225265e+10 | GN7: =IF(GN5<0,ESCENARIO[[#This Row],[13-ago]]+GN5,IF(GN5=0,ESCENARIO[[#This Row],[13-ago]]+GN5+GN2)) -> 3.2042833e+10 | GO7: =IF(GO5<0,ESCENARIO[[#This Row],[14-ago]]+GO5,IF(GO5=0,ESCENARIO[[#This Row],[14-ago]]+GO5+GO2)) -> 3.4904586e+10 | GP7: =IF(GP5<0,ESCENARIO[[#This Row],[15-ago]]+GP5,IF(GP5=0,ESCENARIO[[#This Row],[15-ago]]+GP5+GP2)) -> 3.4904586e+10 | GQ7: =IF(GQ5<0,ESCENARIO[[#This Row],[16-ago]]+GQ5,IF(GQ5=0,ESCENARIO[[#This Row],[16-ago]]+GQ5+GQ2)) -> 3.4904586e+10 | GR7: =IF(GR5<0,ESCENARIO[[#This Row],[17-ago]]+GR5,IF(GR5=0,ESCENARIO[[#This Row],[17-ago]]+GR5+GR2)) -> 3.7520466e+10 | GS7: =IF(GS5<0,ESCENARIO[[#This Row],[18-ago]]+GS5,IF(GS5=0,ESCENARIO[[#This Row],[18-ago]]+GS5+GS2)) -> 3.8915046e+10 | GT7: =IF(GT5<0,ESCENARIO[[#This Row],[19-ago]]+GT5,IF(GT5=0,ESCENARIO[[#This Row],[19-ago]]+GT5+GT2)) -> 4.0633656e+10 | GU7: =IF(GU5<0,ESCENARIO[[#This Row],[20-ago]]+GU5,IF(GU5=0,ESCENARIO[[#This Row],[20-ago]]+GU5+GU2)) -> 4.343981e+10 | GV7: =IF(GV5<0,ESCENARIO[[#This Row],[21-ago]]+GV5,IF(GV5=0,ESCENARIO[[#This Row],[21-ago]]+GV5+GV2)) -> 4.6347551e+10 | GW7: =IF(GW5<0,ESCENARIO[[#This Row],[22-ago]]+GW5,IF(GW5=0,ESCENARIO[[#This Row],[22-ago]]+GW5+GW2)) -> 4.6347551e+10 | GX7: =IF(GX5<0,ESCENARIO[[#This Row],[23-ago]]+GX5,IF(GX5=0,ESCENARIO[[#This Row],[23-ago]]+GX5+GX2)) -> 4.6347551e+10 | GY7: =IF(GY5<0,ESCENARIO[[#This Row],[24-ago]]+GY5,IF(GY5=0,ESCENARIO[[#This Row],[24-ago]]+GY5+GY2)) -> 4.1600626e+10 | GZ7: =IF(GZ5<0,ESCENARIO[[#This Row],[25-ago]]+GZ5,IF(GZ5=0,ESCENARIO[[#This Row],[25-ago]]+GZ5+GZ2)) -> 4.4713582e+10 | HA7: =IF(HA5<0,ESCENARIO[[#This Row],[26-ago]]+HA5,IF(HA5=0,ESCENARIO[[#This Row],[26-ago]]+HA5+HA2)) -> 4.5983888e+10 | HB7: =IF(HB5<0,ESCENARIO[[#This Row],[27-ago]]+HB5,IF(HB5=0,ESCENARIO[[#This Row],[27-ago]]+HB5+HB2)) -> 4.7738563e+10 | HC7: =IF(HC5<0,ESCENARIO[[#This Row],[28-ago]]+HC5,IF(HC5=0,ESCENARIO[[#This Row],[28-ago]]+HC5+HC2)) -> 4.8327454e+10 | HD7: =IF(HD5<0,ESCENARIO[[#This Row],[29-ago]]+HD5,IF(HD5=0,ESCENARIO[[#This Row],[29-ago]]+HD5+HD2)) -> 4.8327454e+10 | HE7: =IF(HE5<0,ESCENARIO[[#This Row],[30-ago]]+HE5,IF(HE5=0,ESCENARIO[[#This Row],[30-ago]]+HE5+HE2)) -> 2.6544541e+10 | HF7: =IF(HF5<0,ESCENARIO[[#This Row],[31-ago]]+HF5,IF(HF5=0,ESCENARIO[[#This Row],[31-ago]]+HF5+HF2)) -> 2.7748046e+10 | HG7: =IF(HG5<0,ESCENARIO[[#This Row],[01-sep]]+HG5,IF(HG5=0,ESCENARIO[[#This Row],[01-sep]]+HG5+HG2)) -> 2.7748046e+10 | HH7: =IF(HH5<0,ESCENARIO[[#This Row],[02-sep]]+HH5,IF(HH5=0,ESCENARIO[[#This Row],[02-sep]]+HH5+HH2)) -> 2.8463478e+10 | HI7: =IF(HI5<0,ESCENARIO[[#This Row],[03-sep]]+HI5,IF(HI5=0,ESCENARIO[[#This Row],[03-sep]]+HI5+HI2)) -> 2.9439487e+10 | HJ7: =IF(HJ5<0,ESCENARIO[[#This Row],[04-sep]]+HJ5,IF(HJ5=0,ESCENARIO[[#This Row],[04-sep]]+HJ5+HJ2)) -> 2.999546e+10 | HK7: =IF(HK5<0,ESCENARIO[[#This Row],[05-sep]]+HK5,IF(HK5=0,ESCENARIO[[#This Row],[05-sep]]+HK5+HK2)) -> 2.999546e+10 | HL7: =IF(HL5<0,ESCENARIO[[#This Row],[06-sep]]+HL5,IF(HL5=0,ESCENARIO[[#This Row],[06-sep]]+HL5+HL2)) -> 2.999546e+10 | HM7: =IF(HM5<0,ESCENARIO[[#This Row],[07-sep]]+HM5,IF(HM5=0,ESCENARIO[[#This Row],[07-sep]]+HM5+HM2)) -> 2.9595705e+10 | HN7: =IF(HN5<0,ESCENARIO[[#This Row],[08-sep]]+HN5,IF(HN5=0,ESCENARIO[[#This Row],[08-sep]]+HN5+HN2)) -> 3.0508114e+10 | HO7: =IF(HO5<0,ESCENARIO[[#This Row],[09-sep]]+HO5,IF(HO5=0,ESCENARIO[[#This Row],[09-sep]]+HO5+HO2)) -> 3.2099332e+10 | HP7: =IF(HP5<0,ESCENARIO[[#This Row],[10-sep]]+HP5,IF(HP5=0,ESCENARIO[[#This Row],[10-sep]]+HP5+HP2)) -> 4.0193251e+10 | HQ7: =IF(HQ5<0,ESCENARIO[[#This Row],[11-sep]]+HQ5,IF(HQ5=0,ESCENARIO[[#This Row],[11-sep]]+HQ5+HQ2)) -> 4.1760947e+10 | HR7: =IF(HR5<0,ESCENARIO[[#This Row],[12-sep]]+HR5,IF(HR5=0,ESCENARIO[[#This Row],[12-sep]]+HR5+HR2)) -> 4.1760947e+10 | HS7: =IF(HS5<0,ESCENARIO[[#This Row],[13-sep]]+HS5,IF(HS5=0,ESCENARIO[[#This Row],[13-sep]]+HS5+HS2)) -> 4.1760947e+10 | HT7: =IF(HT5<0,ESCENARIO[[#This Row],[14-sep]]+HT5,IF(HT5=0,ESCENARIO[[#This Row],[14-sep]]+HT5+HT2)) -> 4.1362502e+10 | HU7: =IF(HU5<0,ESCENARIO[[#This Row],[15-sep]]+HU5,IF(HU5=0,ESCENARIO[[#This Row],[15-sep]]+HU5+HU2)) -> 4.4320043e+10 | HV7: =IF(HV5<0,ESCENARIO[[#This Row],[16-sep]]+HV5,IF(HV5=0,ESCENARIO[[#This Row],[16-sep]]+HV5+HV2)) -> 4.7023295e+10 | HW7: =IF(HW5<0,ESCENARIO[[#This Row],[17-sep]]+HW5,IF(HW5=0,ESCENARIO[[#This Row],[17-sep]]+HW5+HW2)) -> 4.8464455e+10 | HX7: =IF(HX5<0,ESCENARIO[[#This Row],[18-sep]]+HX5,IF(HX5=0,ESCENARIO[[#This Row],[18-sep]]+HX5+HX2)) -> 5.0240467e+10 | HY7: =IF(HY5<0,ESCENARIO[[#This Row],[19-sep]]+HY5,IF(HY5=0,ESCENARIO[[#This Row],[19-sep]]+HY5+HY2)) -> 5.0240467e+10 | HZ7: =IF(HZ5<0,ESCENARIO[[#This Row],[20-sep]]+HZ5,IF(HZ5=0,ESCENARIO[[#This Row],[20-sep]]+HZ5+HZ2)) -> 5.0240467e+10 | IA7: =IF(IA5<0,ESCENARIO[[#This Row],[21-sep]]+IA5,IF(IA5=0,ESCENARIO[[#This Row],[21-sep]]+IA5+IA2)) -> 4.6778915e+10 | IB7: =IF(IB5<0,ESCENARIO[[#This Row],[22-sep]]+IB5,IF(IB5=0,ESCENARIO[[#This Row],[22-sep]]+IB5+IB2)) -> 4.9787124e+10 | IC7: =IF(IC5<0,ESCENARIO[[#This Row],[23-sep]]+IC5,IF(IC5=0,ESCENARIO[[#This Row],[23-sep]]+IC5+IC2)) -> 5.1478108e+10 | ID7: =IF(ID5<0,ESCENARIO[[#This Row],[24-sep]]+ID5,IF(ID5=0,ESCENARIO[[#This Row],[24-sep]]+ID5+ID2)) -> 5.4690295e+10 | IE7: =IF(IE5<0,ESCENARIO[[#This Row],[25-sep]]+IE5,IF(IE5=0,ESCENARIO[[#This Row],[25-sep]]+IE5+IE2)) -> 5.600303e+10 | IF7: =IF(IF5<0,ESCENARIO[[#This Row],[26-sep]]+IF5,IF(IF5=0,ESCENARIO[[#This Row],[26-sep]]+IF5+IF2)) -> 5.600303e+10 | IG7: =IF(IG5<0,ESCENARIO[[#This Row],[27-sep]]+IG5,IF(IG5=0,ESCENARIO[[#This Row],[27-sep]]+IG5+IG2)) -> 5.600303e+10 | IH7: =IF(IH5<0,ESCENARIO[[#This Row],[28-sep]]+IH5,IF(IH5=0,ESCENARIO[[#This Row],[28-sep]]+IH5+IH2)) -> 5.7816312e+10 | II7: =IF(II5<0,ESCENARIO[[#This Row],[29-sep]]+II5,IF(II5=0,ESCENARIO[[#This Row],[29-sep]]+II5+II2)) -> 3.7261143e+10 | IJ7: =IF(IJ5<0,ESCENARIO[[#This Row],[30-sep]]+IJ5,IF(IJ5=0,ESCENARIO[[#This Row],[30-sep]]+IJ5+IJ2)) -> 3.8502954e+10 | IK7: =IF(IK5<0,ESCENARIO[[#This Row],[01-oct]]+IK5,IF(IK5=0,ESCENARIO[[#This Row],[01-oct]]+IK5+IK2)) -> 3.9248266e+10 | IL7: =IF(IL5<0,ESCENARIO[[#This Row],[02-oct]]+IL5,IF(IL5=0,ESCENARIO[[#This Row],[02-oct]]+IL5+IL2)) -> 4.0265037e+10 | IM7: =IF(IM5<0,ESCENARIO[[#This Row],[03-oct]]+IM5,IF(IM5=0,ESCENARIO[[#This Row],[03-oct]]+IM5+IM2)) -> 4.0265037e+10 | IN7: =IF(IN5<0,ESCENARIO[[#This Row],[04-oct]]+IN5,IF(IN5=0,ESCENARIO[[#This Row],[04-oct]]+IN5+IN2)) -> 4.0265037e+10 | IO7: =IF(IO5<0,ESCENARIO[[#This Row],[05-oct]]+IO5,IF(IO5=0,ESCENARIO[[#This Row],[05-oct]]+IO5+IO2)) -> 3.9737131e+10 | IP7: =IF(IP5<0,ESCENARIO[[#This Row],[06-oct]]+IP5,IF(IP5=0,ESCENARIO[[#This Row],[06-oct]]+IP5+IP2)) -> 4.0469215e+10 | IQ7: =IF(IQ5<0,ESCENARIO[[#This Row],[07-oct]]+IQ5,IF(IQ5=0,ESCENARIO[[#This Row],[07-oct]]+IQ5+IQ2)) -> 4.1419328e+10 | IR7: =IF(IR5<0,ESCENARIO[[#This Row],[08-oct]]+IR5,IF(IR5=0,ESCENARIO[[#This Row],[08-oct]]+IR5+IR2)) -> 4.3077002e+10 | IS7: =IF(IS5<0,ESCENARIO[[#This Row],[09-oct]]+IS5,IF(IS5=0,ESCENARIO[[#This Row],[09-oct]]+IS5+IS2)) -> 5.150896e+10 | IT7: =IF(IT5<0,ESCENARIO[[#This Row],[10-oct]]+IT5,IF(IT5=0,ESCENARIO[[#This Row],[10-oct]]+IT5+IT2)) -> 5.150896e+10 | IU7: =IF(IU5<0,ESCENARIO[[#This Row],[11-oct]]+IU5,IF(IU5=0,ESCENARIO[[#This Row],[11-oct]]+IU5+IU2)) -> 5.150896e+10 | IV7: =IF(IV5<0,ESCENARIO[[#This Row],[12-oct]]+IV5,IF(IV5=0,ESCENARIO[[#This Row],[12-oct]]+IV5+IV2)) -> 5.040696e+10 | IW7: =IF(IW5<0,ESCENARIO[[#This Row],[13-oct]]+IW5,IF(IW5=0,ESCENARIO[[#This Row],[13-oct]]+IW5+IW2)) -> 5.2041195e+10 | IX7: =IF(IX5<0,ESCENARIO[[#This Row],[14-oct]]+IX5,IF(IX5=0,ESCENARIO[[#This Row],[14-oct]]+IX5+IX2)) -> 5.1686668e+10 | IY7: =IF(IY5<0,ESCENARIO[[#This Row],[15-oct]]+IY5,IF(IY5=0,ESCENARIO[[#This Row],[15-oct]]+IY5+IY2)) -> 5.476767e+10 | IZ7: =IF(IZ5<0,ESCENARIO[[#This Row],[16-oct]]+IZ5,IF(IZ5=0,ESCENARIO[[#This Row],[16-oct]]+IZ5+IZ2)) -> 5.7583822e+10 | JA7: =IF(JA5<0,ESCENARIO[[#This Row],[17-oct]]+JA5,IF(JA5=0,ESCENARIO[[#This Row],[17-oct]]+JA5+JA2)) -> 5.7583822e+10 | JB7: =IF(JB5<0,ESCENARIO[[#This Row],[18-oct]]+JB5,IF(JB5=0,ESCENARIO[[#This Row],[18-oct]]+JB5+JB2)) -> 5.7583822e+10 | JC7: =IF(JC5<0,ESCENARIO[[#This Row],[19-oct]]+JC5,IF(JC5=0,ESCENARIO[[#This Row],[19-oct]]+JC5+JC2)) -> 5.9085171e+10 | JD7: =IF(JD5<0,ESCENARIO[[#This Row],[20-oct]]+JD5,IF(JD5=0,ESCENARIO[[#This Row],[20-oct]]+JD5+JD2)) -> 6.0935358e+10 | JE7: =IF(JE5<0,ESCENARIO[[#This Row],[21-oct]]+JE5,IF(JE5=0,ESCENARIO[[#This Row],[21-oct]]+JE5+JE2)) -> 6.395635e+10 | JF7: =IF(JF5<0,ESCENARIO[[#This Row],[22-oct]]+JF5,IF(JF5=0,ESCENARIO[[#This Row],[22-oct]]+JF5+JF2)) -> 6.7086709e+10 | JG7: =IF(JG5<0,ESCENARIO[[#This Row],[23-oct]]+JG5,IF(JG5=0,ESCENARIO[[#This Row],[23-oct]]+JG5+JG2)) -> 6.8848316e+10 | JH7: =IF(JH5<0,ESCENARIO[[#This Row],[24-oct]]+JH5,IF(JH5=0,ESCENARIO[[#This Row],[24-oct]]+JH5+JH2)) -> 6.8848316e+10 | JI7: =IF(JI5<0,ESCENARIO[[#This Row],[25-oct]]+JI5,IF(JI5=0,ESCENARIO[[#This Row],[25-oct]]+JI5+JI2)) -> 6.8848316e+10 | JJ7: =IF(JJ5<0,ESCENARIO[[#This Row],[26-oct]]+JJ5,IF(JJ5=0,ESCENARIO[[#This Row],[26-oct]]+JJ5+JJ2)) -> 6.5841404e+10 | JK7: =IF(JK5<0,ESCENARIO[[#This Row],[27-oct]]+JK5,IF(JK5=0,ESCENARIO[[#This Row],[27-oct]]+JK5+JK2)) -> 6.7211872e+10 | JL7: =IF(JL5<0,ESCENARIO[[#This Row],[28-oct]]+JL5,IF(JL5=0,ESCENARIO[[#This Row],[28-oct]]+JL5+JL2)) -> 6.9100885e+10 | JM7: =IF(JM5<0,ESCENARIO[[#This Row],[29-oct]]+JM5,IF(JM5=0,ESCENARIO[[#This Row],[29-oct]]+JM5+JM2)) -> 4.9245387e+10 | JN7: =IF(JN5<0,ESCENARIO[[#This Row],[30-oct]]+JN5,IF(JN5=0,ESCENARIO[[#This Row],[30-oct]]+JN5+JN2)) -> 5.0537556e+10 | JO7: =IF(JO5<0,ESCENARIO[[#This Row],[31-oct]]+JO5,IF(JO5=0,ESCENARIO[[#This Row],[31-oct]]+JO5+JO2)) -> 5.0537556e+10 | JP7: =IF(JP5<0,ESCENARIO[[#This Row],[01-nov]]+JP5,IF(JP5=0,ESCENARIO[[#This Row],[01-nov]]+JP5+JP2)) -> 5.0537556e+10 | JQ7: =IF(JQ5<0,ESCENARIO[[#This Row],[02-nov]]+JQ5,IF(JQ5=0,ESCENARIO[[#This Row],[02-nov]]+JQ5+JQ2)) -> 5.0186711e+10 | JR7: =IF(JR5<0,ESCENARIO[[#This Row],[03-nov]]+JR5,IF(JR5=0,ESCENARIO[[#This Row],[03-nov]]+JR5+JR2)) -> 5.1218752e+10 | JS7: =IF(JS5<0,ESCENARIO[[#This Row],[04-nov]]+JS5,IF(JS5=0,ESCENARIO[[#This Row],[04-nov]]+JS5+JS2)) -> 5.180645e+10 | JT7: =IF(JT5<0,ESCENARIO[[#This Row],[05-nov]]+JT5,IF(JT5=0,ESCENARIO[[#This Row],[05-nov]]+JT5+JT2)) -> 5.2548765e+10 | JU7: =IF(JU5<0,ESCENARIO[[#This Row],[06-nov]]+JU5,IF(JU5=0,ESCENARIO[[#This Row],[06-nov]]+JU5+JU2)) -> 5.3512829e+10 | JV7: =IF(JV5<0,ESCENARIO[[#This Row],[07-nov]]+JV5,IF(JV5=0,ESCENARIO[[#This Row],[07-nov]]+JV5+JV2)) -> 5.3512829e+10 | JW7: =IF(JW5<0,ESCENARIO[[#This Row],[08-nov]]+JW5,IF(JW5=0,ESCENARIO[[#This Row],[08-nov]]+JW5+JW2)) -> 5.3512829e+10 | JX7: =IF(JX5<0,ESCENARIO[[#This Row],[09-nov]]+JX5,IF(JX5=0,ESCENARIO[[#This Row],[09-nov]]+JX5+JX2)) -> 5.5194844e+10 | JY7: =IF(JY5<0,ESCENARIO[[#This Row],[10-nov]]+JY5,IF(JY5=0,ESCENARIO[[#This Row],[10-nov]]+JY5+JY2)) -> 6.3750613e+10 | JZ7: =IF(JZ5<0,ESCENARIO[[#This Row],[11-nov]]+JZ5,IF(JZ5=0,ESCENARIO[[#This Row],[11-nov]]+JZ5+JZ2)) -> 6.5407763e+10 | KA7: =IF(KA5<0,ESCENARIO[[#This Row],[12-nov]]+KA5,IF(KA5=0,ESCENARIO[[#This Row],[12-nov]]+KA5+KA2)) -> 6.5319321e+10 | KB7: =IF(KB5<0,ESCENARIO[[#This Row],[13-nov]]+KB5,IF(KB5=0,ESCENARIO[[#This Row],[13-nov]]+KB5+KB2)) -> 6.8445302e+10 | KC7: =IF(KC5<0,ESCENARIO[[#This Row],[14-nov]]+KC5,IF(KC5=0,ESCENARIO[[#This Row],[14-nov]]+KC5+KC2)) -> 6.8195302e+10 | KD7: =IF(KD5<0,ESCENARIO[[#This Row],[15-nov]]+KD5,IF(KD5=0,ESCENARIO[[#This Row],[15-nov]]+KD5+KD2)) -> 6.8195544e+10 | KE7: =IF(KE5<0,ESCENARIO[[#This Row],[16-nov]]+KE5,IF(KE5=0,ESCENARIO[[#This Row],[16-nov]]+KE5+KE2)) -> 7.1053047e+10 | KF7: =IF(KF5<0,ESCENARIO[[#This Row],[17-nov]]+KF5,IF(KF5=0,ESCENARIO[[#This Row],[17-nov]]+KF5+KF2)) -> 7.2576441e+10 | KG7: =IF(KG5<0,ESCENARIO[[#This Row],[18-nov]]+KG5,IF(KG5=0,ESCENARIO[[#This Row],[18-nov]]+KG5+KG2)) -> 7.4453795e+10 | KH7: =IF(KH5<0,ESCENARIO[[#This Row],[19-nov]]+KH5,IF(KH5=0,ESCENARIO[[#This Row],[19-nov]]+KH5+KH2)) -> 7.7519147e+10 | KI7: =IF(KI5<0,ESCENARIO[[#This Row],[20-nov]]+KI5,IF(KI5=0,ESCENARIO[[#This Row],[20-nov]]+KI5+KI2)) -> 8.069547e+10 | KJ7: =IF(KJ5<0,ESCENARIO[[#This Row],[21-nov]]+KJ5,IF(KJ5=0,ESCENARIO[[#This Row],[21-nov]]+KJ5+KJ2)) -> 8.069547e+10 | KK7: =IF(KK5<0,ESCENARIO[[#This Row],[22-nov]]+KK5,IF(KK5=0,ESCENARIO[[#This Row],[22-nov]]+KK5+KK2)) -> 8.069547e+10 | KL7: =IF(KL5<0,ESCENARIO[[#This Row],[23-nov]]+KL5,IF(KL5=0,ESCENARIO[[#This Row],[23-nov]]+KL5+KL2)) -> 7.4342215e+10 | KM7: =IF(KM5<0,ESCENARIO[[#This Row],[24-nov]]+KM5,IF(KM5=0,ESCENARIO[[#This Row],[24-nov]]+KM5+KM2)) -> 7.6135832e+10 | KN7: =IF(KN5<0,ESCENARIO[[#This Row],[25-nov]]+KN5,IF(KN5=0,ESCENARIO[[#This Row],[25-nov]]+KN5+KN2)) -> 7.9531311e+10 | KO7: =IF(KO5<0,ESCENARIO[[#This Row],[26-nov]]+KO5,IF(KO5=0,ESCENARIO[[#This Row],[26-nov]]+KO5+KO2)) -> 8.0918953e+10 | KP7: =IF(KP5<0,ESCENARIO[[#This Row],[27-nov]]+KP5,IF(KP5=0,ESCENARIO[[#This Row],[27-nov]]+KP5+KP2)) -> 8.2835703e+10 | KQ7: =IF(KQ5<0,ESCENARIO[[#This Row],[28-nov]]+KQ5,IF(KQ5=0,ESCENARIO[[#This Row],[28-nov]]+KQ5+KQ2)) -> 8.2835703e+10 | KR7: =IF(KR5<0,ESCENARIO[[#This Row],[29-nov]]+KR5,IF(KR5=0,ESCENARIO[[#This Row],[29-nov]]+KR5+KR2)) -> 6.228657e+10 | KS7: =IF(KS5<0,ESCENARIO[[#This Row],[30-nov]]+KS5,IF(KS5=0,ESCENARIO[[#This Row],[30-nov]]+KS5+KS2)) -> 6.4241386e+10 | KT7: =IF(KT5<0,ESCENARIO[[#This Row],[01-dic]]+KT5,IF(KT5=0,ESCENARIO[[#This Row],[01-dic]]+KT5+KT2)) -> 6.5032791e+10 | KU7: =IF(KU5<0,ESCENARIO[[#This Row],[02-dic]]+KU5,IF(KU5=0,ESCENARIO[[#This Row],[02-dic]]+KU5+KU2)) -> 6.6112444e+10 | KV7: =IF(KV5<0,ESCENARIO[[#This Row],[03-dic]]+KV5,IF(KV5=0,ESCENARIO[[#This Row],[03-dic]]+KV5+KV2)) -> 6.6727457e+10 | KW7: =IF(KW5<0,ESCENARIO[[#This Row],[04-dic]]+KW5,IF(KW5=0,ESCENARIO[[#This Row],[04-dic]]+KW5+KW2)) -> 6.7504274e+10 | KX7: =IF(KX5<0,ESCENARIO[[#This Row],[05-dic]]+KX5,IF(KX5=0,ESCENARIO[[#This Row],[05-dic]]+KX5+KX2)) -> 6.7504274e+10 | KY7: =IF(KY5<0,ESCENARIO[[#This Row],[06-dic]]+KY5,IF(KY5=0,ESCENARIO[[#This Row],[06-dic]]+KY5+KY2)) -> 6.7504274e+10 | KZ7: =IF(KZ5<0,ESCENARIO[[#This Row],[07-dic]]+KZ5,IF(KZ5=0,ESCENARIO[[#This Row],[07-dic]]+KZ5+KZ2)) -> 6.7504274e+10 | LA7: =IF(LA5<0,ESCENARIO[[#This Row],[08-dic]]+LA5,IF(LA5=0,ESCENARIO[[#This Row],[08-dic]]+LA5+LA2)) -> 6.6402274e+10 | LB7: =IF(LB5<0,ESCENARIO[[#This Row],[09-dic]]+LB5,IF(LB5=0,ESCENARIO[[#This Row],[09-dic]]+LB5+LB2)) -> 6.7412211e+10 | LC7: =IF(LC5<0,ESCENARIO[[#This Row],[10-dic]]+LC5,IF(LC5=0,ESCENARIO[[#This Row],[10-dic]]+LC5+LC2)) -> 6.9172402e+10 | LD7: =IF(LD5<0,ESCENARIO[[#This Row],[11-dic]]+LD5,IF(LD5=0,ESCENARIO[[#This Row],[11-dic]]+LD5+LD2)) -> 7.8125825e+10 | LE7: =IF(LE5<0,ESCENARIO[[#This Row],[12-dic]]+LE5,IF(LE5=0,ESCENARIO[[#This Row],[12-dic]]+LE5+LE2)) -> 7.8125825e+10 | LF7: =IF(LF5<0,ESCENARIO[[#This Row],[13-dic]]+LF5,IF(LF5=0,ESCENARIO[[#This Row],[13-dic]]+LF5+LF2)) -> 7.8125825e+10 | LG7: =IF(LG5<0,ESCENARIO[[#This Row],[14-dic]]+LG5,IF(LG5=0,ESCENARIO[[#This Row],[14-dic]]+LG5+LG2)) -> 7.9859996e+10 | LH7: =IF(LH5<0,ESCENARIO[[#This Row],[15-dic]]+LH5,IF(LH5=0,ESCENARIO[[#This Row],[15-dic]]+LH5+LH2)) -> 8.1023217e+10 | LI7: =IF(LI5<0,ESCENARIO[[#This Row],[16-dic]]+LI5,IF(LI5=0,ESCENARIO[[#This Row],[16-dic]]+LI5+LI2)) -> 8.4294397e+10 | LJ7: =IF(LJ5<0,ESCENARIO[[#This Row],[17-dic]]+LJ5,IF(LJ5=0,ESCENARIO[[#This Row],[17-dic]]+LJ5+LJ2)) -> 8.728471e+10 | LK7: =IF(LK5<0,ESCENARIO[[#This Row],[18-dic]]+LK5,IF(LK5=0,ESCENARIO[[#This Row],[18-dic]]+LK5+LK2)) -> 8.8878909e+10 | LL7: =IF(LL5<0,ESCENARIO[[#This Row],[19-dic]]+LL5,IF(LL5=0,ESCENARIO[[#This Row],[19-dic]]+LL5+LL2)) -> 8.8878909e+10 | LM7: =IF(LM5<0,ESCENARIO[[#This Row],[20-dic]]+LM5,IF(LM5=0,ESCENARIO[[#This Row],[20-dic]]+LM5+LM2)) -> 8.8878909e+10 | LN7: =IF(LN5<0,ESCENARIO[[#This Row],[21-dic]]+LN5,IF(LN5=0,ESCENARIO[[#This Row],[21-dic]]+LN5+LN2)) -> 9.0843518e+10 | LO7: =IF(LO5<0,ESCENARIO[[#This Row],[22-dic]]+LO5,IF(LO5=0,ESCENARIO[[#This Row],[22-dic]]+LO5+LO2)) -> 8.7698086e+10 | LP7: =IF(LP5<0,ESCENARIO[[#This Row],[23-dic]]+LP5,IF(LP5=0,ESCENARIO[[#This Row],[23-dic]]+LP5+LP2)) -> 9.102508e+10 | LQ7: =IF(LQ5<0,ESCENARIO[[#This Row],[24-dic]]+LQ5,IF(LQ5=0,ESCENARIO[[#This Row],[24-dic]]+LQ5+LQ2)) -> 9.2895631e+10 | LR7: =IF(LR5<0,ESCENARIO[[#This Row],[25-dic]]+LR5,IF(LR5=0,ESCENARIO[[#This Row],[25-dic]]+LR5+LR2)) -> 9.2895631e+10 | LS7: =IF(LS5<0,ESCENARIO[[#This Row],[26-dic]]+LS5,IF(LS5=0,ESCENARIO[[#This Row],[26-dic]]+LS5+LS2)) -> 9.2895631e+10 | LT7: =IF(LT5<0,ESCENARIO[[#This Row],[27-dic]]+LT5,IF(LT5=0,ESCENARIO[[#This Row],[27-dic]]+LT5+LT2)) -> 9.2895631e+10 | LU7: =IF(LU5<0,ESCENARIO[[#This Row],[28-dic]]+LU5,IF(LU5=0,ESCENARIO[[#This Row],[28-dic]]+LU5+LU2)) -> 9.6448925e+10 | LV7: =IF(LV5<0,ESCENARIO[[#This Row],[29-dic]]+LV5,IF(LV5=0,ESCENARIO[[#This Row],[29-dic]]+LV5+LV2)) -> 7.3519375e+10 | LW7: =IF(LW5<0,ESCENARIO[[#This Row],[30-dic]]+LW5,IF(LW5=0,ESCENARIO[[#This Row],[30-dic]]+LW5+LW2)) -> 7.5547384e+10 | LX7: =SUM(ESCENARIO[[#This Row],[01-mar]:[31-dic]]) -> 1.1174262e+13
A8: INTERESES ACUMULADOS | B8: =+B6 -> 0 | C8: =+C6-C9 -> 2070444.7 | D8: =(IF(D7>0,+ESCENARIO[[#This Row],[02-feb]]+D6,0))-D9 -> 3360464 | E8: =IF(E7>0,+ESCENARIO[[#This Row],[03-feb]]+E6,0) -> 4650483.4 | F8: =IF(F7>0,+ESCENARIO[[#This Row],[04-feb]]+F6,0) -> 6785475.4 | G8: =IF(G7>0,+ESCENARIO[[#This Row],[05-feb]]+G6,0) -> 9401367.4 | H8: =IF(H7>0,+ESCENARIO[[#This Row],[06-feb]]+H6,0) -> 12624680 | I8: =IF(I7>0,+ESCENARIO[[#This Row],[07-feb]]+I6,0) -> 16636864 | J8: =IF(J7>0,+ESCENARIO[[#This Row],[08-feb]]+J6,0) -> 20649048 | K8: =IF(K7>0,+ESCENARIO[[#This Row],[09-feb]]+K6,0) -> 24661232 | L8: =IF(L7>0,+ESCENARIO[[#This Row],[10-feb]]+L6,0) -> 30049771 | M8: =IF(M7>0,+ESCENARIO[[#This Row],[11-feb]]+M6,0) -> 42439304 | N8: =IF(N7>0,+ESCENARIO[[#This Row],[12-feb]]+N6,0) -> 56184846 | O8: =IF(O7>0,+ESCENARIO[[#This Row],[13-feb]]+O6,0) -> 69590672 | P8: =IF(P7>0,+ESCENARIO[[#This Row],[14-feb]]+P6,0) -> 85554676 | Q8: =IF(Q7>0,+ESCENARIO[[#This Row],[15-feb]]+Q6,0) -> 1.0129144e+08 | R8: =IF(R7>0,+ESCENARIO[[#This Row],[16-feb]]+R6,0) -> 1.1702841e+08 | S8: =IF(S7>0,+ESCENARIO[[#This Row],[17-feb]]+S6,0) -> 1.3510362e+08 | T8: =IF(T7>0,+ESCENARIO[[#This Row],[18-feb]]+T6,0) -> 1.5442539e+08 | U8: =IF(U7>0,+ESCENARIO[[#This Row],[19-feb]]+U6,0) -> 1.7528336e+08 | V8: =IF(V7>0,+ESCENARIO[[#This Row],[20-feb]]+V6,0) -> 1.9864963e+08 | W8: =IF(W7>0,+ESCENARIO[[#This Row],[21-feb]]+W6,0) -> 2.2461502e+08 | X8: =IF(X7>0,+ESCENARIO[[#This Row],[22-feb]]+X6,0) -> 2.5058041e+08 | Y8: =IF(Y7>0,+ESCENARIO[[#This Row],[23-feb]]+Y6,0) -> 2.765458e+08 | Z8: =IF(Z7>0,+ESCENARIO[[#This Row],[24-feb]]+Z6,0) -> 3.0397383e+08 | AA8: =IF(AA7>0,+ESCENARIO[[#This Row],[25-feb]]+AA6,0) -> 3.2726056e+08 | AB8: =IF(AB7>0,+ESCENARIO[[#This Row],[26-feb]]+AB6,0) -> 3.4739107e+08 | AC8: =IF(AC7>0,+ESCENARIO[[#This Row],[27-feb]]+AC6,0) -> 3.5086736e+08 | AD8: =IF(AD7>0,+ESCENARIO[[#This Row],[28-feb]]+AD6,0) -> 3.5264664e+08 | AE8: =IF(AE7>0,+ESCENARIO[[#This Row],[01-mar]]+AE6,0) -> 3.5494617e+08 | AF8: =IF(AF7>0,+ESCENARIO[[#This Row],[02-mar]]+AF6,0) -> 3.5724569e+08 | AG8: =IF(AG7>0,+ESCENARIO[[#This Row],[03-mar]]+AG6,0) -> 3.5910517e+08 | AH8: =IF(AH7>0,+ESCENARIO[[#This Row],[04-mar]]+AH6,0) -> 3.6182523e+08 | AI8: =IF(AI7>0,+ESCENARIO[[#This Row],[05-mar]]+AI6,0) -> 3.6503528e+08 | AJ8: =IF(AJ7>0,+ESCENARIO[[#This Row],[06-mar]]+AJ6,0) -> 3.6886422e+08 | AK8: =IF(AK7>0,+ESCENARIO[[#This Row],[07-mar]]+AK6,0) -> 3.7349694e+08 | AL8: =IF(AL7>0,+ESCENARIO[[#This Row],[08-mar]]+AL6,0) -> 3.7812965e+08 | AM8: =IF(AM7>0,+ESCENARIO[[#This Row],[09-mar]]+AM6,0) -> 3.8276237e+08 | AN8: =IF(AN7>0,+ESCENARIO[[#This Row],[10-mar]]+AN6,0) -> 3.8879743e+08 | AO8: =IF(AO7>0,+ESCENARIO[[#This Row],[11-mar]]+AO6,0) -> 4.0196573e+08 | AP8: =IF(AP7>0,+ESCENARIO[[#This Row],[12-mar]]+AP6,0) -> 4.1651565e+08 | AQ8: =IF(AQ7>0,+ESCENARIO[[#This Row],[13-mar]]+AQ6,0) -> 4.3083191e+08 | AR8: =IF(AR7>0,+ESCENARIO[[#This Row],[14-mar]]+AR6,0) -> 4.4775456e+08 | AS8: =IF(AS7>0,+ESCENARIO[[#This Row],[15-mar]]+AS6,0) -> 4.6443546e+08 | AT8: =IF(AT7>0,+ESCENARIO[[#This Row],[16-mar]]+AT6,0) -> 4.8111659e+08 | AU8: =IF(AU7>0,+ESCENARIO[[#This Row],[17-mar]]+AU6,0) -> 5.0018012e+08 | AV8: =IF(AV7>0,+ESCENARIO[[#This Row],[18-mar]]+AV6,0) -> 5.2051375e+08 | AW8: =IF(AW7>0,+ESCENARIO[[#This Row],[19-mar]]+AW6,0) -> 5.404786e+08 | AX8: =IF(AX7>0,+ESCENARIO[[#This Row],[20-mar]]+AX6,0) -> 5.6299949e+08 | AY8: =IF(AY7>0,+ESCENARIO[[#This Row],[21-mar]]+AY6,0) -> 5.8816859e+08 | AZ8: =IF(AZ7>0,+ESCENARIO[[#This Row],[22-mar]]+AZ6,0) -> 6.1482796e+08 | BA8: =IF(BA7>0,+ESCENARIO[[#This Row],[23-mar]]+BA6,0) -> 6.4431826e+08 | BB8: =IF(BB7>0,+ESCENARIO[[#This Row],[24-mar]]+BB6,0) -> 6.6638079e+08 | BC8: =IF(BC7>0,+ESCENARIO[[#This Row],[25-mar]]+BC6,0) -> 6.884505e+08 | BD8: =IF(BD7>0,+ESCENARIO[[#This Row],[26-mar]]+BD6,0) -> 7.1167714e+08 | BE8: =IF(BE7>0,+ESCENARIO[[#This Row],[27-mar]]+BE6,0) -> 7.3650184e+08 | BF8: =IF(BF7>0,+ESCENARIO[[#This Row],[28-mar]]+BF6,0) -> 7.6186287e+08 | BG8: =IF(BG7>0,+ESCENARIO[[#This Row],[29-mar]]+BG6,0) -> 7.8722389e+08 | BH8: =IF(BH7>0,+ESCENARIO[[#This Row],[30-mar]]+BH6,0) -> 8.0586241e+08 | BI8: =IF(BI7>0,+ESCENARIO[[#This Row],[31-mar]]+BI6,0) -> 8.0614818e+08 | BJ8: =IF(BJ7>0,+ESCENARIO[[#This Row],[01-abr]]+BJ6,0) -> 8.064517e+08 | BK8: =IF(BK7>0,+ESCENARIO[[#This Row],[02-abr]]+BK6,0) -> 8.0739534e+08 | BL8: =IF(BL7>0,+ESCENARIO[[#This Row],[03-abr]]+BL6,0) -> 8.0833897e+08 | BM8: =IF(BM7>0,+ESCENARIO[[#This Row],[04-abr]]+BM6,0) -> 8.092826e+08 | BN8: =IF(BN7>0,+ESCENARIO[[#This Row],[05-abr]]+BN6,0) -> 8.1022623e+08 | BO8: =IF(BO7>0,+ESCENARIO[[#This Row],[06-abr]]+BO6,0) -> 8.1116987e+08 | BP8: =IF(BP7>0,+ESCENARIO[[#This Row],[07-abr]]+BP6,0) -> 8.1191619e+08 | BQ8: =IF(BQ7>0,+ESCENARIO[[#This Row],[08-abr]]+BQ6,0) -> 8.1316014e+08 | BR8: =IF(BR7>0,+ESCENARIO[[#This Row],[09-abr]]+BR6,0) -> 8.1503241e+08 | BS8: =IF(BS7>0,+ESCENARIO[[#This Row],[10-abr]]+BS6,0) -> 8.1772068e+08 | BT8: =IF(BT7>0,+ESCENARIO[[#This Row],[11-abr]]+BT6,0) -> 8.2183265e+08 | BU8: =IF(BU7>0,+ESCENARIO[[#This Row],[12-abr]]+BU6,0) -> 8.2594462e+08 | BV8: =IF(BV7>0,+ESCENARIO[[#This Row],[13-abr]]+BV6,0) -> 8.3005659e+08 | BW8: =IF(BW7>0,+ESCENARIO[[#This Row],[14-abr]]+BW6,0) -> 8.4141036e+08 | BX8: =IF(BX7>0,+ESCENARIO[[#This Row],[15-abr]]+BX6,0) -> 8.5416678e+08 | BY8: =IF(BY7>0,+ESCENARIO[[#This Row],[16-abr]]+BY6,0) -> 8.6786405e+08 | BZ8: =IF(BZ7>0,+ESCENARIO[[#This Row],[17-abr]]+BZ6,0) -> 8.8420715e+08 | CA8: =IF(CA7>0,+ESCENARIO[[#This Row],[18-abr]]+CA6,0) -> 9.029689e+08 | CB8: =IF(CB7>0,+ESCENARIO[[#This Row],[19-abr]]+CB6,0) -> 9.2173066e+08 | CC8: =IF(CC7>0,+ESCENARIO[[#This Row],[20-abr]]+CC6,0) -> 9.3855841e+08 | CD8: =IF(CD7>0,+ESCENARIO[[#This Row],[21-abr]]+CD6,0) -> 9.5667747e+08 | CE8: =IF(CE7>0,+ESCENARIO[[#This Row],[22-abr]]+CE6,0) -> 9.7638557e+08 | CF8: =IF(CF7>0,+ESCENARIO[[#This Row],[23-abr]]+CF6,0) -> 9.9868825e+08 | CG8: =IF(CG7>0,+ESCENARIO[[#This Row],[24-abr]]+CG6,0) -> 1.0236794e+09 | CH8: =IF(CH7>0,+ESCENARIO[[#This Row],[25-abr]]+CH6,0) -> 1.0501836e+09 | CI8: =IF(CI7>0,+ESCENARIO[[#This Row],[26-abr]]+CI6,0) -> 1.0766878e+09 | CJ8: =IF(CJ7>0,+ESCENARIO[[#This Row],[27-abr]]+CJ6,0) -> 1.1031919e+09 | CK8: =IF(CK7>0,+ESCENARIO[[#This Row],[28-abr]]+CK6,0) -> 1.1262611e+09 | CL8: =IF(CL7>0,+ESCENARIO[[#This Row],[29-abr]]+CL6,0) -> 1.1505082e+09 | CM8: =IF(CM7>0,+ESCENARIO[[#This Row],[30-abr]]+CM6,0) -> 1.1531592e+09 | CN8: =IF(CN7>0,+ESCENARIO[[#This Row],[01-may]]+CN6,0) -> 1.157469e+09 | CO8: =IF(CO7>0,+ESCENARIO[[#This Row],[02-may]]+CO6,0) -> 1.1617787e+09 | CP8: =IF(CP7>0,+ESCENARIO[[#This Row],[03-may]]+CP6,0) -> 1.1660884e+09 | CQ8: =IF(CQ7>0,+ESCENARIO[[#This Row],[04-may]]+CQ6,0) -> 1.1703982e+09 | CR8: =IF(CR7>0,+ESCENARIO[[#This Row],[05-may]]+CR6,0) -> 1.1743153e+09 | CS8: =IF(CS7>0,+ESCENARIO[[#This Row],[06-may]]+CS6,0) -> 1.1791577e+09 | CT8: =IF(CT7>0,+ESCENARIO[[#This Row],[07-may]]+CT6,0) -> 1.1845269e+09 | CU8: =IF(CU7>0,+ESCENARIO[[#This Row],[08-may]]+CU6,0) -> 1.1905616e+09 | CV8: =IF(CV7>0,+ESCENARIO[[#This Row],[09-may]]+CV6,0) -> 1.1974605e+09 | CW8: =IF(CW7>0,+ESCENARIO[[#This Row],[10-may]]+CW6,0) -> 1.2043594e+09 | CX8: =IF(CX7>0,+ESCENARIO[[#This Row],[11-may]]+CX6,0) -> 1.2112583e+09 | CY8: =IF(CY7>0,+ESCENARIO[[#This Row],[12-may]]+CY6,0) -> 1.2196651e+09 | CZ8: =IF(CZ7>0,+ESCENARIO[[#This Row],[13-may]]+CZ6,0) -> 1.2357418e+09 | DA8: =IF(DA7>0,+ESCENARIO[[#This Row],[14-may]]+DA6,0) -> 1.2533041e+09 | DB8: =IF(DB7>0,+ESCENARIO[[#This Row],[15-may]]+DB6,0) -> 1.2704607e+09 | DC8: =IF(DC7>0,+ESCENARIO[[#This Row],[16-may]]+DC6,0) -> 1.2904199e+09 | DD8: =IF(DD7>0,+ESCENARIO[[#This Row],[17-may]]+DD6,0) -> 1.3103791e+09 | DE8: =IF(DE7>0,+ESCENARIO[[#This Row],[18-may]]+DE6,0) -> 1.3303383e+09 | DF8: =IF(DF7>0,+ESCENARIO[[#This Row],[19-may]]+DF6,0) -> 1.3528592e+09 | DG8: =IF(DG7>0,+ESCENARIO[[#This Row],[20-may]]+DG6,0) -> 1.3767457e+09 | DH8: =IF(DH7>0,+ESCENARIO[[#This Row],[21-may]]+DH6,0) -> 1.4023152e+09 | DI8: =IF(DI7>0,+ESCENARIO[[#This Row],[22-may]]+DI6,0) -> 1.4306327e+09 | DJ8: =IF(DJ7>0,+ESCENARIO[[#This Row],[23-may]]+DJ6,0) -> 1.4617976e+09 | DK8: =IF(DK7>0,+ESCENARIO[[#This Row],[24-may]]+DK6,0) -> 1.4929625e+09 | DL8: =IF(DL7>0,+ESCENARIO[[#This Row],[25-may]]+DL6,0) -> 1.5241274e+09 | DM8: =IF(DM7>0,+ESCENARIO[[#This Row],[26-may]]+DM6,0) -> 1.5487299e+09 | DN8: =IF(DN7>0,+ESCENARIO[[#This Row],[27-may]]+DN6,0) -> 1.5749412e+09 | DO8: =IF(DO7>0,+ESCENARIO[[#This Row],[28-may]]+DO6,0) -> 1.6041964e+09 | DP8: =IF(DP7>0,+ESCENARIO[[#This Row],[29-may]]+DP6,0) -> 1.6103122e+09 | DQ8: =IF(DQ7>0,+ESCENARIO[[#This Row],[30-may]]+DQ6,0) -> 1.6181686e+09 | DR8: =IF(DR7>0,+ESCENARIO[[#This Row],[31-may]]+DR6,0) -> 1.6266018e+09 | DS8: =IF(DS7>0,+ESCENARIO[[#This Row],[01-jun]]+DS6,0) -> 1.6361929e+09 | DT8: =IF(DT7>0,+ESCENARIO[[#This Row],[02-jun]]+DT6,0) -> 1.6447134e+09 | DU8: =IF(DU7>0,+ESCENARIO[[#This Row],[03-jun]]+DU6,0) -> 1.6538943e+09 | DV8: =IF(DV7>0,+ESCENARIO[[#This Row],[04-jun]]+DV6,0) -> 1.6639747e+09 | DW8: =IF(DW7>0,+ESCENARIO[[#This Row],[05-jun]]+DW6,0) -> 1.6745676e+09 | DX8: =IF(DX7>0,+ESCENARIO[[#This Row],[06-jun]]+DX6,0) -> 1.6858077e+09 | DY8: =IF(DY7>0,+ESCENARIO[[#This Row],[07-jun]]+DY6,0) -> 1.6970478e+09 | DZ8: =IF(DZ7>0,+ESCENARIO[[#This Row],[08-jun]]+DZ6,0) -> 1.7082879e+09 | EA8: =IF(EA7>0,+ESCENARIO[[#This Row],[09-jun]]+EA6,0) -> 1.7193029e+09 | EB8: =IF(EB7>0,+ESCENARIO[[#This Row],[10-jun]]+EB6,0) -> 1.7317847e+09 | EC8: =IF(EC7>0,+ESCENARIO[[#This Row],[11-jun]]+EC6,0) -> 1.7517262e+09 | ED8: =IF(ED7>0,+ESCENARIO[[#This Row],[12-jun]]+ED6,0) -> 1.7731126e+09 | EE8: =IF(EE7>0,+ESCENARIO[[#This Row],[13-jun]]+EE6,0) -> 1.7954681e+09 | EF8: =IF(EF7>0,+ESCENARIO[[#This Row],[14-jun]]+EF6,0) -> 1.8178237e+09 | EG8: =IF(EG7>0,+ESCENARIO[[#This Row],[15-jun]]+EG6,0) -> 1.8399375e+09 | EH8: =IF(EH7>0,+ESCENARIO[[#This Row],[16-jun]]+EH6,0) -> 1.8620515e+09 | EI8: =IF(EI7>0,+ESCENARIO[[#This Row],[17-jun]]+EI6,0) -> 1.886891e+09 | EJ8: =IF(EJ7>0,+ESCENARIO[[#This Row],[18-jun]]+EJ6,0) -> 1.9142219e+09 | EK8: =IF(EK7>0,+ESCENARIO[[#This Row],[19-jun]]+EK6,0) -> 1.9428811e+09 | EL8: =IF(EL7>0,+ESCENARIO[[#This Row],[20-jun]]+EL6,0) -> 1.9731772e+09 | EM8: =IF(EM7>0,+ESCENARIO[[#This Row],[21-jun]]+EM6,0) -> 2.0034732e+09 | EN8: =IF(EN7>0,+ESCENARIO[[#This Row],[22-jun]]+EN6,0) -> 2.0337692e+09 | EO8: =IF(EO7>0,+ESCENARIO[[#This Row],[23-jun]]+EO6,0) -> 2.0605798e+09 | EP8: =IF(EP7>0,+ESCENARIO[[#This Row],[24-jun]]+EP6,0) -> 2.0901632e+09 | EQ8: =IF(EQ7>0,+ESCENARIO[[#This Row],[25-jun]]+EQ6,0) -> 2.1213051e+09 | ER8: =IF(ER7>0,+ESCENARIO[[#This Row],[26-jun]]+ER6,0) -> 2.1554075e+09 | ES8: =IF(ES7>0,+ESCENARIO[[#This Row],[27-jun]]+ES6,0) -> 2.1907198e+09 | ET8: =IF(ET7>0,+ESCENARIO[[#This Row],[28-jun]]+ET6,0) -> 2.226032e+09 | EU8: =IF(EU7>0,+ESCENARIO[[#This Row],[29-jun]]+EU6,0) -> 2.2613443e+09 | EV8: =IF(EV7>0,+ESCENARIO[[#This Row],[30-jun]]+EV6,0) -> 2.2710926e+09 | EW8: =IF(EW7>0,+ESCENARIO[[#This Row],[01-jul]]+EW6,0) -> 2.2825527e+09 | EX8: =IF(EX7>0,+ESCENARIO[[#This Row],[02-jul]]+EX6,0) -> 2.2946744e+09 | EY8: =IF(EY7>0,+ESCENARIO[[#This Row],[03-jul]]+EY6,0) -> 2.3076986e+09 | EZ8: =IF(EZ7>0,+ESCENARIO[[#This Row],[04-jul]]+EZ6,0) -> 2.321237e+09 | FA8: =IF(FA7>0,+ESCENARIO[[#This Row],[05-jul]]+FA6,0) -> 2.3347753e+09 | FB8: =IF(FB7>0,+ESCENARIO[[#This Row],[06-jul]]+FB6,0) -> 2.3483136e+09 | FC8: =IF(FC7>0,+ESCENARIO[[#This Row],[07-jul]]+FC6,0) -> 2.3614308e+09 | FD8: =IF(FD7>0,+ESCENARIO[[#This Row],[08-jul]]+FD6,0) -> 2.3753917e+09 | FE8: =IF(FE7>0,+ESCENARIO[[#This Row],[09-jul]]+FE6,0) -> 2.3908241e+09 | FF8: =IF(FF7>0,+ESCENARIO[[#This Row],[10-jul]]+FF6,0) -> 2.4062564e+09 | FG8: =IF(FG7>0,+ESCENARIO[[#This Row],[11-jul]]+FG6,0) -> 2.4216888e+09 | FH8: =IF(FH7>0,+ESCENARIO[[#This Row],[12-jul]]+FH6,0) -> 2.4371211e+09 | FI8: =IF(FI7>0,+ESCENARIO[[#This Row],[13-jul]]+FI6,0) -> 2.4525535e+09 | FJ8: =IF(FJ7>0,+ESCENARIO[[#This Row],[14-jul]]+FJ6,0) -> 2.4754704e+09 | FK8: =IF(FK7>0,+ESCENARIO[[#This Row],[15-jul]]+FK6,0) -> 2.4998371e+09 | FL8: =IF(FL7>0,+ESCENARIO[[#This Row],[16-jul]]+FL6,0) -> 2.5251761e+09 | FM8: =IF(FM7>0,+ESCENARIO[[#This Row],[17-jul]]+FM6,0) -> 2.5532497e+09 | FN8: =IF(FN7>0,+ESCENARIO[[#This Row],[18-jul]]+FN6,0) -> 2.583823e+09 | FO8: =IF(FO7>0,+ESCENARIO[[#This Row],[19-jul]]+FO6,0) -> 2.6143963e+09 | FP8: =IF(FP7>0,+ESCENARIO[[#This Row],[20-jul]]+FP6,0) -> 2.6449697e+09 | FQ8: =IF(FQ7>0,+ESCENARIO[[#This Row],[21-jul]]+FQ6,0) -> 2.6768756e+09 | FR8: =IF(FR7>0,+ESCENARIO[[#This Row],[22-jul]]+FR6,0) -> 2.710424e+09 | FS8: =IF(FS7>0,+ESCENARIO[[#This Row],[23-jul]]+FS6,0) -> 2.7466538e+09 | FT8: =IF(FT7>0,+ESCENARIO[[#This Row],[24-jul]]+FT6,0) -> 2.7856624e+09 | FU8: =IF(FU7>0,+ESCENARIO[[#This Row],[25-jul]]+FU6,0) -> 2.8262346e+09 | FV8: =IF(FV7>0,+ESCENARIO[[#This Row],[26-jul]]+FV6,0) -> 2.8668068e+09 | FW8: =IF(FW7>0,+ESCENARIO[[#This Row],[27-jul]]+FW6,0) -> 2.9073791e+09 | FX8: =IF(FX7>0,+ESCENARIO[[#This Row],[28-jul]]+FX6,0) -> 2.9447297e+09 | FY8: =IF(FY7>0,+ESCENARIO[[#This Row],[29-jul]]+FY6,0) -> 2.9832974e+09 | FZ8: =IF(FZ7>0,+ESCENARIO[[#This Row],[30-jul]]+FZ6,0) -> 3.0235419e+09 | GA8: =IF(GA7>0,+ESCENARIO[[#This Row],[31-jul]]+GA6,0) -> 3.040478e+09 | GB8: =IF(GB7>0,+ESCENARIO[[#This Row],[01-ago]]+GB6,0) -> 3.0585667e+09 | GC8: =IF(GC7>0,+ESCENARIO[[#This Row],[02-ago]]+GC6,0) -> 3.0766554e+09 | GD8: =IF(GD7>0,+ESCENARIO[[#This Row],[03-ago]]+GD6,0) -> 3.094744e+09 | GE8: =IF(GE7>0,+ESCENARIO[[#This Row],[04-ago]]+GE6,0) -> 3.1124316e+09 | GF8: =IF(GF7>0,+ESCENARIO[[#This Row],[05-ago]]+GF6,0) -> 3.1310329e+09 | GG8: =IF(GG7>0,+ESCENARIO[[#This Row],[06-ago]]+GG6,0) -> 3.1501544e+09 | GH8: =IF(GH7>0,+ESCENARIO[[#This Row],[07-ago]]+GH6,0) -> 3.169933e+09 | GI8: =IF(GI7>0,+ESCENARIO[[#This Row],[08-ago]]+GI6,0) -> 3.190565e+09 | GJ8: =IF(GJ7>0,+ESCENARIO[[#This Row],[09-ago]]+GJ6,0) -> 3.2111971e+09 | GK8: =IF(GK7>0,+ESCENARIO[[#This Row],[10-ago]]+GK6,0) -> 3.2318291e+09 | GL8: =IF(GL7>0,+ESCENARIO[[#This Row],[11-ago]]+GL6,0) -> 3.2539501e+09 | GM8: =IF(GM7>0,+ESCENARIO[[#This Row],[12-ago]]+GM6,0) -> 3.283645e+09 | GN8: =IF(GN7>0,+ESCENARIO[[#This Row],[13-ago]]+GN6,0) -> 3.3148068e+09 | GO8: =IF(GO7>0,+ESCENARIO[[#This Row],[14-ago]]+GO6,0) -> 3.3457923e+09 | GP8: =IF(GP7>0,+ESCENARIO[[#This Row],[15-ago]]+GP6,0) -> 3.379545e+09 | GQ8: =IF(GQ7>0,+ESCENARIO[[#This Row],[16-ago]]+GQ6,0) -> 3.4132977e+09 | GR8: =IF(GR7>0,+ESCENARIO[[#This Row],[17-ago]]+GR6,0) -> 3.4470505e+09 | GS8: =IF(GS7>0,+ESCENARIO[[#This Row],[18-ago]]+GS6,0) -> 3.4833327e+09 | GT8: =IF(GT7>0,+ESCENARIO[[#This Row],[19-ago]]+GT6,0) -> 3.5209636e+09 | GU8: =IF(GU7>0,+ESCENARIO[[#This Row],[20-ago]]+GU6,0) -> 3.5602563e+09 | GV8: =IF(GV7>0,+ESCENARIO[[#This Row],[21-ago]]+GV6,0) -> 3.6022626e+09 | GW8: =IF(GW7>0,+ESCENARIO[[#This Row],[22-ago]]+GW6,0) -> 3.6470807e+09 | GX8: =IF(GX7>0,+ESCENARIO[[#This Row],[23-ago]]+GX6,0) -> 3.6918988e+09 | GY8: =IF(GY7>0,+ESCENARIO[[#This Row],[24-ago]]+GY6,0) -> 3.7367169e+09 | GZ8: =IF(GZ7>0,+ESCENARIO[[#This Row],[25-ago]]+GZ6,0) -> 3.7769447e+09 | HA8: =IF(HA7>0,+ESCENARIO[[#This Row],[26-ago]]+HA6,0) -> 3.8201827e+09 | HB8: =IF(HB7>0,+ESCENARIO[[#This Row],[27-ago]]+HB6,0) -> 3.8646491e+09 | HC8: =IF(HC7>0,+ESCENARIO[[#This Row],[28-ago]]+HC6,0) -> 3.9108123e+09 | HD8: =IF(HD7>0,+ESCENARIO[[#This Row],[29-ago]]+HD6,0) -> 3.957545e+09 | HE8: =IF(HE7>0,+ESCENARIO[[#This Row],[30-ago]]+HE6,0) -> 4.0042776e+09 | HF8: =IF(HF7>0,+ESCENARIO[[#This Row],[31-ago]]+HF6,0) -> 4.0299462e+09 | HG8: =IF(HG7>0,+ESCENARIO[[#This Row],[01-sep]]+HG6,0) -> 4.0567786e+09 | HH8: =IF(HH7>0,+ESCENARIO[[#This Row],[02-sep]]+HH6,0) -> 4.0836109e+09 | HI8: =IF(HI7>0,+ESCENARIO[[#This Row],[03-sep]]+HI6,0) -> 4.1111351e+09 | HJ8: =IF(HJ7>0,+ESCENARIO[[#This Row],[04-sep]]+HJ6,0) -> 4.1396031e+09 | HK8: =IF(HK7>0,+ESCENARIO[[#This Row],[05-sep]]+HK6,0) -> 4.1686087e+09 | HL8: =IF(HL7>0,+ESCENARIO[[#This Row],[06-sep]]+HL6,0) -> 4.1976143e+09 | HM8: =IF(HM7>0,+ESCENARIO[[#This Row],[07-sep]]+HM6,0) -> 4.2266199e+09 | HN8: =IF(HN7>0,+ESCENARIO[[#This Row],[08-sep]]+HN6,0) -> 4.255239e+09 | HO8: =IF(HO7>0,+ESCENARIO[[#This Row],[09-sep]]+HO6,0) -> 4.2847403e+09 | HP8: =IF(HP7>0,+ESCENARIO[[#This Row],[10-sep]]+HP6,0) -> 4.3157804e+09 | HQ8: =IF(HQ7>0,+ESCENARIO[[#This Row],[11-sep]]+HQ6,0) -> 4.3546472e+09 | HR8: =IF(HR7>0,+ESCENARIO[[#This Row],[12-sep]]+HR6,0) -> 4.3950301e+09 | HS8: =IF(HS7>0,+ESCENARIO[[#This Row],[13-sep]]+HS6,0) -> 4.4354129e+09 | HT8: =IF(HT7>0,+ESCENARIO[[#This Row],[14-sep]]+HT6,0) -> 4.4757957e+09 | HU8: =IF(HU7>0,+ESCENARIO[[#This Row],[15-sep]]+HU6,0) -> 4.5157933e+09 | HV8: =IF(HV7>0,+ESCENARIO[[#This Row],[16-sep]]+HV6,0) -> 4.5586508e+09 | HW8: =IF(HW7>0,+ESCENARIO[[#This Row],[17-sep]]+HW6,0) -> 4.6041223e+09 | HX8: =IF(HX7>0,+ESCENARIO[[#This Row],[18-sep]]+HX6,0) -> 4.6509874e+09 | HY8: =IF(HY7>0,+ESCENARIO[[#This Row],[19-sep]]+HY6,0) -> 4.69957e+09 | HZ8: =IF(HZ7>0,+ESCENARIO[[#This Row],[20-sep]]+HZ6,0) -> 4.7481525e+09 | IA8: =IF(IA7>0,+ESCENARIO[[#This Row],[21-sep]]+IA6,0) -> 4.796735e+09 | IB8: =IF(IB7>0,+ESCENARIO[[#This Row],[22-sep]]+IB6,0) -> 4.8419702e+09 | IC8: =IF(IC7>0,+ESCENARIO[[#This Row],[23-sep]]+IC6,0) -> 4.8901144e+09 | ID8: =IF(ID7>0,+ESCENARIO[[#This Row],[24-sep]]+ID6,0) -> 4.9398937e+09 | IE8: =IF(IE7>0,+ESCENARIO[[#This Row],[25-sep]]+IE6,0) -> 4.9927792e+09 | IF8: =IF(IF7>0,+ESCENARIO[[#This Row],[26-sep]]+IF6,0) -> 5.0469341e+09 | IG8: =IF(IG7>0,+ESCENARIO[[#This Row],[27-sep]]+IG6,0) -> 5.1010891e+09 | IH8: =IF(IH7>0,+ESCENARIO[[#This Row],[28-sep]]+IH6,0) -> 5.155244e+09 | II8: =IF(II7>0,+ESCENARIO[[#This Row],[29-sep]]+II6,0) -> 5.2111524e+09 | IJ8: =IF(IJ7>0,+ESCENARIO[[#This Row],[30-sep]]+IJ6,0) -> 5.2471839e+09 | IK8: =IF(IK7>0,+ESCENARIO[[#This Row],[01-oct]]+IK6,0) -> 5.2844163e+09 | IL8: =IF(IL7>0,+ESCENARIO[[#This Row],[02-oct]]+IL6,0) -> 5.3223693e+09 | IM8: =IF(IM7>0,+ESCENARIO[[#This Row],[03-oct]]+IM6,0) -> 5.3613056e+09 | IN8: =IF(IN7>0,+ESCENARIO[[#This Row],[04-oct]]+IN6,0) -> 5.4002419e+09 | IO8: =IF(IO7>0,+ESCENARIO[[#This Row],[05-oct]]+IO6,0) -> 5.4391782e+09 | IP8: =IF(IP7>0,+ESCENARIO[[#This Row],[06-oct]]+IP6,0) -> 5.477604e+09 | IQ8: =IF(IQ7>0,+ESCENARIO[[#This Row],[07-oct]]+IQ6,0) -> 5.5167377e+09 | IR8: =IF(IR7>0,+ESCENARIO[[#This Row],[08-oct]]+IR6,0) -> 5.5567902e+09 | IS8: =IF(IS7>0,+ESCENARIO[[#This Row],[09-oct]]+IS6,0) -> 5.5984457e+09 | IT8: =IF(IT7>0,+ESCENARIO[[#This Row],[10-oct]]+IT6,0) -> 5.6482549e+09 | IU8: =IF(IU7>0,+ESCENARIO[[#This Row],[11-oct]]+IU6,0) -> 5.698064e+09 | IV8: =IF(IV7>0,+ESCENARIO[[#This Row],[12-oct]]+IV6,0) -> 5.7478732e+09 | IW8: =IF(IW7>0,+ESCENARIO[[#This Row],[13-oct]]+IW6,0) -> 5.7966167e+09 | IX8: =IF(IX7>0,+ESCENARIO[[#This Row],[14-oct]]+IX6,0) -> 5.8469406e+09 | IY8: =IF(IY7>0,+ESCENARIO[[#This Row],[15-oct]]+IY6,0) -> 5.8969216e+09 | IZ8: =IF(IZ7>0,+ESCENARIO[[#This Row],[16-oct]]+IZ6,0) -> 5.9498819e+09 | JA8: =IF(JA7>0,+ESCENARIO[[#This Row],[17-oct]]+JA6,0) -> 6.0055655e+09 | JB8: =IF(JB7>0,+ESCENARIO[[#This Row],[18-oct]]+JB6,0) -> 6.061249e+09 | JC8: =IF(JC7>0,+ESCENARIO[[#This Row],[19-oct]]+JC6,0) -> 6.1169326e+09 | JD8: =IF(JD7>0,+ESCENARIO[[#This Row],[20-oct]]+JD6,0) -> 6.1740679e+09 | JE8: =IF(JE7>0,+ESCENARIO[[#This Row],[21-oct]]+JE6,0) -> 6.2329924e+09 | JF8: =IF(JF7>0,+ESCENARIO[[#This Row],[22-oct]]+JF6,0) -> 6.2948382e+09 | JG8: =IF(JG7>0,+ESCENARIO[[#This Row],[23-oct]]+JG6,0) -> 6.3597111e+09 | JH8: =IF(JH7>0,+ESCENARIO[[#This Row],[24-oct]]+JH6,0) -> 6.4262874e+09 | JI8: =IF(JI7>0,+ESCENARIO[[#This Row],[25-oct]]+JI6,0) -> 6.4928637e+09 | JJ8: =IF(JJ7>0,+ESCENARIO[[#This Row],[26-oct]]+JJ6,0) -> 6.55944e+09 | JK8: =IF(JK7>0,+ESCENARIO[[#This Row],[27-oct]]+JK6,0) -> 6.6231087e+09 | JL8: =IF(JL7>0,+ESCENARIO[[#This Row],[28-oct]]+JL6,0) -> 6.6881025e+09 | JM8: =IF(JM7>0,+ESCENARIO[[#This Row],[29-oct]]+JM6,0) -> 6.7549231e+09 | JN8: =IF(JN7>0,+ESCENARIO[[#This Row],[30-oct]]+JN6,0) -> 6.8025434e+09 | JO8: =IF(JO7>0,+ESCENARIO[[#This Row],[31-oct]]+JO6,0) -> 6.8514132e+09 | JP8: =IF(JP7>0,+ESCENARIO[[#This Row],[01-nov]]+JP6,0) -> 6.900283e+09 | JQ8: =IF(JQ7>0,+ESCENARIO[[#This Row],[02-nov]]+JQ6,0) -> 6.9491528e+09 | JR8: =IF(JR7>0,+ESCENARIO[[#This Row],[03-nov]]+JR6,0) -> 6.9976834e+09 | JS8: =IF(JS7>0,+ESCENARIO[[#This Row],[04-nov]]+JS6,0) -> 7.0472119e+09 | JT8: =IF(JT7>0,+ESCENARIO[[#This Row],[05-nov]]+JT6,0) -> 7.0973088e+09 | JU8: =IF(JU7>0,+ESCENARIO[[#This Row],[06-nov]]+JU6,0) -> 7.1481234e+09 | JV8: =IF(JV7>0,+ESCENARIO[[#This Row],[07-nov]]+JV6,0) -> 7.1998703e+09 | JW8: =IF(JW7>0,+ESCENARIO[[#This Row],[08-nov]]+JW6,0) -> 7.2516172e+09 | JX8: =IF(JX7>0,+ESCENARIO[[#This Row],[09-nov]]+JX6,0) -> 7.3033641e+09 | JY8: =IF(JY7>0,+ESCENARIO[[#This Row],[10-nov]]+JY6,0) -> 7.3567375e+09 | JZ8: =IF(JZ7>0,+ESCENARIO[[#This Row],[11-nov]]+JZ6,0) -> 7.4183844e+09 | KA8: =IF(KA7>0,+ESCENARIO[[#This Row],[12-nov]]+KA6,0) -> 7.4816337e+09 | KB8: =IF(KB7>0,+ESCENARIO[[#This Row],[13-nov]]+KB6,0) -> 7.5447975e+09 | KC8: =IF(KC7>0,+ESCENARIO[[#This Row],[14-nov]]+KC6,0) -> 7.6109841e+09 | KD8: =IF(KD7>0,+ESCENARIO[[#This Row],[15-nov]]+KD6,0) -> 7.6769289e+09 | KE8: =IF(KE7>0,+ESCENARIO[[#This Row],[16-nov]]+KE6,0) -> 7.742874e+09 | KF8: =IF(KF7>0,+ESCENARIO[[#This Row],[17-nov]]+KF6,0) -> 7.8115823e+09 | KG8: =IF(KG7>0,+ESCENARIO[[#This Row],[18-nov]]+KG6,0) -> 7.8817637e+09 | KH8: =IF(KH7>0,+ESCENARIO[[#This Row],[19-nov]]+KH6,0) -> 7.9537606e+09 | KI8: =IF(KI7>0,+ESCENARIO[[#This Row],[20-nov]]+KI6,0) -> 8.0287216e+09 | KJ8: =IF(KJ7>0,+ESCENARIO[[#This Row],[21-nov]]+KJ6,0) -> 8.1067541e+09 | KK8: =IF(KK7>0,+ESCENARIO[[#This Row],[22-nov]]+KK6,0) -> 8.1847866e+09 | KL8: =IF(KL7>0,+ESCENARIO[[#This Row],[23-nov]]+KL6,0) -> 8.2628191e+09 | KM8: =IF(KM7>0,+ESCENARIO[[#This Row],[24-nov]]+KM6,0) -> 8.3347081e+09 | KN8: =IF(KN7>0,+ESCENARIO[[#This Row],[25-nov]]+KN6,0) -> 8.4083314e+09 | KO8: =IF(KO7>0,+ESCENARIO[[#This Row],[26-nov]]+KO6,0) -> 8.4852382e+09 | KP8: =IF(KP7>0,+ESCENARIO[[#This Row],[27-nov]]+KP6,0) -> 8.5634868e+09 | KQ8: =IF(KQ7>0,+ESCENARIO[[#This Row],[28-nov]]+KQ6,0) -> 8.6435889e+09 | KR8: =IF(KR7>0,+ESCENARIO[[#This Row],[29-nov]]+KR6,0) -> 8.7236911e+09 | KS8: =IF(KS7>0,+ESCENARIO[[#This Row],[30-nov]]+KS6,0) -> 8.7839222e+09 | KT8: =IF(KT7>0,+ESCENARIO[[#This Row],[01-dic]]+KT6,0) -> 8.8460436e+09 | KU8: =IF(KU7>0,+ESCENARIO[[#This Row],[02-dic]]+KU6,0) -> 8.9089303e+09 | KV8: =IF(KV7>0,+ESCENARIO[[#This Row],[03-dic]]+KV6,0) -> 8.972861e+09 | KW8: =IF(KW7>0,+ESCENARIO[[#This Row],[04-dic]]+KW6,0) -> 9.0373865e+09 | KX8: =IF(KX7>0,+ESCENARIO[[#This Row],[05-dic]]+KX6,0) -> 9.1026631e+09 | KY8: =IF(KY7>0,+ESCENARIO[[#This Row],[06-dic]]+KY6,0) -> 9.1679398e+09 | KZ8: =IF(KZ7>0,+ESCENARIO[[#This Row],[07-dic]]+KZ6,0) -> 9.2332164e+09 | LA8: =IF(LA7>0,+ESCENARIO[[#This Row],[08-dic]]+LA6,0) -> 9.298493e+09 | LB8: =IF(LB7>0,+ESCENARIO[[#This Row],[09-dic]]+LB6,0) -> 9.362704e+09 | LC8: =IF(LC7>0,+ESCENARIO[[#This Row],[10-dic]]+LC6,0) -> 9.4278916e+09 | LD8: =IF(LD7>0,+ESCENARIO[[#This Row],[11-dic]]+LD6,0) -> 9.4947813e+09 | LE8: =IF(LE7>0,+ESCENARIO[[#This Row],[12-dic]]+LE6,0) -> 9.570329e+09 | LF8: =IF(LF7>0,+ESCENARIO[[#This Row],[13-dic]]+LF6,0) -> 9.6458767e+09 | LG8: =IF(LG7>0,+ESCENARIO[[#This Row],[14-dic]]+LG6,0) -> 9.7214244e+09 | LH8: =IF(LH7>0,+ESCENARIO[[#This Row],[15-dic]]+LH6,0) -> 9.798649e+09 | LI8: =IF(LI7>0,+ESCENARIO[[#This Row],[16-dic]]+LI6,0) -> 9.8769984e+09 | LJ8: =IF(LJ7>0,+ESCENARIO[[#This Row],[17-dic]]+LJ6,0) -> 9.9585111e+09 | LK8: =IF(LK7>0,+ESCENARIO[[#This Row],[18-dic]]+LK6,0) -> 1.0042915e+10 | LL8: =IF(LL7>0,+ESCENARIO[[#This Row],[19-dic]]+LL6,0) -> 1.0128861e+10 | LM8: =IF(LM7>0,+ESCENARIO[[#This Row],[20-dic]]+LM6,0) -> 1.0214807e+10 | LN8: =IF(LN7>0,+ESCENARIO[[#This Row],[21-dic]]+LN6,0) -> 1.0300753e+10 | LO8: =IF(LO7>0,+ESCENARIO[[#This Row],[22-dic]]+LO6,0) -> 1.0388599e+10 | LP8: =IF(LP7>0,+ESCENARIO[[#This Row],[23-dic]]+LP6,0) -> 1.0473403e+10 | LQ8: =IF(LQ7>0,+ESCENARIO[[#This Row],[24-dic]]+LQ6,0) -> 1.0561424e+10 | LR8: =IF(LR7>0,+ESCENARIO[[#This Row],[25-dic]]+LR6,0) -> 1.0651254e+10 | LS8: =IF(LS7>0,+ESCENARIO[[#This Row],[26-dic]]+LS6,0) -> 1.0741084e+10 | LT8: =IF(LT7>0,+ESCENARIO[[#This Row],[27-dic]]+LT6,0) -> 1.0830914e+10 | LU8: =IF(LU7>0,+ESCENARIO[[#This Row],[28-dic]]+LU6,0) -> 1.0920744e+10 | LV8: =IF(LV7>0,+ESCENARIO[[#This Row],[29-dic]]+LV6,0) -> 1.1014011e+10 | LW8: =IF(LW7>0,+ESCENARIO[[#This Row],[30-dic]]+LW6,0) -> 1.1085104e+10 | LX8: =SUM(ESCENARIO[[#This Row],[01-mar]:[31-dic]]) -> 1.1831357e+12
A9: INTERESES RECUPERADO | C9: =IF(C5<0,-C5*(0.0967%),0) -> 227245 | D9: =IF(D5<0,-D5*(0.0967%),0) -> 780425.26 | E9: =IF(E5<0,-E5*(0.0967%),0) -> 0 | F9: =IF(F5<0,-F5*(0.0967%),0) -> 0 | G9: =IF(G5<0,-G5*(0.0967%),0) -> 0 | H9: =IF(H5<0,-H5*(0.0967%),0) -> 0 | I9: =IF(I5<0,-I5*(0.0967%),0) -> 0 | J9: =IF(J5<0,-J5*(0.0967%),0) -> 0 | ... LW9: =IF(LW5<0,-LW5*(0.0967%),0) -> 0 | LX9: =SUM(ESCENARIO[[#This Row],[01-mar]:[31-dic]]) -> 2.7620348e+08
A10: Total | B10: =+B8-B3 -> 0 | C10: =+B7-C3+C2 -> 2.141101e+09 | D10: =+C7-D3+D2 -> 1.3340428e+09 | E10: =+D7-E3+E2 -> 2.207851e+09 | F10: =+E7-F3+F2 -> 2.7051624e+09 | G10: =+F7-G3+G2 -> 3.3333116e+09 | H10: =+G7-H3+H2 -> 4.1491046e+09 | I10: =+H7-I3+I2 -> 4.1491046e+09 | J10: =+I7-J3+J2 -> 4.1491046e+09 | ... LW10: =+LV7-LW3+LW2 -> 7.5547384e+10

Sheet Hoja1

Sheet Hoja8
A1: ESCENARIO 1 | B1: FEBRERO | C1: MARZO | D1: ABRIL | E1: MAYO | F1: JUNIO | G1: JULIO | H1: AGOSTO | I1: SEP | J1: OCTUBRE | K1: NOV | L1: DIC
C2: =B6 -> 2.3252979e+09 | D2: =C6 -> -8.912832e+08 | E2: =D6 -> 3.2050768e+08 | F2: =E6 -> 4.6495843e+09 | G2: =F6 -> 5.3518136e+09 | H2: =G6 -> 9.6276329e+09 | I2: =H6 -> 1.729148e+10 | J2: =I6 -> 2.6915293e+10 | ... L2: =K6 -> 5.1501017e+10
A3: GASTOS PROYECTADOS | B3: 3.6568363e+10 | C3: 4.0408365e+10 | D3: 3.6546064e+10 | E3: 3.5660898e+10 | F3: 3.8191952e+10 | G3: 3.4748004e+10 | H3: 3.1825268e+10 | I3: 3.1184263e+10 | J3: 3.0501829e+10 | K3: 3.0561488e+10 | L3: 3.4394041e+10
A4: INGRESOS FINANCIEROS PROYECTADOS | B4: 3.650232e+10 | C4: 3.7191784e+10 | D4: 3.7757855e+10 | E4: 3.9989975e+10 | F4: 3.8894181e+10 | G4: 3.9023823e+10 | H4: 3.9489115e+10 | I4: 4.0808075e+10 | J4: 4.2512404e+10 | K4: 4.3136637e+10 | L4: 4.5141536e+10
B5: 2.3913417e+09
B6: =+B5+B4-B3 -> 2.3252979e+09 | C6: =+C5+C4-C3+C2 -> -8.912832e+08 | D6: =+D5+D4-D3+D2 -> 3.2050768e+08 | E6: =+E5+E4-E3+E2 -> 4.6495843e+09 | F6: =+F5+F4-F3+F2 -> 5.3518136e+09 | G6: =+G5+G4-G3+G2 -> 9.6276329e+09 | H6: =+H5+H4-H3+H2 -> 1.729148e+10 | I6: =+I5+I4-I3+I2 -> 2.6915293e+10 | J6: =+J5+J4-J3+J2 -> 3.8925867e+10 | ... L6: =+L5+L4-L3+L2 -> 6.2248512e+10

Sheet INVERSIONES
A1: ESCENARIO 1 | B1: INVERSIONES FCI | C1: FCI | D1: FCI1 | E1: FCI2 | F1: FCI3 | G1: FCI7 | H1: FCI4 | I1: FCI8 | J1: FCI5 | K1: FCI9 | L1: FCI6 | M1: FCI62 | N1: FCI63 | O1: FCI64 | P1: FCI65 | Q1: FCI66 | R1: FCI67 | S1: FCI68 | T1: FCI69 | U1: FCI70 | V1: FCI71 | W1: FCI72 | X1: FCI73 | Y1: FCI74 | Z1: FCI75 | AA1: FCI76 | AB1: FCI77 | AC1: FCI78 | AD1: FCI79 | AE1: FCI80 | AF1: FCI81 | AG1: FCI82 | AH1: FCI83 | AI1: FCI84 | AJ1: FCI85 | AK1: FCI86 | AL1: FCI87 | AM1: FCI88 | AN1: FCI89 | AO1: FCI90 | AP1: FCI91 | AQ1: FCI92 | AR1: FCI93 | AS1: FCI94 | AT1: FCI95 | AU1: FCI96 | AV1: FCI97 | AW1: FCI98 | AX1: FCI99 | AY1: FCI100 | AZ1: FCI101 | BA1: FCI102 | BB1: FCI103 | BC1: FCI104 | BD1: FCI105 | BE1: FCI106 | BF1: FCI107 | BG1: FCI108 | BH1: FCI109 | BI1: FCI110 | BJ1: FCI111 | BK1: FCI112 | BL1: FCI113 | BM1: FCI114 | BN1: FCI115 | BO1: FCI116 | BP1: FCI117 | BQ1: FCI118 | BR1: FCI119 | BS1: FCI120 | BT1: FCI121 | BU1: FCI122 | BV1: FCI123 | BW1: FCI124 | BX1: FCI125 | BY1: FCI126 | BZ1: FCI127 | CA1: FCI128 | CB1: FCI129 | CC1: FCI130 | CD1: FCI131 | CE1: FCI132 | CF1: FCI133 | CG1: FCI134 | CH1: FCI135 | CI1: FCI136 | CJ1: FCI137 | CK1: FCI138 | CL1: FCI139 | CM1: FCI140 | CN1: FCI141 | CO1: FCI142 | CP1: FCI143 | CQ1: FCI144 | CR1: FCI145 | CS1: FCI146 | CT1: FCI147 | CU1: FCI148 | CV1: FCI149 | CW1: FCI150 | CX1: FCI151 | CY1: FCI152 | CZ1: FCI153 | DA1: FCI154 | DB1: FCI155 | DC1: FCI156 | DD1: FCI157 | DE1: FCI158 | DF1: FCI159 | DG1: FCI160 | DH1: FCI161 | DI1: FCI162 | DJ1: FCI163 | DK1: FCI164 | DL1: FCI165 | DM1: FCI166 | DN1: FCI167 | DO1: FCI168 | DP1: FCI169 | DQ1: FCI170
A2: 01-feb | B2: =HLOOKUP($A2,ESCENARIO[#All],7,FALSE) -> 2.376101e+09 | C2: =HLOOKUP($A2,ESCENARIO[#All],7,FALSE) -> 2.376101e+09
A3: 02-feb | B3: =HLOOKUP($A3,ESCENARIO[#All],7,FALSE) -> 2.141101e+09 | C3: =IF($B2<=Tabla5[[#This Row],[INVERSIONES FCI]],+Tabla5[[#This Row],[INVERSIONES FCI]]-C2,Tabla5[[#This Row],[INVERSIONES FCI]]) -> 2.141101e+09 | D3: {=IF(Tabla5[[#This Row],[FCI]]=0,0,_xlfn.XLOOKUP(TRUE,$B3:C3>0,$B3:C3,"",0,-1))} -> 2.141101e+09
A4: 03-feb | B4: =HLOOKUP($A4,ESCENARIO[#All],7,FALSE) -> 1.3340428e+09 | C4: =IF($B3<=Tabla5[[#This Row],[INVERSIONES FCI]],+Tabla5[[#This Row],[INVERSIONES FCI]]-C3,Tabla5[[#This Row],[INVERSIONES FCI]]) -> 1.3340428e+09 | D4: =IF($B3<=Tabla5[[#This Row],[INVERSIONES FCI]],+Tabla5[[#This Row],[INVERSIONES FCI]]-D3,Tabla5[[#This Row],[INVERSIONES FCI]]) -> 1.3340428e+09 | E4: {=IF(Tabla5[[#This Row],[FCI]]=0,0,_xlfn.XLOOKUP(TRUE,$B4:D4>0,$B4:D4,"",0,-1))} -> 1.3340428e+09
A5: 04-feb | B5: =HLOOKUP($A5,ESCENARIO[#All],7,FALSE) -> 2.207851e+09 | C5: =IF($B4<=Tabla5[[#This Row],[INVERSIONES FCI]],+Tabla5[[#This Row],[INVERSIONES FCI]]-C4,Tabla5[[#This Row],[INVERSIONES FCI]]) -> 8.7380819e+08 | D5: =IF($B4<=Tabla5[[#This Row],[INVERSIONES FCI]],+Tabla5[[#This Row],[INVERSIONES FCI]]-D4,Tabla5[[#This Row],[INVERSIONES FCI]]) -> 8.7380819e+08 | E5: =IF($B4<=Tabla5[[#This Row],[INVERSIONES FCI]],+Tabla5[[#This Row],[INVERSIONES FCI]]-E4,Tabla5[[#This Row],[INVERSIONES FCI]]) -> 8.7380819e+08 | F5: {=IF(Tabla5[[#This Row],[FCI]]=0,0,_xlfn.XLOOKUP(TRUE,$B5:E5>0,$B5:E5,"",0,-1))} -> 8.7380819e+08
A6: 05-feb | B6: =HLOOKUP($A6,ESCENARIO[#All],7,FALSE) -> 2.7051624e+09 | C6: =IF($B5<=Tabla5[[#This Row],[INVERSIONES FCI]],+Tabla5[[#This Row],[INVERSIONES FCI]]-C5,Tabla5[[#This Row],[INVERSIONES FCI]]) -> 1.8313542e+09 | D6: =IF($B5<=Tabla5[[#This Row],[INVERSIONES FCI]],+Tabla5[[#This Row],[INVERSIONES FCI]]-D5,Tabla5[[#This Row],[INVERSIONES FCI]]) -> 1.8313542e+09 | E6: =IF($B5<=Tabla5[[#This Row],[INVERSIONES FCI]],+Tabla5[[#This Row],[INVERSIONES FCI]]-E5,Tabla5[[#This Row],[INVERSIONES FCI]]) -> 1.8313542e+09 | F6: =IF($B5<=Tabla5[[#This Row],[INVERSIONES FCI]],+Tabla5[[#This Row],[INVERSIONES FCI]]-F5,Tabla5[[#This Row],[INVERSIONES FCI]]) -> 1.8313542e+09 | G6: {=IF(Tabla5[[#This Row],[FCI]]=0,0,_xlfn.XLOOKUP(TRUE,$B6:F6>0,$B6:F6,"",0,-1))} -> 1.8313542e+09
A7: 06-feb | B7: =HLOOKUP($A7,ESCENARIO[#All],7,FALSE) -> 3.3333116e+09 | C7: =IF($B6<=Tabla5[[#This Row],[INVERSIONES FCI]],+Tabla5[[#This Row],[INVERSIONES FCI]]-C6,Tabla5[[#This Row],[INVERSIONES FCI]]) -> 1.5019574e+09 | D7: =IF($B6<=Tabla5[[#This Row],[INVERSIONES FCI]],+Tabla5[[#This Row],[INVERSIONES FCI]]-D6,Tabla5[[#This Row],[INVERSIONES FCI]]) -> 1.5019574e+09 | E7: =IF($B6<=Tabla5[[#This Row],[INVERSIONES FCI]],+Tabla5[[#This Row],[INVERSIONES FCI]]-E6,Tabla5[[#This Row],[INVERSIONES FCI]]) -> 1.5019574e+09 | F7: =IF($B6<=Tabla5[[#This Row],[INVERSIONES FCI]],+Tabla5[[#This Row],[INVERSIONES FCI]]-F6,Tabla5[[#This Row],[INVERSIONES FCI]]) -> 1.5019574e+09 | G7: =IF($B6<=Tabla5[[#This Row],[INVERSIONES FCI]],+Tabla5[[#This Row],[INVERSIONES FCI]]-G6,Tabla5[[#This Row],[INVERSIONES FCI]]) -> 1.5019574e+09 | H7: {=IF(Tabla5[[#This Row],[FCI]]=0,0,_xlfn.XLOOKUP(TRUE,$B7:G7>0,$B7:G7,"",0,-1))} -> 1.5019574e+09
A8: 07-feb | B8: =HLOOKUP($A8,ESCENARIO[#All],7,FALSE) -> 4.1491046e+09 | C8: =IF($B7<=Tabla5[[#This Row],[INVERSIONES FCI]],+Tabla5[[#This Row],[INVERSIONES FCI]]-C7,Tabla5[[#This Row],[INVERSIONES FCI]]) -> 2.6471472e+09 | D8: =IF($B7<=Tabla5[[#This Row],[INVERSIONES FCI]],+Tabla5[[#This Row],[INVERSIONES FCI]]-D7,Tabla5[[#This Row],[INVERSIONES FCI]]) -> 2.6471472e+09 | E8: =IF($B7<=Tabla5[[#This Row],[INVERSIONES FCI]],+Tabla5[[#This Row],[INVERSIONES FCI]]-E7,Tabla5[[#This Row],[INVERSIONES FCI]]) -> 2.6471472e+09 | F8: =IF($B7<=Tabla5[[#This Row],[INVERSIONES FCI]],+Tabla5[[#This Row],[INVERSIONES FCI]]-F7,Tabla5[[#This Row],[INVERSIONES FCI]]) -> 2.6471472e+09 | G8: =IF($B7<=Tabla5[[#This Row],[INVERSIONES FCI]],+Tabla5[[#This Row],[INVERSIONES FCI]]-G7,Tabla5[[#This Row],[INVERSIONES FCI]]) -> 2.6471472e+09 | H8: =IF($B7<=Tabla5[[#This Row],[INVERSIONES FCI]],+Tabla5[[#This Row],[INVERSIONES FCI]]-H7,Tabla5[[#This Row],[INVERSIONES FCI]]) -> 2.6471472e+09 | I8: {=IF(Tabla5[[#This Row],[FCI]]=0,0,_xlfn.XLOOKUP(TRUE,$B8:H8>0,$B8:H8,"",0,-1))} -> 2.6471472e+09
A9: 08-feb | B9: =HLOOKUP($A9,ESCENARIO[#All],7,FALSE) -> 4.1491046e+09 | C9: =IF($B8<=Tabla5[[#This Row],[INVERSIONES FCI]],+Tabla5[[#This Row],[INVERSIONES FCI]]-C8,Tabla5[[#This Row],[INVERSIONES FCI]]) -> 1.5019574e+09 | D9: =IF($B8<=Tabla5[[#This Row],[INVERSIONES FCI]],+Tabla5[[#This Row],[INVERSIONES FCI]]-D8,Tabla5[[#This Row],[INVERSIONES FCI]]) -> 1.5019574e+09 | E9: =IF($B8<=Tabla5[[#This Row],[INVERSIONES FCI]],+Tabla5[[#This Row],[INVERSIONES FCI]]-E8,Tabla5[[#This Row],[INVERSIONES FCI]]) -> 1.5019574e+09 | F9: =IF($B8<=Tabla5[[#This Row],[INVERSIONES FCI]],+Tabla5[[#This Row],[INVERSIONES FCI]]-F8,Tabla5[[#This Row],[INVERSIONES FCI]]) -> 1.5019574e+09 | G9: =IF($B8<=Tabla5[[#This Row],[INVERSIONES FCI]],+Tabla5[[#This Row],[INVERSIONES FCI]]-G8,Tabla5[[#This Row],[INVERSIONES FCI]]) -> 1.5019574e+09 | H9: =IF($B8<=Tabla5[[#This Row],[INVERSIONES FCI]],+Tabla5[[#This Row],[INVERSIONES FCI]]-H8,Tabla5[[#This Row],[INVERSIONES FCI]]) -> 1.5019574e+09 | I9: =IF($B8<=Tabla5[[#This Row],[INVERSIONES FCI]],+Tabla5[[#This Row],[INVERSIONES FCI]]-I8,Tabla5[[#This Row],[INVERSIONES FCI]]) -> 1.5019574e+09 | J9: {=IF(Tabla5[[#This Row],[FCI]]=0,0,_xlfn.XLOOKUP(TRUE,$B9:I9>0,$B9:I9,"",0,-1))} -> 1.5019574e+09
A10: 09-feb | B10: =HLOOKUP($A10,ESCENARIO[#All],7,FALSE) -> 4.1491046e+09 | C10: =IF($B9<=Tabla5[[#This Row],[INVERSIONES FCI]],+Tabla5[[#This Row],[INVERSIONES FCI]]-C9,Tabla5[[#This Row],[INVERSIONES FCI]]) -> 2.6471472e+09 | D10: =IF($B9<=Tabla5[[#This Row],[INVERSIONES FCI]],+Tabla5[[#This Row],[INVERSIONES FCI]]-D9,Tabla5[[#This Row],[INVERSIONES FCI]]) -> 2.6471472e+09 | E10: =IF($B9<=Tabla5[[#This Row],[INVERSIONES FCI]],+Tabla5[[#This Row],[INVERSIONES FCI]]-E9,Tabla5[[#This Row],[INVERSIONES FCI]]) -> 2.6471472e+09 | F10: =IF($B9<=Tabla5[[#This Row],[INVERSIONES FCI]],+Tabla5[[#This Row],[INVERSIONES FCI]]-F9,Tabla5[[#This Row],[INVERSIONES FCI]]) -> 2.6471472e+09 | G10: =IF($B9<=Tabla5[[#This Row],[INVERSIONES FCI]],+Tabla5[[#This Row],[INVERSIONES FCI]]-G9,Tabla5[[#This Row],[INVERSIONES FCI]]) -> 2.6471472e+09 | H10: =IF($B9<=Tabla5[[#This Row],[INVERSIONES FCI]],+Tabla5[[#This Row],[INVERSIONES FCI]]-H9,Tabla5[[#This Row],[INVERSIONES FCI]]) -> 2.6471472e+09 | I10: =IF($B9<=Tabla5[[#This Row],[INVERSIONES FCI]],+Tabla5[[#This Row],[INVERSIONES FCI]]-I9,Tabla5[[#This Row],[INVERSIONES FCI]]) -> 2.6471472e+09 | J10: =IF($B9<=Tabla5[[#This Row],[INVERSIONES FCI]],+Tabla5[[#This Row],[INVERSIONES FCI]]-J9,Tabla5[[#This Row],[INVERSIONES FCI]]) -> 2.6471472e+09 | K10: {=IF(Tabla5[[#This Row],[FCI]]=0,0,_xlfn.XLOOKUP(TRUE,$B10:J10>0,$B10:J10,"",0,-1))} -> 2.6471472e+09
A11: 10-feb | B11: =HLOOKUP($A11,ESCENARIO[#All],7,FALSE) -> 5.572429e+09 | C11: =IF($B10<=Tabla5[[#This Row],[INVERSIONES FCI]],+Tabla5[[#This Row],[INVERSIONES FCI]]-C10,Tabla5[[#This Row],[INVERSIONES FCI]]) -> 2.9252817e+09 | D11: =IF($B10<=Tabla5[[#This Row],[INVERSIONES FCI]],+Tabla5[[#This Row],[INVERSIONES FCI]]-D10,Tabla5[[#This Row],[INVERSIONES FCI]]) -> 2.9252817e+09 | E11: =IF($B10<=Tabla5[[#This Row],[INVERSIONES FCI]],+Tabla5[[#This Row],[INVERSIONES FCI]]-E10,Tabla5[[#This Row],[INVERSIONES FCI]]) -> 2.9252817e+09 | F11: =IF($B10<=Tabla5[[#This Row],[INVERSIONES FCI]],+Tabla5[[#This Row],[INVERSIONES FCI]]-F10,Tabla5[[#This Row],[INVERSIONES FCI]]) -> 2.9252817e+09 | G11: =IF($B10<=Tabla5[[#This Row],[INVERSIONES FCI]],+Tabla5[[#This Row],[INVERSIONES FCI]]-G10,Tabla5[[#This Row],[INVERSIONES FCI]]) -> 2.9252817e+09 | H11: =IF($B10<=Tabla5[[#This Row],[INVERSIONES FCI]],+Tabla5[[#This Row],[INVERSIONES FCI]]-H10,Tabla5[[#This Row],[INVERSIONES FCI]]) -> 2.9252817e+09 | I11: =IF($B10<=Tabla5[[#This Row],[INVERSIONES FCI]],+Tabla5[[#This Row],[INVERSIONES FCI]]-I10,Tabla5[[#This Row],[INVERSIONES FCI]]) -> 2.9252817e+09 | J11: =IF($B10<=Tabla5[[#This Row],[INVERSIONES FCI]],+Tabla5[[#This Row],[INVERSIONES FCI]]-J10,Tabla5[[#This Row],[INVERSIONES FCI]]) -> 2.9252817e+09 | K11: =IF($B10<=Tabla5[[#This Row],[INVERSIONES FCI]],+Tabla5[[#This Row],[INVERSIONES FCI]]-K10,Tabla5[[#This Row],[INVERSIONES FCI]]) -> 2.9252817e+09 | L11: {=IF(Tabla5[[#This Row],[FCI]]=0,0,_xlfn.XLOOKUP(TRUE,$B11:K11>0,$B11:K11,"",0,-1))} -> 2.9252817e+09
A12: 11-feb | B12: =HLOOKUP($A12,ESCENARIO[#All],7,FALSE) -> 1.281234e+10 | C12: =IF($B11<=Tabla5[[#This Row],[INVERSIONES FCI]],+Tabla5[[#This Row],[INVERSIONES FCI]]-C11,Tabla5[[#This Row],[INVERSIONES FCI]]) -> 9.8870585e+09 | D12: =IF($B11<=Tabla5[[#This Row],[INVERSIONES FCI]],+Tabla5[[#This Row],[INVERSIONES FCI]]-D11,Tabla5[[#This Row],[INVERSIONES FCI]]) -> 9.8870585e+09 | E12: =IF($B11<=Tabla5[[#This Row],[INVERSIONES FCI]],+Tabla5[[#This Row],[INVERSIONES FCI]]-E11,Tabla5[[#This Row],[INVERSIONES FCI]]) -> 9.8870585e+09 | F12: =IF($B11<=Tabla5[[#This Row],[INVERSIONES FCI]],+Tabla5[[#This Row],[INVERSIONES FCI]]-F11,Tabla5[[#This Row],[INVERSIONES FCI]]) -> 9.8870585e+09 | G12: =IF($B11<=Tabla5[[#This Row],[INVERSIONES FCI]],+Tabla5[[#This Row],[INVERSIONES FCI]]-G11,Tabla5[[#This Row],[INVERSIONES FCI]]) -> 9.8870585e+09 | H12: =IF($B11<=Tabla5[[#This Row],[INVERSIONES FCI]],+Tabla5[[#This Row],[INVERSIONES FCI]]-H11,Tabla5[[#This Row],[INVERSIONES FCI]]) -> 9.8870585e+09 | I12: =IF($B11<=Tabla5[[#This Row],[INVERSIONES FCI]],+Tabla5[[#This Row],[INVERSIONES FCI]]-I11,Tabla5[[#This Row],[INVERSIONES FCI]]) -> 9.8870585e+09 | J12: =IF($B11<=Tabla5[[#This Row],[INVERSIONES FCI]],+Tabla5[[#This Row],[INVERSIONES FCI]]-J11,Tabla5[[#This Row],[INVERSIONES FCI]]) -> 9.8870585e+09 | ... L12: =IF($B11<=Tabla5[[#This Row],[INVERSIONES FCI]],+Tabla5[[#This Row],[INVERSIONES FCI]]-L11,Tabla5[[#This Row],[INVERSIONES FCI]]) -> 9.8870585e+09 | M12: {=IF(Tabla5[[#This Row],[FCI]]=0,0,_xlfn.XLOOKUP(TRUE,$B12:L12>0,$B12:L12,"",0,-1))} -> 9.8870585e+09
A13: 12-feb | B13: =HLOOKUP($A13,ESCENARIO[#All],7,FALSE) -> 1.4214625e+10 | C13: =IF($B12<=Tabla5[[#This Row],[INVERSIONES FCI]],+Tabla5[[#This Row],[INVERSIONES FCI]]-C12,Tabla5[[#This Row],[INVERSIONES FCI]]) -> 4.3275661e+09 | D13: =IF($B12<=Tabla5[[#This Row],[INVERSIONES FCI]],+Tabla5[[#This Row],[INVERSIONES FCI]]-D12,Tabla5[[#This Row],[INVERSIONES FCI]]) -> 4.3275661e+09 | E13: =IF($B12<=Tabla5[[#This Row],[INVERSIONES FCI]],+Tabla5[[#This Row],[INVERSIONES FCI]]-E12,Tabla5[[#This Row],[INVERSIONES FCI]]) -> 4.3275661e+09 | F13: =IF($B12<=Tabla5[[#This Row],[INVERSIONES FCI]],+Tabla5[[#This Row],[INVERSIONES FCI]]-F12,Tabla5[[#This Row],[INVERSIONES FCI]]) -> 4.3275661e+09 | G13: =IF($B12<=Tabla5[[#This Row],[INVERSIONES FCI]],+Tabla5[[#This Row],[INVERSIONES FCI]]-G12,Tabla5[[#This Row],[INVERSIONES FCI]]) -> 4.3275661e+09 | H13: =IF($B12<=Tabla5[[#This Row],[INVERSIONES FCI]],+Tabla5[[#This Row],[INVERSIONES FCI]]-H12,Tabla5[[#This Row],[INVERSIONES FCI]]) -> 4.3275661e+09 | I13: =IF($B12<=Tabla5[[#This Row],[INVERSIONES FCI]],+Tabla5[[#This Row],[INVERSIONES FCI]]-I12,Tabla5[[#This Row],[INVERSIONES FCI]]) -> 4.3275661e+09 | J13: =IF($B12<=Tabla5[[#This Row],[INVERSIONES FCI]],+Tabla5[[#This Row],[INVERSIONES FCI]]-J12,Tabla5[[#This Row],[INVERSIONES FCI]]) -> 4.3275661e+09 | ... M13: =IF($B12<=Tabla5[[#This Row],[INVERSIONES FCI]],+Tabla5[[#This Row],[INVERSIONES FCI]]-M12,Tabla5[[#This Row],[INVERSIONES FCI]]) -> 4.3275661e+09 | N13: {=IF(Tabla5[[#This Row],[FCI]]=0,0,_xlfn.XLOOKUP(TRUE,$B13:M13>0,$B13:M13,"",0,-1))} -> 4.3275661e+09
A14: 13-feb | B14: =HLOOKUP($A14,ESCENARIO[#All],7,FALSE) -> 1.3863315e+10 | C14: =IF($B13<=Tabla5[[#This Row],[INVERSIONES FCI]],+Tabla5[[#This Row],[INVERSIONES FCI]]-C13,Tabla5[[#This Row],[INVERSIONES FCI]]) -> 1.3863315e+10 | D14: =IF($B13<=Tabla5[[#This Row],[INVERSIONES FCI]],+Tabla5[[#This Row],[INVERSIONES FCI]]-D13,Tabla5[[#This Row],[INVERSIONES FCI]]) -> 1.3863315e+10 | E14: =IF($B13<=Tabla5[[#This Row],[INVERSIONES FCI]],+Tabla5[[#This Row],[INVERSIONES FCI]]-E13,Tabla5[[#This Row],[INVERSIONES FCI]]) -> 1.3863315e+10 | F14: =IF($B13<=Tabla5[[#This Row],[INVERSIONES FCI]],+Tabla5[[#This Row],[INVERSIONES FCI]]-F13,Tabla5[[#This Row],[INVERSIONES FCI]]) -> 1.3863315e+10 | G14: =IF($B13<=Tabla5[[#This Row],[INVERSIONES FCI]],+Tabla5[[#This Row],[INVERSIONES FCI]]-G13,Tabla5[[#This Row],[INVERSIONES FCI]]) -> 1.3863315e+10 | H14: =IF($B13<=Tabla5[[#This Row],[INVERSIONES FCI]],+Tabla5[[#This Row],[INVERSIONES FCI]]-H13,Tabla5[[#This Row],[INVERSIONES FCI]]) -> 1.3863315e+10 | I14: =IF($B13<=Tabla5[[#This Row],[INVERSIONES FCI]],+Tabla5[[#This Row],[INVERSIONES FCI]]-I13,Tabla5[[#This Row],[INVERSIONES FCI]]) -> 1.3863315e+10 | J14: =IF($B13<=Tabla5[[#This Row],[INVERSIONES FCI]],+Tabla5[[#This Row],[INVERSIONES FCI]]-J13,Tabla5[[#This Row],[INVERSIONES FCI]]) -> 1.3863315e+10 | ... N14: =IF($B13<=Tabla5[[#This Row],[INVERSIONES FCI]],+Tabla5[[#This Row],[INVERSIONES FCI]]-N13,Tabla5[[#This Row],[INVERSIONES FCI]]) -> 1.3863315e+10 | O14: {=IF(Tabla5[[#This Row],[FCI]]=0,0,_xlfn.XLOOKUP(TRUE,$B14:N14>0,$B14:N14,"",0,-1))} -> 1.3863315e+10
A15: 14-feb | B15: =HLOOKUP($A15,ESCENARIO[#All],7,FALSE) -> 1.6508794e+10 | C15: =IF($B14<=Tabla5[[#This Row],[INVERSIONES FCI]],+Tabla5[[#This Row],[INVERSIONES FCI]]-C14,Tabla5[[#This Row],[INVERSIONES FCI]]) -> 2.6454791e+09 | D15: =IF($B14<=Tabla5[[#This Row],[INVERSIONES FCI]],+Tabla5[[#This Row],[INVERSIONES FCI]]-D14,Tabla5[[#This Row],[INVERSIONES FCI]]) -> 2.6454791e+09 | E15: =IF($B14<=Tabla5[[#This Row],[INVERSIONES FCI]],+Tabla5[[#This Row],[INVERSIONES FCI]]-E14,Tabla5[[#This Row],[INVERSIONES FCI]]) -> 2.6454791e+09 | F15: =IF($B14<=Tabla5[[#This Row],[INVERSIONES FCI]],+Tabla5[[#This Row],[INVERSIONES FCI]]-F14,Tabla5[[#This Row],[INVERSIONES FCI]]) -> 2.6454791e+09 | G15: =IF($B14<=Tabla5[[#This Row],[INVERSIONES FCI]],+Tabla5[[#This Row],[INVERSIONES FCI]]-G14,Tabla5[[#This Row],[INVERSIONES FCI]]) -> 2.6454791e+09 | H15: =IF($B14<=Tabla5[[#This Row],[INVERSIONES FCI]],+Tabla5[[#This Row],[INVERSIONES FCI]]-H14,Tabla5[[#This Row],[INVERSIONES FCI]]) -> 2.6454791e+09 | I15: =IF($B14<=Tabla5[[#This Row],[INVERSIONES FCI]],+Tabla5[[#This Row],[INVERSIONES FCI]]-I14,Tabla5[[#This Row],[INVERSIONES FCI]]) -> 2.6454791e+09 | J15: =IF($B14<=Tabla5[[#This Row],[INVERSIONES FCI]],+Tabla5[[#This Row],[INVERSIONES FCI]]-J14,Tabla5[[#This Row],[INVERSIONES FCI]]) -> 2.6454791e+09 | ... O15: =IF($B14<=Tabla5[[#This Row],[INVERSIONES FCI]],+Tabla5[[#This Row],[INVERSIONES FCI]]-O14,Tabla5[[#This Row],[INVERSIONES FCI]]) -> 2.6454791e+09 | P15: {=IF(Tabla5[[#This Row],[FCI]]=0,0,_xlfn.XLOOKUP(TRUE,$B15:O15>0,$B15:O15,"",0,-1))} -> 2.6454791e+09
A16: 15-feb | B16: =HLOOKUP($A16,ESCENARIO[#All],7,FALSE) -> 1.6273794e+10 | C16: =IF($B15<=Tabla5[[#This Row],[INVERSIONES FCI]],+Tabla5[[#This Row],[INVERSIONES FCI]]-C15,Tabla5[[#This Row],[INVERSIONES FCI]]) -> 1.6273794e+10 | D16: =IF($B15<=Tabla5[[#This Row],[INVERSIONES FCI]],+Tabla5[[#This Row],[INVERSIONES FCI]]-D15,Tabla5[[#This Row],[INVERSIONES FCI]]) -> 1.6273794e+10 | E16: =IF($B15<=Tabla5[[#This Row],[INVERSIONES FCI]],+Tabla5[[#This Row],[INVERSIONES FCI]]-E15,Tabla5[[#This Row],[INVERSIONES FCI]]) -> 1.6273794e+10 | F16: =IF($B15<=Tabla5[[#This Row],[INVERSIONES FCI]],+Tabla5[[#This Row],[INVERSIONES FCI]]-F15,Tabla5[[#This Row],[INVERSIONES FCI]]) -> 1.6273794e+10 | G16: =IF($B15<=Tabla5[[#This Row],[INVERSIONES FCI]],+Tabla5[[#This Row],[INVERSIONES FCI]]-G15,Tabla5[[#This Row],[INVERSIONES FCI]]) -> 1.6273794e+10 | H16: =IF($B15<=Tabla5[[#This Row],[INVERSIONES FCI]],+Tabla5[[#This Row],[INVERSIONES FCI]]-H15,Tabla5[[#This Row],[INVERSIONES FCI]]) -> 1.6273794e+10 | I16: =IF($B15<=Tabla5[[#This Row],[INVERSIONES FCI]],+Tabla5[[#This Row],[INVERSIONES FCI]]-I15,Tabla5[[#This Row],[INVERSIONES FCI]]) -> 1.6273794e+10 | J16: =IF($B15<=Tabla5[[#This Row],[INVERSIONES FCI]],+Tabla5[[#This Row],[INVERSIONES FCI]]-J15,Tabla5[[#This Row],[INVERSIONES FCI]]) -> 1.6273794e+10 | ... P16: =IF($B15<=Tabla5[[#This Row],[INVERSIONES FCI]],+Tabla5[[#This Row],[INVERSIONES FCI]]-P15,Tabla5[[#This Row],[INVERSIONES FCI]]) -> 1.6273794e+10 | Q16: {=IF(Tabla5[[#This Row],[FCI]]=0,0,_xlfn.XLOOKUP(TRUE,$B16:P16>0,$B16:P16,"",0,-1))} -> 1.6273794e+10
A17: 16-feb | B17: =HLOOKUP($A17,ESCENARIO[#All],7,FALSE) -> 1.6274022e+10 | C17: =IF($B16<=Tabla5[[#This Row],[INVERSIONES FCI]],+Tabla5[[#This Row],[INVERSIONES FCI]]-C16,Tabla5[[#This Row],[INVERSIONES FCI]]) -> 227245 | D17: =IF($B16<=Tabla5[[#This Row],[INVERSIONES FCI]],+Tabla5[[#This Row],[INVERSIONES FCI]]-D16,Tabla5[[#This Row],[INVERSIONES FCI]]) -> 227245 | E17: =IF($B16<=Tabla5[[#This Row],[INVERSIONES FCI]],+Tabla5[[#This Row],[INVERSIONES FCI]]-E16,Tabla5[[#This Row],[INVERSIONES FCI]]) -> 227245 | F17: =IF($B16<=Tabla5[[#This Row],[INVERSIONES FCI]],+Tabla5[[#This Row],[INVERSIONES FCI]]-F16,Tabla5[[#This Row],[INVERSIONES FCI]]) -> 227245 | G17: =IF($B16<=Tabla5[[#This Row],[INVERSIONES FCI]],+Tabla5[[#This Row],[INVERSIONES FCI]]-G16,Tabla5[[#This Row],[INVERSIONES FCI]]) -> 227245 | H17: =IF($B16<=Tabla5[[#This Row],[INVERSIONES FCI]],+Tabla5[[#This Row],[INVERSIONES FCI]]-H16,Tabla5[[#This Row],[INVERSIONES FCI]]) -> 227245 | I17: =IF($B16<=Tabla5[[#This Row],[INVERSIONES FCI]],+Tabla5[[#This Row],[INVERSIONES FCI]]-I16,Tabla5[[#This Row],[INVERSIONES FCI]]) -> 227245 | J17: =IF($B16<=Tabla5[[#This Row],[INVERSIONES FCI]],+Tabla5[[#This Row],[INVERSIONES FCI]]-J16,Tabla5[[#This Row],[INVERSIONES FCI]]) -> 227245 | ... Q17: =IF($B16<=Tabla5[[#This Row],[INVERSIONES FCI]],+Tabla5[[#This Row],[INVERSIONES FCI]]-Q16,Tabla5[[#This Row],[INVERSIONES FCI]]) -> 227245 | R17: {=IF(Tabla5[[#This Row],[FCI]]=0,0,_xlfn.XLOOKUP(TRUE,$B17:Q17>0,$B17:Q17,"",0,-1))} -> 227245
A18: 17-feb | B18: =HLOOKUP($A18,ESCENARIO[#All],7,FALSE) -> 1.8692047e+10 | C18: =IF($B17<=Tabla5[[#This Row],[INVERSIONES FCI]],+Tabla5[[#This Row],[INVERSIONES FCI]]-C17,Tabla5[[#This Row],[INVERSIONES FCI]]) -> 1.869182e+10 | D18: =IF($B17<=Tabla5[[#This Row],[INVERSIONES FCI]],+Tabla5[[#This Row],[INVERSIONES FCI]]-D17,Tabla5[[#This Row],[INVERSIONES FCI]]) -> 1.869182e+10 | E18: =IF($B17<=Tabla5[[#This Row],[INVERSIONES FCI]],+Tabla5[[#This Row],[INVERSIONES FCI]]-E17,Tabla5[[#This Row],[INVERSIONES FCI]]) -> 1.869182e+10 | F18: =IF($B17<=Tabla5[[#This Row],[INVERSIONES FCI]],+Tabla5[[#This Row],[INVERSIONES FCI]]-F17,Tabla5[[#This Row],[INVERSIONES FCI]]) -> 1.869182e+10 | G18: =IF($B17<=Tabla5[[#This Row],[INVERSIONES FCI]],+Tabla5[[#This Row],[INVERSIONES FCI]]-G17,Tabla5[[#This Row],[INVERSIONES FCI]]) -> 1.869182e+10 | H18: =IF($B17<=Tabla5[[#This Row],[INVERSIONES FCI]],+Tabla5[[#This Row],[INVERSIONES FCI]]-H17,Tabla5[[#This Row],[INVERSIONES FCI]]) -> 1.869182e+10 | I18: =IF($B17<=Tabla5[[#This Row],[INVERSIONES FCI]],+Tabla5[[#This Row],[INVERSIONES FCI]]-I17,Tabla5[[#This Row],[INVERSIONES FCI]]) -> 1.869182e+10 | J18: =IF($B17<=Tabla5[[#This Row],[INVERSIONES FCI]],+Tabla5[[#This Row],[INVERSIONES FCI]]-J17,Tabla5[[#This Row],[INVERSIONES FCI]]) -> 1.869182e+10 | ... R18: =IF($B17<=Tabla5[[#This Row],[INVERSIONES FCI]],+Tabla5[[#This Row],[INVERSIONES FCI]]-R17,Tabla5[[#This Row],[INVERSIONES FCI]]) -> 1.869182e+10 | S18: {=IF(Tabla5[[#This Row],[FCI]]=0,0,_xlfn.XLOOKUP(TRUE,$B18:R18>0,$B18:R18,"",0,-1))} -> 1.869182e+10
A19: 18-feb | B19: =HLOOKUP($A19,ESCENARIO[#All],7,FALSE) -> 1.9981147e+10 | C19: =IF($B18<=Tabla5[[#This Row],[INVERSIONES FCI]],+Tabla5[[#This Row],[INVERSIONES FCI]]-C18,Tabla5[[#This Row],[INVERSIONES FCI]]) -> 1.2893269e+09 | D19: =IF($B18<=Tabla5[[#This Row],[INVERSIONES FCI]],+Tabla5[[#This Row],[INVERSIONES FCI]]-D18,Tabla5[[#This Row],[INVERSIONES FCI]]) -> 1.2893269e+09 | E19: =IF($B18<=Tabla5[[#This Row],[INVERSIONES FCI]],+Tabla5[[#This Row],[INVERSIONES FCI]]-E18,Tabla5[[#This Row],[INVERSIONES FCI]]) -> 1.2893269e+09 | F19: =IF($B18<=Tabla5[[#This Row],[INVERSIONES FCI]],+Tabla5[[#This Row],[INVERSIONES FCI]]-F18,Tabla5[[#This Row],[INVERSIONES FCI]]) -> 1.2893269e+09 | G19: =IF($B18<=Tabla5[[#This Row],[INVERSIONES FCI]],+Tabla5[[#This Row],[INVERSIONES FCI]]-G18,Tabla5[[#This Row],[INVERSIONES FCI]]) -> 1.2893269e+09 | H19: =IF($B18<=Tabla5[[#This Row],[INVERSIONES FCI]],+Tabla5[[#This Row],[INVERSIONES FCI]]-H18,Tabla5[[#This Row],[INVERSIONES FCI]]) -> 1.2893269e+09 | I19: =IF($B18<=Tabla5[[#This Row],[INVERSIONES FCI]],+Tabla5[[#This Row],[INVERSIONES FCI]]-I18,Tabla5[[#This Row],[INVERSIONES FCI]]) -> 1.2893269e+09 | J19: =IF($B18<=Tabla5[[#This Row],[INVERSIONES FCI]],+Tabla5[[#This Row],[INVERSIONES FCI]]-J18,Tabla5[[#This Row],[INVERSIONES FCI]]) -> 1.2893269e+09 | ... S19: =IF($B18<=Tabla5[[#This Row],[INVERSIONES FCI]],+Tabla5[[#This Row],[INVERSIONES FCI]]-S18,Tabla5[[#This Row],[INVERSIONES FCI]]) -> 1.2893269e+09 | T19: {=IF(Tabla5[[#This Row],[FCI]]=0,0,_xlfn.XLOOKUP(TRUE,$B19:S19>0,$B19:S19,"",0,-1))} -> 1.2893269e+09
A20: 19-feb | B20: =HLOOKUP($A20,ESCENARIO[#All],7,FALSE) -> 2.1569768e+10 | C20: =IF($B19<=Tabla5[[#This Row],[INVERSIONES FCI]],+Tabla5[[#This Row],[INVERSIONES FCI]]-C19,Tabla5[[#This Row],[INVERSIONES FCI]]) -> 2.0280441e+10 | D20: =IF($B19<=Tabla5[[#This Row],[INVERSIONES FCI]],+Tabla5[[#This Row],[INVERSIONES FCI]]-D19,Tabla5[[#This Row],[INVERSIONES FCI]]) -> 2.0280441e+10 | E20: =IF($B19<=Tabla5[[#This Row],[INVERSIONES FCI]],+Tabla5[[#This Row],[INVERSIONES FCI]]-E19,Tabla5[[#This Row],[INVERSIONES FCI]]) -> 2.0280441e+10 | F20: =IF($B19<=Tabla5[[#This Row],[INVERSIONES FCI]],+Tabla5[[#This Row],[INVERSIONES FCI]]-F19,Tabla5[[#This Row],[INVERSIONES FCI]]) -> 2.0280441e+10 | G20: =IF($B19<=Tabla5[[#This Row],[INVERSIONES FCI]],+Tabla5[[#This Row],[INVERSIONES FCI]]-G19,Tabla5[[#This Row],[INVERSIONES FCI]]) -> 2.0280441e+10 | H20: =IF($B19<=Tabla5[[#This Row],[INVERSIONES FCI]],+Tabla5[[#This Row],[INVERSIONES FCI]]-H19,Tabla5[[#This Row],[INVERSIONES FCI]]) -> 2.0280441e+10 | I20: =IF($B19<=Tabla5[[#This Row],[INVERSIONES FCI]],+Tabla5[[#This Row],[INVERSIONES FCI]]-I19,Tabla5[[#This Row],[INVERSIONES FCI]]) -> 2.0280441e+10 | J20: =IF($B19<=Tabla5[[#This Row],[INVERSIONES FCI]],+Tabla5[[#This Row],[INVERSIONES FCI]]-J19,Tabla5[[#This Row],[INVERSIONES FCI]]) -> 2.0280441e+10 | ... T20: =IF($B19<=Tabla5[[#This Row],[INVERSIONES FCI]],+Tabla5[[#This Row],[INVERSIONES FCI]]-T19,Tabla5[[#This Row],[INVERSIONES FCI]]) -> 2.0280441e+10 | U20: {=IF(Tabla5[[#This Row],[FCI]]=0,0,_xlfn.XLOOKUP(TRUE,$B20:T20>0,$B20:T20,"",0,-1))} -> 2.0280441e+10
A21: 20-feb | B21: =HLOOKUP($A21,ESCENARIO[#All],7,FALSE) -> 2.4163675e+10 | C21: =IF($B20<=Tabla5[[#This Row],[INVERSIONES FCI]],+Tabla5[[#This Row],[INVERSIONES FCI]]-C20,Tabla5[[#This Row],[INVERSIONES FCI]]) -> 3.8832342e+09 | D21: =IF($B20<=Tabla5[[#This Row],[INVERSIONES FCI]],+Tabla5[[#This Row],[INVERSIONES FCI]]-D20,Tabla5[[#This Row],[INVERSIONES FCI]]) -> 3.8832342e+09 | E21: =IF($B20<=Tabla5[[#This Row],[INVERSIONES FCI]],+Tabla5[[#This Row],[INVERSIONES FCI]]-E20,Tabla5[[#This Row],[INVERSIONES FCI]]) -> 3.8832342e+09 | F21: =IF($B20<=Tabla5[[#This Row],[INVERSIONES FCI]],+Tabla5[[#This Row],[INVERSIONES FCI]]-F20,Tabla5[[#This Row],[INVERSIONES FCI]]) -> 3.8832342e+09 | G21: =IF($B20<=Tabla5[[#This Row],[INVERSIONES FCI]],+Tabla5[[#This Row],[INVERSIONES FCI]]-G20,Tabla5[[#This Row],[INVERSIONES FCI]]) -> 3.8832342e+09 | H21: =IF($B20<=Tabla5[[#This Row],[INVERSIONES FCI]],+Tabla5[[#This Row],[INVERSIONES FCI]]-H20,Tabla5[[#This Row],[INVERSIONES FCI]]) -> 3.8832342e+09 | I21: =IF($B20<=Tabla5[[#This Row],[INVERSIONES FCI]],+Tabla5[[#This Row],[INVERSIONES FCI]]-I20,Tabla5[[#This Row],[INVERSIONES FCI]]) -> 3.8832342e+09 | J21: =IF($B20<=Tabla5[[#This Row],[INVERSIONES FCI]],+Tabla5[[#This Row],[INVERSIONES FCI]]-J20,Tabla5[[#This Row],[INVERSIONES FCI]]) -> 3.8832342e+09 | ... U21: =IF($B20<=Tabla5[[#This Row],[INVERSIONES FCI]],+Tabla5[[#This Row],[INVERSIONES FCI]]-U20,Tabla5[[#This Row],[INVERSIONES FCI]]) -> 3.8832342e+09 | V21: {=IF(Tabla5[[#This Row],[FCI]]=0,0,_xlfn.XLOOKUP(TRUE,$B21:U21>0,$B21:U21,"",0,-1))} -> 3.8832342e+09
A22: 21-feb | B22: =HLOOKUP($A22,ESCENARIO[#All],7,FALSE) -> 2.6851487e+10 | C22: =IF($B21<=Tabla5[[#This Row],[INVERSIONES FCI]],+Tabla5[[#This Row],[INVERSIONES FCI]]-C21,Tabla5[[#This Row],[INVERSIONES FCI]]) -> 2.2968253e+10 | D22: =IF($B21<=Tabla5[[#This Row],[INVERSIONES FCI]],+Tabla5[[#This Row],[INVERSIONES FCI]]-D21,Tabla5[[#This Row],[INVERSIONES FCI]]) -> 2.2968253e+10 | E22: =IF($B21<=Tabla5[[#This Row],[INVERSIONES FCI]],+Tabla5[[#This Row],[INVERSIONES FCI]]-E21,Tabla5[[#This Row],[INVERSIONES FCI]]) -> 2.2968253e+10 | F22: =IF($B21<=Tabla5[[#This Row],[INVERSIONES FCI]],+Tabla5[[#This Row],[INVERSIONES FCI]]-F21,Tabla5[[#This Row],[INVERSIONES FCI]]) -> 2.2968253e+10 | G22: =IF($B21<=Tabla5[[#This Row],[INVERSIONES FCI]],+Tabla5[[#This Row],[INVERSIONES FCI]]-G21,Tabla5[[#This Row],[INVERSIONES FCI]]) -> 2.2968253e+10 | H22: =IF($B21<=Tabla5[[#This Row],[INVERSIONES FCI]],+Tabla5[[#This Row],[INVERSIONES FCI]]-H21,Tabla5[[#This Row],[INVERSIONES FCI]]) -> 2.2968253e+10 | I22: =IF($B21<=Tabla5[[#This Row],[INVERSIONES FCI]],+Tabla5[[#This Row],[INVERSIONES FCI]]-I21,Tabla5[[#This Row],[INVERSIONES FCI]]) -> 2.2968253e+10 | J22: =IF($B21<=Tabla5[[#This Row],[INVERSIONES FCI]],+Tabla5[[#This Row],[INVERSIONES FCI]]-J21,Tabla5[[#This Row],[INVERSIONES FCI]]) -> 2.2968253e+10 | ... V22: =IF($B21<=Tabla5[[#This Row],[INVERSIONES FCI]],+Tabla5[[#This Row],[INVERSIONES FCI]]-V21,Tabla5[[#This Row],[INVERSIONES FCI]]) -> 2.2968253e+10 | W22: {=IF(Tabla5[[#This Row],[FCI]]=0,0,_xlfn.XLOOKUP(TRUE,$B22:V22>0,$B22:V22,"",0,-1))} -> 2.2968253e+10
A23: 22-feb | B23: =HLOOKUP($A23,ESCENARIO[#All],7,FALSE) -> 2.6851487e+10 | C23: =IF($B22<=Tabla5[[#This Row],[INVERSIONES FCI]],+Tabla5[[#This Row],[INVERSIONES FCI]]-C22,Tabla5[[#This Row],[INVERSIONES FCI]]) -> 3.8832342e+09 | D23: =IF($B22<=Tabla5[[#This Row],[INVERSIONES FCI]],+Tabla5[[#This Row],[INVERSIONES FCI]]-D22,Tabla5[[#This Row],[INVERSIONES FCI]]) -> 3.8832342e+09 | E23: =IF($B22<=Tabla5[[#This Row],[INVERSIONES FCI]],+Tabla5[[#This Row],[INVERSIONES FCI]]-E22,Tabla5[[#This Row],[INVERSIONES FCI]]) -> 3.8832342e+09 | F23: =IF($B22<=Tabla5[[#This Row],[INVERSIONES FCI]],+Tabla5[[#This Row],[INVERSIONES FCI]]-F22,Tabla5[[#This Row],[INVERSIONES FCI]]) -> 3.8832342e+09 | G23: =IF($B22<=Tabla5[[#This Row],[INVERSIONES FCI]],+Tabla5[[#This Row],[INVERSIONES FCI]]-G22,Tabla5[[#This Row],[INVERSIONES FCI]]) -> 3.8832342e+09 | H23: =IF($B22<=Tabla5[[#This Row],[INVERSIONES FCI]],+Tabla5[[#This Row],[INVERSIONES FCI]]-H22,Tabla5[[#This Row],[INVERSIONES FCI]]) -> 3.8832342e+09 | I23: =IF($B22<=Tabla5[[#This Row],[INVERSIONES FCI]],+Tabla5[[#This Row],[INVERSIONES FCI]]-I22,Tabla5[[#This Row],[INVERSIONES FCI]]) -> 3.8832342e+09 | J23: =IF($B22<=Tabla5[[#This Row],[INVERSIONES FCI]],+Tabla5[[#This Row],[INVERSIONES FCI]]-J22,Tabla5[[#This Row],[INVERSIONES FCI]]) -> 3.8832342e+09 | ... W23: =IF($B22<=Tabla5[[#This Row],[INVERSIONES FCI]],+Tabla5[[#This Row],[INVERSIONES FCI]]-W22,Tabla5[[#This Row],[INVERSIONES FCI]]) -> 3.8832342e+09 | X23: {=IF(Tabla5[[#This Row],[FCI]]=0,0,_xlfn.XLOOKUP(TRUE,$B23:W23>0,$B23:W23,"",0,-1))} -> 3.8832342e+09
A24: 23-feb | B24: =HLOOKUP($A24,ESCENARIO[#All],7,FALSE) -> 2.6851487e+10 | C24: =IF($B23<=Tabla5[[#This Row],[INVERSIONES FCI]],+Tabla5[[#This Row],[INVERSIONES FCI]]-C23,Tabla5[[#This Row],[INVERSIONES FCI]]) -> 2.2968253e+10 | D24: =IF($B23<=Tabla5[[#This Row],[INVERSIONES FCI]],+Tabla5[[#This Row],[INVERSIONES FCI]]-D23,Tabla5[[#This Row],[INVERSIONES FCI]]) -> 2.2968253e+10 | E24: =IF($B23<=Tabla5[[#This Row],[INVERSIONES FCI]],+Tabla5[[#This Row],[INVERSIONES FCI]]-E23,Tabla5[[#This Row],[INVERSIONES FCI]]) -> 2.2968253e+10 | F24: =IF($B23<=Tabla5[[#This Row],[INVERSIONES FCI]],+Tabla5[[#This Row],[INVERSIONES FCI]]-F23,Tabla5[[#This Row],[INVERSIONES FCI]]) -> 2.2968253e+10 | G24: =IF($B23<=Tabla5[[#This Row],[INVERSIONES FCI]],+Tabla5[[#This Row],[INVERSIONES FCI]]-G23,Tabla5[[#This Row],[INVERSIONES FCI]]) -> 2.2968253e+10 | H24: =IF($B23<=Tabla5[[#This Row],[INVERSIONES FCI]],+Tabla5[[#This Row],[INVERSIONES FCI]]-H23,Tabla5[[#This Row],[INVERSIONES FCI]]) -> 2.2968253e+10 | I24: =IF($B23<=Tabla5[[#This Row],[INVERSIONES FCI]],+Tabla5[[#This Row],[INVERSIONES FCI]]-I23,Tabla5[[#This Row],[INVERSIONES FCI]]) -> 2.2968253e+10 | J24: =IF($B23<=Tabla5[[#This Row],[INVERSIONES FCI]],+Tabla5[[#This Row],[INVERSIONES FCI]]-J23,Tabla5[[#This Row],[INVERSIONES FCI]]) -> 2.2968253e+10 | ... X24: =IF($B23<=Tabla5[[#This Row],[INVERSIONES FCI]],+Tabla5[[#This Row],[INVERSIONES FCI]]-X23,Tabla5[[#This Row],[INVERSIONES FCI]]) -> 2.2968253e+10 | Y24: {=IF(Tabla5[[#This Row],[FCI]]=0,0,_xlfn.XLOOKUP(TRUE,$B24:X24>0,$B24:X24,"",0,-1))} -> 2.2968253e+10
A25: 24-feb | B25: =HLOOKUP($A25,ESCENARIO[#All],7,FALSE) -> 2.8364051e+10 | C25: =IF($B24<=Tabla5[[#This Row],[INVERSIONES FCI]],+Tabla5[[#This Row],[INVERSIONES FCI]]-C24,Tabla5[[#This Row],[INVERSIONES FCI]]) -> 5.3957985e+09 | D25: =IF($B24<=Tabla5[[#This Row],[INVERSIONES FCI]],+Tabla5[[#This Row],[INVERSIONES FCI]]-D24,Tabla5[[#This Row],[INVERSIONES FCI]]) -> 5.3957985e+09 | E25: =IF($B24<=Tabla5[[#This Row],[INVERSIONES FCI]],+Tabla5[[#This Row],[INVERSIONES FCI]]-E24,Tabla5[[#This Row],[INVERSIONES FCI]]) -> 5.3957985e+09 | F25: =IF($B24<=Tabla5[[#This Row],[INVERSIONES FCI]],+Tabla5[[#This Row],[INVERSIONES FCI]]-F24,Tabla5[[#This Row],[INVERSIONES FCI]]) -> 5.3957985e+09 | G25: =IF($B24<=Tabla5[[#This Row],[INVERSIONES FCI]],+Tabla5[[#This Row],[INVERSIONES FCI]]-G24,Tabla5[[#This Row],[INVERSIONES FCI]]) -> 5.3957985e+09 | H25: =IF($B24<=Tabla5[[#This Row],[INVERSIONES FCI]],+Tabla5[[#This Row],[INVERSIONES FCI]]-H24,Tabla5[[#This Row],[INVERSIONES FCI]]) -> 5.3957985e+09 | I25: =IF($B24<=Tabla5[[#This Row],[INVERSIONES FCI]],+Tabla5[[#This Row],[INVERSIONES FCI]]-I24,Tabla5[[#This Row],[INVERSIONES FCI]]) -> 5.3957985e+09 | J25: =IF($B24<=Tabla5[[#This Row],[INVERSIONES FCI]],+Tabla5[[#This Row],[INVERSIONES FCI]]-J24,Tabla5[[#This Row],[INVERSIONES FCI]]) -> 5.3957985e+09 | ... Y25: =IF($B24<=Tabla5[[#This Row],[INVERSIONES FCI]],+Tabla5[[#This Row],[INVERSIONES FCI]]-Y24,Tabla5[[#This Row],[INVERSIONES FCI]]) -> 5.3957985e+09 | Z25: {=IF(Tabla5[[#This Row],[FCI]]=0,0,_xlfn.XLOOKUP(TRUE,$B25:Y25>0,$B25:Y25,"",0,-1))} -> 5.3957985e+09
A26: 25-feb | B26: =HLOOKUP($A26,ESCENARIO[#All],7,FALSE) -> 2.4081417e+10 | C26: =IF($B25<=Tabla5[[#This Row],[INVERSIONES FCI]],+Tabla5[[#This Row],[INVERSIONES FCI]]-C25,Tabla5[[#This Row],[INVERSIONES FCI]]) -> 2.4081417e+10 | D26: =IF($B25<=Tabla5[[#This Row],[INVERSIONES FCI]],+Tabla5[[#This Row],[INVERSIONES FCI]]-D25,Tabla5[[#This Row],[INVERSIONES FCI]]) -> 2.4081417e+10 | E26: =IF($B25<=Tabla5[[#This Row],[INVERSIONES FCI]],+Tabla5[[#This Row],[INVERSIONES FCI]]-E25,Tabla5[[#This Row],[INVERSIONES FCI]]) -> 2.4081417e+10 | F26: =IF($B25<=Tabla5[[#This Row],[INVERSIONES FCI]],+Tabla5[[#This Row],[INVERSIONES FCI]]-F25,Tabla5[[#This Row],[INVERSIONES FCI]]) -> 2.4081417e+10 | G26: =IF($B25<=Tabla5[[#This Row],[INVERSIONES FCI]],+Tabla5[[#This Row],[INVERSIONES FCI]]-G25,Tabla5[[#This Row],[INVERSIONES FCI]]) -> 2.4081417e+10 | H26: =IF($B25<=Tabla5[[#This Row],[INVERSIONES FCI]],+Tabla5[[#This Row],[INVERSIONES FCI]]-H25,Tabla5[[#This Row],[INVERSIONES FCI]]) -> 2.4081417e+10 | I26: =IF($B25<=Tabla5[[#This Row],[INVERSIONES FCI]],+Tabla5[[#This Row],[INVERSIONES FCI]]-I25,Tabla5[[#This Row],[INVERSIONES FCI]]) -> 2.4081417e+10 | J26: =IF($B25<=Tabla5[[#This Row],[INVERSIONES FCI]],+Tabla5[[#This Row],[INVERSIONES FCI]]-J25,Tabla5[[#This Row],[INVERSIONES FCI]]) -> 2.4081417e+10 | ... Z26: =IF($B25<=Tabla5[[#This Row],[INVERSIONES FCI]],+Tabla5[[#This Row],[INVERSIONES FCI]]-Z25,Tabla5[[#This Row],[INVERSIONES FCI]]) -> 2.4081417e+10 | AA26: {=IF(Tabla5[[#This Row],[FCI]]=0,0,_xlfn.XLOOKUP(TRUE,$B26:Z26>0,$B26:Z26,"",0,-1))} -> 2.4081417e+10
A27: 26-feb | B27: =HLOOKUP($A27,ESCENARIO[#All],7,FALSE) -> 2.0817484e+10 | C27: =IF($B26<=Tabla5[[#This Row],[INVERSIONES FCI]],+Tabla5[[#This Row],[INVERSIONES FCI]]-C26,Tabla5[[#This Row],[INVERSIONES FCI]]) -> 2.0817484e+10 | D27: =IF($B26<=Tabla5[[#This Row],[INVERSIONES FCI]],+Tabla5[[#This Row],[INVERSIONES FCI]]-D26,Tabla5[[#This Row],[INVERSIONES FCI]]) -> 2.0817484e+10 | E27: =IF($B26<=Tabla5[[#This Row],[INVERSIONES FCI]],+Tabla5[[#This Row],[INVERSIONES FCI]]-E26,Tabla5[[#This Row],[INVERSIONES FCI]]) -> 2.0817484e+10 | F27: =IF($B26<=Tabla5[[#This Row],[INVERSIONES FCI]],+Tabla5[[#This Row],[INVERSIONES FCI]]-F26,Tabla5[[#This Row],[INVERSIONES FCI]]) -> 2.0817484e+10 | G27: =IF($B26<=Tabla5[[#This Row],[INVERSIONES FCI]],+Tabla5[[#This Row],[INVERSIONES FCI]]-G26,Tabla5[[#This Row],[INVERSIONES FCI]]) -> 2.0817484e+10 | H27: =IF($B26<=Tabla5[[#This Row],[INVERSIONES FCI]],+Tabla5[[#This Row],[INVERSIONES FCI]]-H26,Tabla5[[#This Row],[INVERSIONES FCI]]) -> 2.0817484e+10 | I27: =IF($B26<=Tabla5[[#This Row],[INVERSIONES FCI]],+Tabla5[[#This Row],[INVERSIONES FCI]]-I26,Tabla5[[#This Row],[INVERSIONES FCI]]) -> 2.0817484e+10 | J27: =IF($B26<=Tabla5[[#This Row],[INVERSIONES FCI]],+Tabla5[[#This Row],[INVERSIONES FCI]]-J26,Tabla5[[#This Row],[INVERSIONES FCI]]) -> 2.0817484e+10 | ... AA27: =IF($B26<=Tabla5[[#This Row],[INVERSIONES FCI]],+Tabla5[[#This Row],[INVERSIONES FCI]]-AA26,Tabla5[[#This Row],[INVERSIONES FCI]]) -> 2.0817484e+10 | AB27: {=IF(Tabla5[[#This Row],[FCI]]=0,0,_xlfn.XLOOKUP(TRUE,$B27:AA27>0,$B27:AA27,"",0,-1))} -> 2.0817484e+10
A28: 27-feb | B28: =HLOOKUP($A28,ESCENARIO[#All],7,FALSE) -> 3.5949211e+09 | C28: =IF($B27<=Tabla5[[#This Row],[INVERSIONES FCI]],+Tabla5[[#This Row],[INVERSIONES FCI]]-C27,Tabla5[[#This Row],[INVERSIONES FCI]]) -> 3.5949211e+09 | D28: =IF($B27<=Tabla5[[#This Row],[INVERSIONES FCI]],+Tabla5[[#This Row],[INVERSIONES FCI]]-D27,Tabla5[[#This Row],[INVERSIONES FCI]]) -> 3.5949211e+09 | E28: =IF($B27<=Tabla5[[#This Row],[INVERSIONES FCI]],+Tabla5[[#This Row],[INVERSIONES FCI]]-E27,Tabla5[[#This Row],[INVERSIONES FCI]]) -> 3.5949211e+09 | F28: =IF($B27<=Tabla5[[#This Row],[INVERSIONES FCI]],+Tabla5[[#This Row],[INVERSIONES FCI]]-F27,Tabla5[[#This Row],[INVERSIONES FCI]]) -> 3.5949211e+09 | G28: =IF($B27<=Tabla5[[#This Row],[INVERSIONES FCI]],+Tabla5[[#This Row],[INVERSIONES FCI]]-G27,Tabla5[[#This Row],[INVERSIONES FCI]]) -> 3.5949211e+09 | H28: =IF($B27<=Tabla5[[#This Row],[INVERSIONES FCI]],+Tabla5[[#This Row],[INVERSIONES FCI]]-H27,Tabla5[[#This Row],[INVERSIONES FCI]]) -> 3.5949211e+09 | I28: =IF($B27<=Tabla5[[#This Row],[INVERSIONES FCI]],+Tabla5[[#This Row],[INVERSIONES FCI]]-I27,Tabla5[[#This Row],[INVERSIONES FCI]]) -> 3.5949211e+09 | J28: =IF($B27<=Tabla5[[#This Row],[INVERSIONES FCI]],+Tabla5[[#This Row],[INVERSIONES FCI]]-J27,Tabla5[[#This Row],[INVERSIONES FCI]]) -> 3.5949211e+09 | ... AB28: =IF($B27<=Tabla5[[#This Row],[INVERSIONES FCI]],+Tabla5[[#This Row],[INVERSIONES FCI]]-AB27,Tabla5[[#This Row],[INVERSIONES FCI]]) -> 3.5949211e+09 | AC28: {=IF(Tabla5[[#This Row],[FCI]]=0,0,_xlfn.XLOOKUP(TRUE,$B28:AB28>0,$B28:AB28,"",0,-1))} -> 3.5949211e+09
A29: 28-feb | B29: =HLOOKUP($A29,ESCENARIO[#All],7,FALSE) -> 1840000000 | C29: =IF($B28<=Tabla5[[#This Row],[INVERSIONES FCI]],+Tabla5[[#This Row],[INVERSIONES FCI]]-C28,Tabla5[[#This Row],[INVERSIONES FCI]]) -> 1840000000 | D29: =IF($B28<=Tabla5[[#This Row],[INVERSIONES FCI]],+Tabla5[[#This Row],[INVERSIONES FCI]]-D28,Tabla5[[#This Row],[INVERSIONES FCI]]) -> 1840000000 | E29: =IF($B28<=Tabla5[[#This Row],[INVERSIONES FCI]],+Tabla5[[#This Row],[INVERSIONES FCI]]-E28,Tabla5[[#This Row],[INVERSIONES FCI]]) -> 1840000000 | F29: =IF($B28<=Tabla5[[#This Row],[INVERSIONES FCI]],+Tabla5[[#This Row],[INVERSIONES FCI]]-F28,Tabla5[[#This Row],[INVERSIONES FCI]]) -> 1840000000 | G29: =IF($B28<=Tabla5[[#This Row],[INVERSIONES FCI]],+Tabla5[[#This Row],[INVERSIONES FCI]]-G28,Tabla5[[#This Row],[INVERSIONES FCI]]) -> 1840000000 | H29: =IF($B28<=Tabla5[[#This Row],[INVERSIONES FCI]],+Tabla5[[#This Row],[INVERSIONES FCI]]-H28,Tabla5[[#This Row],[INVERSIONES FCI]]) -> 1840000000 | I29: =IF($B28<=Tabla5[[#This Row],[INVERSIONES FCI]],+Tabla5[[#This Row],[INVERSIONES FCI]]-I28,Tabla5[[#This Row],[INVERSIONES FCI]]) -> 1840000000 | J29: =IF($B28<=Tabla5[[#This Row],[INVERSIONES FCI]],+Tabla5[[#This Row],[INVERSIONES FCI]]-J28,Tabla5[[#This Row],[INVERSIONES FCI]]) -> 1840000000 | ... AC29: =IF($B28<=Tabla5[[#This Row],[INVERSIONES FCI]],+Tabla5[[#This Row],[INVERSIONES FCI]]-AC28,Tabla5[[#This Row],[INVERSIONES FCI]]) -> 1840000000 | AD29: {=IF(Tabla5[[#This Row],[FCI]]=0,0,_xlfn.XLOOKUP(TRUE,$B29:AC29>0,$B29:AC29,"",0,-1))} -> 1840000000
A30: 01-mar | B30: =HLOOKUP($A30,ESCENARIO[#All],7,FALSE) -> 2378000000 | C30: =IF($B29<=Tabla5[[#This Row],[INVERSIONES FCI]],+Tabla5[[#This Row],[INVERSIONES FCI]]-C29,Tabla5[[#This Row],[INVERSIONES FCI]]) -> 538000000 | D30: =IF($B29<=Tabla5[[#This Row],[INVERSIONES FCI]],+Tabla5[[#This Row],[INVERSIONES FCI]]-D29,Tabla5[[#This Row],[INVERSIONES FCI]]) -> 538000000 | E30: =IF($B29<=Tabla5[[#This Row],[INVERSIONES FCI]],+Tabla5[[#This Row],[INVERSIONES FCI]]-E29,Tabla5[[#This Row],[INVERSIONES FCI]]) -> 538000000 | F30: =IF($B29<=Tabla5[[#This Row],[INVERSIONES FCI]],+Tabla5[[#This Row],[INVERSIONES FCI]]-F29,Tabla5[[#This Row],[INVERSIONES FCI]]) -> 538000000 | G30: =IF($B29<=Tabla5[[#This Row],[INVERSIONES FCI]],+Tabla5[[#This Row],[INVERSIONES FCI]]-G29,Tabla5[[#This Row],[INVERSIONES FCI]]) -> 538000000 | H30: =IF($B29<=Tabla5[[#This Row],[INVERSIONES FCI]],+Tabla5[[#This Row],[INVERSIONES FCI]]-H29,Tabla5[[#This Row],[INVERSIONES FCI]]) -> 538000000 | I30: =IF($B29<=Tabla5[[#This Row],[INVERSIONES FCI]],+Tabla5[[#This Row],[INVERSIONES FCI]]-I29,Tabla5[[#This Row],[INVERSIONES FCI]]) -> 538000000 | J30: =IF($B29<=Tabla5[[#This Row],[INVERSIONES FCI]],+Tabla5[[#This Row],[INVERSIONES FCI]]-J29,Tabla5[[#This Row],[INVERSIONES FCI]]) -> 538000000 | ... AD30: =IF($B29<=Tabla5[[#This Row],[INVERSIONES FCI]],+Tabla5[[#This Row],[INVERSIONES FCI]]-AD29,Tabla5[[#This Row],[INVERSIONES FCI]]) -> 538000000 | AE30: {=IF(Tabla5[[#This Row],[FCI]]=0,0,_xlfn.XLOOKUP(TRUE,$B30:AD30>0,$B30:AD30,"",0,-1))} -> 538000000
A31: 02-mar | B31: =HLOOKUP($A31,ESCENARIO[#All],7,FALSE) -> 2378000000 | C31: =IF($B30<=Tabla5[[#This Row],[INVERSIONES FCI]],+Tabla5[[#This Row],[INVERSIONES FCI]]-C30,Tabla5[[#This Row],[INVERSIONES FCI]]) -> 1840000000 | D31: =IF($B30<=Tabla5[[#This Row],[INVERSIONES FCI]],+Tabla5[[#This Row],[INVERSIONES FCI]]-D30,Tabla5[[#This Row],[INVERSIONES FCI]]) -> 1840000000 | E31: =IF($B30<=Tabla5[[#This Row],[INVERSIONES FCI]],+Tabla5[[#This Row],[INVERSIONES FCI]]-E30,Tabla5[[#This Row],[INVERSIONES FCI]]) -> 1840000000 | F31: =IF($B30<=Tabla5[[#This Row],[INVERSIONES FCI]],+Tabla5[[#This Row],[INVERSIONES FCI]]-F30,Tabla5[[#This Row],[INVERSIONES FCI]]) -> 1840000000 | G31: =IF($B30<=Tabla5[[#This Row],[INVERSIONES FCI]],+Tabla5[[#This Row],[INVERSIONES FCI]]-G30,Tabla5[[#This Row],[INVERSIONES FCI]]) -> 1840000000 | H31: =IF($B30<=Tabla5[[#This Row],[INVERSIONES FCI]],+Tabla5[[#This Row],[INVERSIONES FCI]]-H30,Tabla5[[#This Row],[INVERSIONES FCI]]) -> 1840000000 | I31: =IF($B30<=Tabla5[[#This Row],[INVERSIONES FCI]],+Tabla5[[#This Row],[INVERSIONES FCI]]-I30,Tabla5[[#This Row],[INVERSIONES FCI]]) -> 1840000000 | J31: =IF($B30<=Tabla5[[#This Row],[INVERSIONES FCI]],+Tabla5[[#This Row],[INVERSIONES FCI]]-J30,Tabla5[[#This Row],[INVERSIONES FCI]]) -> 1840000000 | ... AE31: =IF($B30<=Tabla5[[#This Row],[INVERSIONES FCI]],+Tabla5[[#This Row],[INVERSIONES FCI]]-AE30,Tabla5[[#This Row],[INVERSIONES FCI]]) -> 1840000000 | AF31: {=IF(Tabla5[[#This Row],[FCI]]=0,0,_xlfn.XLOOKUP(TRUE,$B31:AE31>0,$B31:AE31,"",0,-1))} -> 1840000000
A32: 03-mar | B32: =HLOOKUP($A32,ESCENARIO[#All],7,FALSE) -> 1.9229327e+09 | C32: =IF($B31<=Tabla5[[#This Row],[INVERSIONES FCI]],+Tabla5[[#This Row],[INVERSIONES FCI]]-C31,Tabla5[[#This Row],[INVERSIONES FCI]]) -> 1.9229327e+09 | D32: =IF($B31<=Tabla5[[#This Row],[INVERSIONES FCI]],+Tabla5[[#This Row],[INVERSIONES FCI]]-D31,Tabla5[[#This Row],[INVERSIONES FCI]]) -> 1.9229327e+09 | E32: =IF($B31<=Tabla5[[#This Row],[INVERSIONES FCI]],+Tabla5[[#This Row],[INVERSIONES FCI]]-E31,Tabla5[[#This Row],[INVERSIONES FCI]]) -> 1.9229327e+09 | F32: =IF($B31<=Tabla5[[#This Row],[INVERSIONES FCI]],+Tabla5[[#This Row],[INVERSIONES FCI]]-F31,Tabla5[[#This Row],[INVERSIONES FCI]]) -> 1.9229327e+09 | G32: =IF($B31<=Tabla5[[#This Row],[INVERSIONES FCI]],+Tabla5[[#This Row],[INVERSIONES FCI]]-G31,Tabla5[[#This Row],[INVERSIONES FCI]]) -> 1.9229327e+09 | H32: =IF($B31<=Tabla5[[#This Row],[INVERSIONES FCI]],+Tabla5[[#This Row],[INVERSIONES FCI]]-H31,Tabla5[[#This Row],[INVERSIONES FCI]]) -> 1.9229327e+09 | I32: =IF($B31<=Tabla5[[#This Row],[INVERSIONES FCI]],+Tabla5[[#This Row],[INVERSIONES FCI]]-I31,Tabla5[[#This Row],[INVERSIONES FCI]]) -> 1.9229327e+09 | J32: =IF($B31<=Tabla5[[#This Row],[INVERSIONES FCI]],+Tabla5[[#This Row],[INVERSIONES FCI]]-J31,Tabla5[[#This Row],[INVERSIONES FCI]]) -> 1.9229327e+09 | ... AF32: =IF($B31<=Tabla5[[#This Row],[INVERSIONES FCI]],+Tabla5[[#This Row],[INVERSIONES FCI]]-AF31,Tabla5[[#This Row],[INVERSIONES FCI]]) -> 1.9229327e+09 | AG32: {=IF(Tabla5[[#This Row],[FCI]]=0,0,_xlfn.XLOOKUP(TRUE,$B32:AF32>0,$B32:AF32,"",0,-1))} -> 1.9229327e+09
A33: 04-mar | B33: =HLOOKUP($A33,ESCENARIO[#All],7,FALSE) -> 2.8128905e+09 | C33: =IF($B32<=Tabla5[[#This Row],[INVERSIONES FCI]],+Tabla5[[#This Row],[INVERSIONES FCI]]-C32,Tabla5[[#This Row],[INVERSIONES FCI]]) -> 8.8995777e+08 | D33: =IF($B32<=Tabla5[[#This Row],[INVERSIONES FCI]],+Tabla5[[#This Row],[INVERSIONES FCI]]-D32,Tabla5[[#This Row],[INVERSIONES FCI]]) -> 8.8995777e+08 | E33: =IF($B32<=Tabla5[[#This Row],[INVERSIONES FCI]],+Tabla5[[#This Row],[INVERSIONES FCI]]-E32,Tabla5[[#This Row],[INVERSIONES FCI]]) -> 8.8995777e+08 | F33: =IF($B32<=Tabla5[[#This Row],[INVERSIONES FCI]],+Tabla5[[#This Row],[INVERSIONES FCI]]-F32,Tabla5[[#This Row],[INVERSIONES FCI]]) -> 8.8995777e+08 | G33: =IF($B32<=Tabla5[[#This Row],[INVERSIONES FCI]],+Tabla5[[#This Row],[INVERSIONES FCI]]-G32,Tabla5[[#This Row],[INVERSIONES FCI]]) -> 8.8995777e+08 | H33: =IF($B32<=Tabla5[[#This Row],[INVERSIONES FCI]],+Tabla5[[#This Row],[INVERSIONES FCI]]-H32,Tabla5[[#This Row],[INVERSIONES FCI]]) -> 8.8995777e+08 | I33: =IF($B32<=Tabla5[[#This Row],[INVERSIONES FCI]],+Tabla5[[#This Row],[INVERSIONES FCI]]-I32,Tabla5[[#This Row],[INVERSIONES FCI]]) -> 8.8995777e+08 | J33: =IF($B32<=Tabla5[[#This Row],[INVERSIONES FCI]],+Tabla5[[#This Row],[INVERSIONES FCI]]-J32,Tabla5[[#This Row],[INVERSIONES FCI]]) -> 8.8995777e+08 | ... AG33: =IF($B32<=Tabla5[[#This Row],[INVERSIONES FCI]],+Tabla5[[#This Row],[INVERSIONES FCI]]-AG32,Tabla5[[#This Row],[INVERSIONES FCI]]) -> 8.8995777e+08 | AH33: {=IF(Tabla5[[#This Row],[FCI]]=0,0,_xlfn.XLOOKUP(TRUE,$B33:AG33>0,$B33:AG33,"",0,-1))} -> 8.8995777e+08
A34: 05-mar | B34: =HLOOKUP($A34,ESCENARIO[#All],7,FALSE) -> 3.3195952e+09 | C34: =IF($B33<=Tabla5[[#This Row],[INVERSIONES FCI]],+Tabla5[[#This Row],[INVERSIONES FCI]]-C33,Tabla5[[#This Row],[INVERSIONES FCI]]) -> 2.4296375e+09 | D34: =IF($B33<=Tabla5[[#This Row],[INVERSIONES FCI]],+Tabla5[[#This Row],[INVERSIONES FCI]]-D33,Tabla5[[#This Row],[INVERSIONES FCI]]) -> 2.4296375e+09 | E34: =IF($B33<=Tabla5[[#This Row],[INVERSIONES FCI]],+Tabla5[[#This Row],[INVERSIONES FCI]]-E33,Tabla5[[#This Row],[INVERSIONES FCI]]) -> 2.4296375e+09 | F34: =IF($B33<=Tabla5[[#This Row],[INVERSIONES FCI]],+Tabla5[[#This Row],[INVERSIONES FCI]]-F33,Tabla5[[#This Row],[INVERSIONES FCI]]) -> 2.4296375e+09 | G34: =IF($B33<=Tabla5[[#This Row],[INVERSIONES FCI]],+Tabla5[[#This Row],[INVERSIONES FCI]]-G33,Tabla5[[#This Row],[INVERSIONES FCI]]) -> 2.4296375e+09 | H34: =IF($B33<=Tabla5[[#This Row],[INVERSIONES FCI]],+Tabla5[[#This Row],[INVERSIONES FCI]]-H33,Tabla5[[#This Row],[INVERSIONES FCI]]) -> 2.4296375e+09 | I34: =IF($B33<=Tabla5[[#This Row],[INVERSIONES FCI]],+Tabla5[[#This Row],[INVERSIONES FCI]]-I33,Tabla5[[#This Row],[INVERSIONES FCI]]) -> 2.4296375e+09 | J34: =IF($B33<=Tabla5[[#This Row],[INVERSIONES FCI]],+Tabla5[[#This Row],[INVERSIONES FCI]]-J33,Tabla5[[#This Row],[INVERSIONES FCI]]) -> 2.4296375e+09 | ... AH34: =IF($B33<=Tabla5[[#This Row],[INVERSIONES FCI]],+Tabla5[[#This Row],[INVERSIONES FCI]]-AH33,Tabla5[[#This Row],[INVERSIONES FCI]]) -> 2.4296375e+09 | AI34: {=IF(Tabla5[[#This Row],[FCI]]=0,0,_xlfn.XLOOKUP(TRUE,$B34:AH34>0,$B34:AH34,"",0,-1))} -> 2.4296375e+09
A35: 06-mar | B35: =HLOOKUP($A35,ESCENARIO[#All],7,FALSE) -> 3.959609e+09 | C35: =IF($B34<=Tabla5[[#This Row],[INVERSIONES FCI]],+Tabla5[[#This Row],[INVERSIONES FCI]]-C34,Tabla5[[#This Row],[INVERSIONES FCI]]) -> 1.5299716e+09 | D35: =IF($B34<=Tabla5[[#This Row],[INVERSIONES FCI]],+Tabla5[[#This Row],[INVERSIONES FCI]]-D34,Tabla5[[#This Row],[INVERSIONES FCI]]) -> 1.5299716e+09 | E35: =IF($B34<=Tabla5[[#This Row],[INVERSIONES FCI]],+Tabla5[[#This Row],[INVERSIONES FCI]]-E34,Tabla5[[#This Row],[INVERSIONES FCI]]) -> 1.5299716e+09 | F35: =IF($B34<=Tabla5[[#This Row],[INVERSIONES FCI]],+Tabla5[[#This Row],[INVERSIONES FCI]]-F34,Tabla5[[#This Row],[INVERSIONES FCI]]) -> 1.5299716e+09 | G35: =IF($B34<=Tabla5[[#This Row],[INVERSIONES FCI]],+Tabla5[[#This Row],[INVERSIONES FCI]]-G34,Tabla5[[#This Row],[INVERSIONES FCI]]) -> 1.5299716e+09 | H35: =IF($B34<=Tabla5[[#This Row],[INVERSIONES FCI]],+Tabla5[[#This Row],[INVERSIONES FCI]]-H34,Tabla5[[#This Row],[INVERSIONES FCI]]) -> 1.5299716e+09 | I35: =IF($B34<=Tabla5[[#This Row],[INVERSIONES FCI]],+Tabla5[[#This Row],[INVERSIONES FCI]]-I34,Tabla5[[#This Row],[INVERSIONES FCI]]) -> 1.5299716e+09 | J35: =IF($B34<=Tabla5[[#This Row],[INVERSIONES FCI]],+Tabla5[[#This Row],[INVERSIONES FCI]]-J34,Tabla5[[#This Row],[INVERSIONES FCI]]) -> 1.5299716e+09 | ... AI35: =IF($B34<=Tabla5[[#This Row],[INVERSIONES FCI]],+Tabla5[[#This Row],[INVERSIONES FCI]]-AI34,Tabla5[[#This Row],[INVERSIONES FCI]]) -> 1.5299716e+09 | AJ35: {=IF(Tabla5[[#This Row],[FCI]]=0,0,_xlfn.XLOOKUP(TRUE,$B35:AI35>0,$B35:AI35,"",0,-1))} -> 1.5299716e+09
A36: 07-mar | B36: =HLOOKUP($A36,ESCENARIO[#All],7,FALSE) -> 4.7908109e+09 | C36: =IF($B35<=Tabla5[[#This Row],[INVERSIONES FCI]],+Tabla5[[#This Row],[INVERSIONES FCI]]-C35,Tabla5[[#This Row],[INVERSIONES FCI]]) -> 3.2608394e+09 | D36: =IF($B35<=Tabla5[[#This Row],[INVERSIONES FCI]],+Tabla5[[#This Row],[INVERSIONES FCI]]-D35,Tabla5[[#This Row],[INVERSIONES FCI]]) -> 3.2608394e+09 | E36: =IF($B35<=Tabla5[[#This Row],[INVERSIONES FCI]],+Tabla5[[#This Row],[INVERSIONES FCI]]-E35,Tabla5[[#This Row],[INVERSIONES FCI]]) -> 3.2608394e+09 | F36: =IF($B35<=Tabla5[[#This Row],[INVERSIONES FCI]],+Tabla5[[#This Row],[INVERSIONES FCI]]-F35,Tabla5[[#This Row],[INVERSIONES FCI]]) -> 3.2608394e+09 | G36: =IF($B35<=Tabla5[[#This Row],[INVERSIONES FCI]],+Tabla5[[#This Row],[INVERSIONES FCI]]-G35,Tabla5[[#This Row],[INVERSIONES FCI]]) -> 3.2608394e+09 | H36: =IF($B35<=Tabla5[[#This Row],[INVERSIONES FCI]],+Tabla5[[#This Row],[INVERSIONES FCI]]-H35,Tabla5[[#This Row],[INVERSIONES FCI]]) -> 3.2608394e+09 | I36: =IF($B35<=Tabla5[[#This Row],[INVERSIONES FCI]],+Tabla5[[#This Row],[INVERSIONES FCI]]-I35,Tabla5[[#This Row],[INVERSIONES FCI]]) -> 3.2608394e+09 | J36: =IF($B35<=Tabla5[[#This Row],[INVERSIONES FCI]],+Tabla5[[#This Row],[INVERSIONES FCI]]-J35,Tabla5[[#This Row],[INVERSIONES FCI]]) -> 3.2608394e+09 | ... AJ36: =IF($B35<=Tabla5[[#This Row],[INVERSIONES FCI]],+Tabla5[[#This Row],[INVERSIONES FCI]]-AJ35,Tabla5[[#This Row],[INVERSIONES FCI]]) -> 3.2608394e+09 | AK36: {=IF(Tabla5[[#This Row],[FCI]]=0,0,_xlfn.XLOOKUP(TRUE,$B36:AJ36>0,$B36:AJ36,"",0,-1))} -> 3.2608394e+09
A37: 08-mar | B37: =HLOOKUP($A37,ESCENARIO[#All],7,FALSE) -> 4.7908109e+09 | C37: =IF($B36<=Tabla5[[#This Row],[INVERSIONES FCI]],+Tabla5[[#This Row],[INVERSIONES FCI]]-C36,Tabla5[[#This Row],[INVERSIONES FCI]]) -> 1.5299716e+09 | D37: =IF($B36<=Tabla5[[#This Row],[INVERSIONES FCI]],+Tabla5[[#This Row],[INVERSIONES FCI]]-D36,Tabla5[[#This Row],[INVERSIONES FCI]]) -> 1.5299716e+09 | E37: =IF($B36<=Tabla5[[#This Row],[INVERSIONES FCI]],+Tabla5[[#This Row],[INVERSIONES FCI]]-E36,Tabla5[[#This Row],[INVERSIONES FCI]]) -> 1.5299716e+09 | F37: =IF($B36<=Tabla5[[#This Row],[INVERSIONES FCI]],+Tabla5[[#This Row],[INVERSIONES FCI]]-F36,Tabla5[[#This Row],[INVERSIONES FCI]]) -> 1.5299716e+09 | G37: =IF($B36<=Tabla5[[#This Row],[INVERSIONES FCI]],+Tabla5[[#This Row],[INVERSIONES FCI]]-G36,Tabla5[[#This Row],[INVERSIONES FCI]]) -> 1.5299716e+09 | H37: =IF($B36<=Tabla5[[#This Row],[INVERSIONES FCI]],+Tabla5[[#This Row],[INVERSIONES FCI]]-H36,Tabla5[[#This Row],[INVERSIONES FCI]]) -> 1.5299716e+09 | I37: =IF($B36<=Tabla5[[#This Row],[INVERSIONES FCI]],+Tabla5[[#This Row],[INVERSIONES FCI]]-I36,Tabla5[[#This Row],[INVERSIONES FCI]]) -> 1.5299716e+09 | J37: =IF($B36<=Tabla5[[#This Row],[INVERSIONES FCI]],+Tabla5[[#This Row],[INVERSIONES FCI]]-J36,Tabla5[[#This Row],[INVERSIONES FCI]]) -> 1.5299716e+09 | ... AK37: =IF($B36<=Tabla5[[#This Row],[INVERSIONES FCI]],+Tabla5[[#This Row],[INVERSIONES FCI]]-AK36,Tabla5[[#This Row],[INVERSIONES FCI]]) -> 1.5299716e+09 | AL37: {=IF(Tabla5[[#This Row],[FCI]]=0,0,_xlfn.XLOOKUP(TRUE,$B37:AK37>0,$B37:AK37,"",0,-1))} -> 1.5299716e+09
A38: 09-mar | B38: =HLOOKUP($A38,ESCENARIO[#All],7,FALSE) -> 4.7908109e+09 | C38: =IF($B37<=Tabla5[[#This Row],[INVERSIONES FCI]],+Tabla5[[#This Row],[INVERSIONES FCI]]-C37,Tabla5[[#This Row],[INVERSIONES FCI]]) -> 3.2608394e+09 | D38: =IF($B37<=Tabla5[[#This Row],[INVERSIONES FCI]],+Tabla5[[#This Row],[INVERSIONES FCI]]-D37,Tabla5[[#This Row],[INVERSIONES FCI]]) -> 3.2608394e+09 | E38: =IF($B37<=Tabla5[[#This Row],[INVERSIONES FCI]],+Tabla5[[#This Row],[INVERSIONES FCI]]-E37,Tabla5[[#This Row],[INVERSIONES FCI]]) -> 3.2608394e+09 | F38: =IF($B37<=Tabla5[[#This Row],[INVERSIONES FCI]],+Tabla5[[#This Row],[INVERSIONES FCI]]-F37,Tabla5[[#This Row],[INVERSIONES FCI]]) -> 3.2608394e+09 | G38: =IF($B37<=Tabla5[[#This Row],[INVERSIONES FCI]],+Tabla5[[#This Row],[INVERSIONES FCI]]-G37,Tabla5[[#This Row],[INVERSIONES FCI]]) -> 3.2608394e+09 | H38: =IF($B37<=Tabla5[[#This Row],[INVERSIONES FCI]],+Tabla5[[#This Row],[INVERSIONES FCI]]-H37,Tabla5[[#This Row],[INVERSIONES FCI]]) -> 3.2608394e+09 | I38: =IF($B37<=Tabla5[[#This Row],[INVERSIONES FCI]],+Tabla5[[#This Row],[INVERSIONES FCI]]-I37,Tabla5[[#This Row],[INVERSIONES FCI]]) -> 3.2608394e+09 | J38: =IF($B37<=Tabla5[[#This Row],[INVERSIONES FCI]],+Tabla5[[#This Row],[INVERSIONES FCI]]-J37,Tabla5[[#This Row],[INVERSIONES FCI]]) -> 3.2608394e+09 | ... AL38: =IF($B37<=Tabla5[[#This Row],[INVERSIONES FCI]],+Tabla5[[#This Row],[INVERSIONES FCI]]-AL37,Tabla5[[#This Row],[INVERSIONES FCI]]) -> 3.2608394e+09 | AM38: {=IF(Tabla5[[#This Row],[FCI]]=0,0,_xlfn.XLOOKUP(TRUE,$B38:AL38>0,$B38:AL38,"",0,-1))} -> 3.2608394e+09
A39: 10-mar | B39: =HLOOKUP($A39,ESCENARIO[#All],7,FALSE) -> 6.2410194e+09 | C39: =IF($B38<=Tabla5[[#This Row],[INVERSIONES FCI]],+Tabla5[[#This Row],[INVERSIONES FCI]]-C38,Tabla5[[#This Row],[INVERSIONES FCI]]) -> 2.98018e+09 | D39: =IF($B38<=Tabla5[[#This Row],[INVERSIONES FCI]],+Tabla5[[#This Row],[INVERSIONES FCI]]-D38,Tabla5[[#This Row],[INVERSIONES FCI]]) -> 2.98018e+09 | E39: =IF($B38<=Tabla5[[#This Row],[INVERSIONES FCI]],+Tabla5[[#This Row],[INVERSIONES FCI]]-E38,Tabla5[[#This Row],[INVERSIONES FCI]]) -> 2.98018e+09 | F39: =IF($B38<=Tabla5[[#This Row],[INVERSIONES FCI]],+Tabla5[[#This Row],[INVERSIONES FCI]]-F38,Tabla5[[#This Row],[INVERSIONES FCI]]) -> 2.98018e+09 | G39: =IF($B38<=Tabla5[[#This Row],[INVERSIONES FCI]],+Tabla5[[#This Row],[INVERSIONES FCI]]-G38,Tabla5[[#This Row],[INVERSIONES FCI]]) -> 2.98018e+09 | H39: =IF($B38<=Tabla5[[#This Row],[INVERSIONES FCI]],+Tabla5[[#This Row],[INVERSIONES FCI]]-H38,Tabla5[[#This Row],[INVERSIONES FCI]]) -> 2.98018e+09 | I39: =IF($B38<=Tabla5[[#This Row],[INVERSIONES FCI]],+Tabla5[[#This Row],[INVERSIONES FCI]]-I38,Tabla5[[#This Row],[INVERSIONES FCI]]) -> 2.98018e+09 | J39: =IF($B38<=Tabla5[[#This Row],[INVERSIONES FCI]],+Tabla5[[#This Row],[INVERSIONES FCI]]-J38,Tabla5[[#This Row],[INVERSIONES FCI]]) -> 2.98018e+09 | ... AM39: =IF($B38<=Tabla5[[#This Row],[INVERSIONES FCI]],+Tabla5[[#This Row],[INVERSIONES FCI]]-AM38,Tabla5[[#This Row],[INVERSIONES FCI]]) -> 2.98018e+09 | AN39: {=IF(Tabla5[[#This Row],[FCI]]=0,0,_xlfn.XLOOKUP(TRUE,$B39:AM39>0,$B39:AM39,"",0,-1))} -> 2.98018e+09
A40: 11-mar | B40: =HLOOKUP($A40,ESCENARIO[#All],7,FALSE) -> 1.361768e+10 | C40: =IF($B39<=Tabla5[[#This Row],[INVERSIONES FCI]],+Tabla5[[#This Row],[INVERSIONES FCI]]-C39,Tabla5[[#This Row],[INVERSIONES FCI]]) -> 1.06375e+10 | D40: =IF($B39<=Tabla5[[#This Row],[INVERSIONES FCI]],+Tabla5[[#This Row],[INVERSIONES FCI]]-D39,Tabla5[[#This Row],[INVERSIONES FCI]]) -> 1.06375e+10 | E40: =IF($B39<=Tabla5[[#This Row],[INVERSIONES FCI]],+Tabla5[[#This Row],[INVERSIONES FCI]]-E39,Tabla5[[#This Row],[INVERSIONES FCI]]) -> 1.06375e+10 | F40: =IF($B39<=Tabla5[[#This Row],[INVERSIONES FCI]],+Tabla5[[#This Row],[INVERSIONES FCI]]-F39,Tabla5[[#This Row],[INVERSIONES FCI]]) -> 1.06375e+10 | G40: =IF($B39<=Tabla5[[#This Row],[INVERSIONES FCI]],+Tabla5[[#This Row],[INVERSIONES FCI]]-G39,Tabla5[[#This Row],[INVERSIONES FCI]]) -> 1.06375e+10 | H40: =IF($B39<=Tabla5[[#This Row],[INVERSIONES FCI]],+Tabla5[[#This Row],[INVERSIONES FCI]]-H39,Tabla5[[#This Row],[INVERSIONES FCI]]) -> 1.06375e+10 | I40: =IF($B39<=Tabla5[[#This Row],[INVERSIONES FCI]],+Tabla5[[#This Row],[INVERSIONES FCI]]-I39,Tabla5[[#This Row],[INVERSIONES FCI]]) -> 1.06375e+10 | J40: =IF($B39<=Tabla5[[#This Row],[INVERSIONES FCI]],+Tabla5[[#This Row],[INVERSIONES FCI]]-J39,Tabla5[[#This Row],[INVERSIONES FCI]]) -> 1.06375e+10 | ... AN40: =IF($B39<=Tabla5[[#This Row],[INVERSIONES FCI]],+Tabla5[[#This Row],[INVERSIONES FCI]]-AN39,Tabla5[[#This Row],[INVERSIONES FCI]]) -> 1.06375e+10 | AO40: {=IF(Tabla5[[#This Row],[FCI]]=0,0,_xlfn.XLOOKUP(TRUE,$B40:AN40>0,$B40:AN40,"",0,-1))} -> 1.06375e+10
A41: 12-mar | B41: =HLOOKUP($A41,ESCENARIO[#All],7,FALSE) -> 1.5046451e+10 | C41: =IF($B40<=Tabla5[[#This Row],[INVERSIONES FCI]],+Tabla5[[#This Row],[INVERSIONES FCI]]-C40,Tabla5[[#This Row],[INVERSIONES FCI]]) -> 4.4089511e+09 | D41: =IF($B40<=Tabla5[[#This Row],[INVERSIONES FCI]],+Tabla5[[#This Row],[INVERSIONES FCI]]-D40,Tabla5[[#This Row],[INVERSIONES FCI]]) -> 4.4089511e+09 | E41: =IF($B40<=Tabla5[[#This Row],[INVERSIONES FCI]],+Tabla5[[#This Row],[INVERSIONES FCI]]-E40,Tabla5[[#This Row],[INVERSIONES FCI]]) -> 4.4089511e+09 | F41: =IF($B40<=Tabla5[[#This Row],[INVERSIONES FCI]],+Tabla5[[#This Row],[INVERSIONES FCI]]-F40,Tabla5[[#This Row],[INVERSIONES FCI]]) -> 4.4089511e+09 | G41: =IF($B40<=Tabla5[[#This Row],[INVERSIONES FCI]],+Tabla5[[#This Row],[INVERSIONES FCI]]-G40,Tabla5[[#This Row],[INVERSIONES FCI]]) -> 4.4089511e+09 | H41: =IF($B40<=Tabla5[[#This Row],[INVERSIONES FCI]],+Tabla5[[#This Row],[INVERSIONES FCI]]-H40,Tabla5[[#This Row],[INVERSIONES FCI]]) -> 4.4089511e+09 | I41: =IF($B40<=Tabla5[[#This Row],[INVERSIONES FCI]],+Tabla5[[#This Row],[INVERSIONES FCI]]-I40,Tabla5[[#This Row],[INVERSIONES FCI]]) -> 4.4089511e+09 | J41: =IF($B40<=Tabla5[[#This Row],[INVERSIONES FCI]],+Tabla5[[#This Row],[INVERSIONES FCI]]-J40,Tabla5[[#This Row],[INVERSIONES FCI]]) -> 4.4089511e+09 | ... AO41: =IF($B40<=Tabla5[[#This Row],[INVERSIONES FCI]],+Tabla5[[#This Row],[INVERSIONES FCI]]-AO40,Tabla5[[#This Row],[INVERSIONES FCI]]) -> 4.4089511e+09 | AP41: {=IF(Tabla5[[#This Row],[FCI]]=0,0,_xlfn.XLOOKUP(TRUE,$B41:AO41>0,$B41:AO41,"",0,-1))} -> 4.4089511e+09
A42: 13-mar | B42: =HLOOKUP($A42,ESCENARIO[#All],7,FALSE) -> 1.480482e+10 | C42: =IF($B41<=Tabla5[[#This Row],[INVERSIONES FCI]],+Tabla5[[#This Row],[INVERSIONES FCI]]-C41,Tabla5[[#This Row],[INVERSIONES FCI]]) -> 1.480482e+10 | D42: =IF($B41<=Tabla5[[#This Row],[INVERSIONES FCI]],+Tabla5[[#This Row],[INVERSIONES FCI]]-D41,Tabla5[[#This Row],[INVERSIONES FCI]]) -> 1.480482e+10 | E42: =IF($B41<=Tabla5[[#This Row],[INVERSIONES FCI]],+Tabla5[[#This Row],[INVERSIONES FCI]]-E41,Tabla5[[#This Row],[INVERSIONES FCI]]) -> 1.480482e+10 | F42: =IF($B41<=Tabla5[[#This Row],[INVERSIONES FCI]],+Tabla5[[#This Row],[INVERSIONES FCI]]-F41,Tabla5[[#This Row],[INVERSIONES FCI]]) -> 1.480482e+10 | G42: =IF($B41<=Tabla5[[#This Row],[INVERSIONES FCI]],+Tabla5[[#This Row],[INVERSIONES FCI]]-G41,Tabla5[[#This Row],[INVERSIONES FCI]]) -> 1.480482e+10 | H42: =IF($B41<=Tabla5[[#This Row],[INVERSIONES FCI]],+Tabla5[[#This Row],[INVERSIONES FCI]]-H41,Tabla5[[#This Row],[INVERSIONES FCI]]) -> 1.480482e+10 | I42: =IF($B41<=Tabla5[[#This Row],[INVERSIONES FCI]],+Tabla5[[#This Row],[INVERSIONES FCI]]-I41,Tabla5[[#This Row],[INVERSIONES FCI]]) -> 1.480482e+10 | J42: =IF($B41<=Tabla5[[#This Row],[INVERSIONES FCI]],+Tabla5[[#This Row],[INVERSIONES FCI]]-J41,Tabla5[[#This Row],[INVERSIONES FCI]]) -> 1.480482e+10 | ... AP42: =IF($B41<=Tabla5[[#This Row],[INVERSIONES FCI]],+Tabla5[[#This Row],[INVERSIONES FCI]]-AP41,Tabla5[[#This Row],[INVERSIONES FCI]]) -> 1.480482e+10 | AQ42: {=IF(Tabla5[[#This Row],[FCI]]=0,0,_xlfn.XLOOKUP(TRUE,$B42:AP42>0,$B42:AP42,"",0,-1))} -> 1.480482e+10
A43: 14-mar | B43: =HLOOKUP($A43,ESCENARIO[#All],7,FALSE) -> 1.7500155e+10 | C43: =IF($B42<=Tabla5[[#This Row],[INVERSIONES FCI]],+Tabla5[[#This Row],[INVERSIONES FCI]]-C42,Tabla5[[#This Row],[INVERSIONES FCI]]) -> 2.695335e+09 | D43: =IF($B42<=Tabla5[[#This Row],[INVERSIONES FCI]],+Tabla5[[#This Row],[INVERSIONES FCI]]-D42,Tabla5[[#This Row],[INVERSIONES FCI]]) -> 2.695335e+09 | E43: =IF($B42<=Tabla5[[#This Row],[INVERSIONES FCI]],+Tabla5[[#This Row],[INVERSIONES FCI]]-E42,Tabla5[[#This Row],[INVERSIONES FCI]]) -> 2.695335e+09 | F43: =IF($B42<=Tabla5[[#This Row],[INVERSIONES FCI]],+Tabla5[[#This Row],[INVERSIONES FCI]]-F42,Tabla5[[#This Row],[INVERSIONES FCI]]) -> 2.695335e+09 | G43: =IF($B42<=Tabla5[[#This Row],[INVERSIONES FCI]],+Tabla5[[#This Row],[INVERSIONES FCI]]-G42,Tabla5[[#This Row],[INVERSIONES FCI]]) -> 2.695335e+09 | H43: =IF($B42<=Tabla5[[#This Row],[INVERSIONES FCI]],+Tabla5[[#This Row],[INVERSIONES FCI]]-H42,Tabla5[[#This Row],[INVERSIONES FCI]]) -> 2.695335e+09 | I43: =IF($B42<=Tabla5[[#This Row],[INVERSIONES FCI]],+Tabla5[[#This Row],[INVERSIONES FCI]]-I42,Tabla5[[#This Row],[INVERSIONES FCI]]) -> 2.695335e+09 | J43: =IF($B42<=Tabla5[[#This Row],[INVERSIONES FCI]],+Tabla5[[#This Row],[INVERSIONES FCI]]-J42,Tabla5[[#This Row],[INVERSIONES FCI]]) -> 2.695335e+09 | ... AQ43: =IF($B42<=Tabla5[[#This Row],[INVERSIONES FCI]],+Tabla5[[#This Row],[INVERSIONES FCI]]-AQ42,Tabla5[[#This Row],[INVERSIONES FCI]]) -> 2.695335e+09 | AR43: {=IF(Tabla5[[#This Row],[FCI]]=0,0,_xlfn.XLOOKUP(TRUE,$B43:AQ43>0,$B43:AQ43,"",0,-1))} -> 2.695335e+09
A44: 15-mar | B44: =HLOOKUP($A44,ESCENARIO[#All],7,FALSE) -> 1.7250155e+10 | C44: =IF($B43<=Tabla5[[#This Row],[INVERSIONES FCI]],+Tabla5[[#This Row],[INVERSIONES FCI]]-C43,Tabla5[[#This Row],[INVERSIONES FCI]]) -> 1.7250155e+10 | D44: =IF($B43<=Tabla5[[#This Row],[INVERSIONES FCI]],+Tabla5[[#This Row],[INVERSIONES FCI]]-D43,Tabla5[[#This Row],[INVERSIONES FCI]]) -> 1.7250155e+10 | E44: =IF($B43<=Tabla5[[#This Row],[INVERSIONES FCI]],+Tabla5[[#This Row],[INVERSIONES FCI]]-E43,Tabla5[[#This Row],[INVERSIONES FCI]]) -> 1.7250155e+10 | F44: =IF($B43<=Tabla5[[#This Row],[INVERSIONES FCI]],+Tabla5[[#This Row],[INVERSIONES FCI]]-F43,Tabla5[[#This Row],[INVERSIONES FCI]]) -> 1.7250155e+10 | G44: =IF($B43<=Tabla5[[#This Row],[INVERSIONES FCI]],+Tabla5[[#This Row],[INVERSIONES FCI]]-G43,Tabla5[[#This Row],[INVERSIONES FCI]]) -> 1.7250155e+10 | H44: =IF($B43<=Tabla5[[#This Row],[INVERSIONES FCI]],+Tabla5[[#This Row],[INVERSIONES FCI]]-H43,Tabla5[[#This Row],[INVERSIONES FCI]]) -> 1.7250155e+10 | I44: =IF($B43<=Tabla5[[#This Row],[INVERSIONES FCI]],+Tabla5[[#This Row],[INVERSIONES FCI]]-I43,Tabla5[[#This Row],[INVERSIONES FCI]]) -> 1.7250155e+10 | J44: =IF($B43<=Tabla5[[#This Row],[INVERSIONES FCI]],+Tabla5[[#This Row],[INVERSIONES FCI]]-J43,Tabla5[[#This Row],[INVERSIONES FCI]]) -> 1.7250155e+10 | ... AR44: =IF($B43<=Tabla5[[#This Row],[INVERSIONES FCI]],+Tabla5[[#This Row],[INVERSIONES FCI]]-AR43,Tabla5[[#This Row],[INVERSIONES FCI]]) -> 1.7250155e+10 | AS44: {=IF(Tabla5[[#This Row],[FCI]]=0,0,_xlfn.XLOOKUP(TRUE,$B44:AR44>0,$B44:AR44,"",0,-1))} -> 1.7250155e+10
A45: 16-mar | B45: =HLOOKUP($A45,ESCENARIO[#All],7,FALSE) -> 1.7250397e+10 | C45: =IF($B44<=Tabla5[[#This Row],[INVERSIONES FCI]],+Tabla5[[#This Row],[INVERSIONES FCI]]-C44,Tabla5[[#This Row],[INVERSIONES FCI]]) -> 241750 | D45: =IF($B44<=Tabla5[[#This Row],[INVERSIONES FCI]],+Tabla5[[#This Row],[INVERSIONES FCI]]-D44,Tabla5[[#This Row],[INVERSIONES FCI]]) -> 241750 | E45: =IF($B44<=Tabla5[[#This Row],[INVERSIONES FCI]],+Tabla5[[#This Row],[INVERSIONES FCI]]-E44,Tabla5[[#This Row],[INVERSIONES FCI]]) -> 241750 | F45: =IF($B44<=Tabla5[[#This Row],[INVERSIONES FCI]],+Tabla5[[#This Row],[INVERSIONES FCI]]-F44,Tabla5[[#This Row],[INVERSIONES FCI]]) -> 241750 | G45: =IF($B44<=Tabla5[[#This Row],[INVERSIONES FCI]],+Tabla5[[#This Row],[INVERSIONES FCI]]-G44,Tabla5[[#This Row],[INVERSIONES FCI]]) -> 241750 | H45: =IF($B44<=Tabla5[[#This Row],[INVERSIONES FCI]],+Tabla5[[#This Row],[INVERSIONES FCI]]-H44,Tabla5[[#This Row],[INVERSIONES FCI]]) -> 241750 | I45: =IF($B44<=Tabla5[[#This Row],[INVERSIONES FCI]],+Tabla5[[#This Row],[INVERSIONES FCI]]-I44,Tabla5[[#This Row],[INVERSIONES FCI]]) -> 241750 | J45: =IF($B44<=Tabla5[[#This Row],[INVERSIONES FCI]],+Tabla5[[#This Row],[INVERSIONES FCI]]-J44,Tabla5[[#This Row],[INVERSIONES FCI]]) -> 241750 | ... AS45: =IF($B44<=Tabla5[[#This Row],[INVERSIONES FCI]],+Tabla5[[#This Row],[INVERSIONES FCI]]-AS44,Tabla5[[#This Row],[INVERSIONES FCI]]) -> 241750 | AT45: {=IF(Tabla5[[#This Row],[FCI]]=0,0,_xlfn.XLOOKUP(TRUE,$B45:AS45>0,$B45:AS45,"",0,-1))} -> 241750
A46: 17-mar | B46: =HLOOKUP($A46,ESCENARIO[#All],7,FALSE) -> 1.9714094e+10 | C46: =IF($B45<=Tabla5[[#This Row],[INVERSIONES FCI]],+Tabla5[[#This Row],[INVERSIONES FCI]]-C45,Tabla5[[#This Row],[INVERSIONES FCI]]) -> 1.9713853e+10 | D46: =IF($B45<=Tabla5[[#This Row],[INVERSIONES FCI]],+Tabla5[[#This Row],[INVERSIONES FCI]]-D45,Tabla5[[#This Row],[INVERSIONES FCI]]) -> 1.9713853e+10 | E46: =IF($B45<=Tabla5[[#This Row],[INVERSIONES FCI]],+Tabla5[[#This Row],[INVERSIONES FCI]]-E45,Tabla5[[#This Row],[INVERSIONES FCI]]) -> 1.9713853e+10 | F46: =IF($B45<=Tabla5[[#This Row],[INVERSIONES FCI]],+Tabla5[[#This Row],[INVERSIONES FCI]]-F45,Tabla5[[#This Row],[INVERSIONES FCI]]) -> 1.9713853e+10 | G46: =IF($B45<=Tabla5[[#This Row],[INVERSIONES FCI]],+Tabla5[[#This Row],[INVERSIONES FCI]]-G45,Tabla5[[#This Row],[INVERSIONES FCI]]) -> 1.9713853e+10 | H46: =IF($B45<=Tabla5[[#This Row],[INVERSIONES FCI]],+Tabla5[[#This Row],[INVERSIONES FCI]]-H45,Tabla5[[#This Row],[INVERSIONES FCI]]) -> 1.9713853e+10 | I46: =IF($B45<=Tabla5[[#This Row],[INVERSIONES FCI]],+Tabla5[[#This Row],[INVERSIONES FCI]]-I45,Tabla5[[#This Row],[INVERSIONES FCI]]) -> 1.9713853e+10 | J46: =IF($B45<=Tabla5[[#This Row],[INVERSIONES FCI]],+Tabla5[[#This Row],[INVERSIONES FCI]]-J45,Tabla5[[#This Row],[INVERSIONES FCI]]) -> 1.9713853e+10 | ... AT46: =IF($B45<=Tabla5[[#This Row],[INVERSIONES FCI]],+Tabla5[[#This Row],[INVERSIONES FCI]]-AT45,Tabla5[[#This Row],[INVERSIONES FCI]]) -> 1.9713853e+10 | AU46: {=IF(Tabla5[[#This Row],[FCI]]=0,0,_xlfn.XLOOKUP(TRUE,$B46:AT46>0,$B46:AT46,"",0,-1))} -> 1.9713853e+10
A47: 18-mar | B47: =HLOOKUP($A47,ESCENARIO[#All],7,FALSE) -> 2.1027543e+10 | C47: =IF($B46<=Tabla5[[#This Row],[INVERSIONES FCI]],+Tabla5[[#This Row],[INVERSIONES FCI]]-C46,Tabla5[[#This Row],[INVERSIONES FCI]]) -> 1.3136903e+09 | D47: =IF($B46<=Tabla5[[#This Row],[INVERSIONES FCI]],+Tabla5[[#This Row],[INVERSIONES FCI]]-D46,Tabla5[[#This Row],[INVERSIONES FCI]]) -> 1.3136903e+09 | E47: =IF($B46<=Tabla5[[#This Row],[INVERSIONES FCI]],+Tabla5[[#This Row],[INVERSIONES FCI]]-E46,Tabla5[[#This Row],[INVERSIONES FCI]]) -> 1.3136903e+09 | F47: =IF($B46<=Tabla5[[#This Row],[INVERSIONES FCI]],+Tabla5[[#This Row],[INVERSIONES FCI]]-F46,Tabla5[[#This Row],[INVERSIONES FCI]]) -> 1.3136903e+09 | G47: =IF($B46<=Tabla5[[#This Row],[INVERSIONES FCI]],+Tabla5[[#This Row],[INVERSIONES FCI]]-G46,Tabla5[[#This Row],[INVERSIONES FCI]]) -> 1.3136903e+09 | H47: =IF($B46<=Tabla5[[#This Row],[INVERSIONES FCI]],+Tabla5[[#This Row],[INVERSIONES FCI]]-H46,Tabla5[[#This Row],[INVERSIONES FCI]]) -> 1.3136903e+09 | I47: =IF($B46<=Tabla5[[#This Row],[INVERSIONES FCI]],+Tabla5[[#This Row],[INVERSIONES FCI]]-I46,Tabla5[[#This Row],[INVERSIONES FCI]]) -> 1.3136903e+09 | J47: =IF($B46<=Tabla5[[#This Row],[INVERSIONES FCI]],+Tabla5[[#This Row],[INVERSIONES FCI]]-J46,Tabla5[[#This Row],[INVERSIONES FCI]]) -> 1.3136903e+09 | ... AU47: =IF($B46<=Tabla5[[#This Row],[INVERSIONES FCI]],+Tabla5[[#This Row],[INVERSIONES FCI]]-AU46,Tabla5[[#This Row],[INVERSIONES FCI]]) -> 1.3136903e+09 | AV47: {=IF(Tabla5[[#This Row],[FCI]]=0,0,_xlfn.XLOOKUP(TRUE,$B47:AU47>0,$B47:AU47,"",0,-1))} -> 1.3136903e+09
A48: 19-mar | B48: =HLOOKUP($A48,ESCENARIO[#All],7,FALSE) -> 2.0646171e+10 | C48: =IF($B47<=Tabla5[[#This Row],[INVERSIONES FCI]],+Tabla5[[#This Row],[INVERSIONES FCI]]-C47,Tabla5[[#This Row],[INVERSIONES FCI]]) -> 2.0646171e+10 | D48: =IF($B47<=Tabla5[[#This Row],[INVERSIONES FCI]],+Tabla5[[#This Row],[INVERSIONES FCI]]-D47,Tabla5[[#This Row],[INVERSIONES FCI]]) -> 2.0646171e+10 | E48: =IF($B47<=Tabla5[[#This Row],[INVERSIONES FCI]],+Tabla5[[#This Row],[INVERSIONES FCI]]-E47,Tabla5[[#This Row],[INVERSIONES FCI]]) -> 2.0646171e+10 | F48: =IF($B47<=Tabla5[[#This Row],[INVERSIONES FCI]],+Tabla5[[#This Row],[INVERSIONES FCI]]-F47,Tabla5[[#This Row],[INVERSIONES FCI]]) -> 2.0646171e+10 | G48: =IF($B47<=Tabla5[[#This Row],[INVERSIONES FCI]],+Tabla5[[#This Row],[INVERSIONES FCI]]-G47,Tabla5[[#This Row],[INVERSIONES FCI]]) -> 2.0646171e+10 | H48: =IF($B47<=Tabla5[[#This Row],[INVERSIONES FCI]],+Tabla5[[#This Row],[INVERSIONES FCI]]-H47,Tabla5[[#This Row],[INVERSIONES FCI]]) -> 2.0646171e+10 | I48: =IF($B47<=Tabla5[[#This Row],[INVERSIONES FCI]],+Tabla5[[#This Row],[INVERSIONES FCI]]-I47,Tabla5[[#This Row],[INVERSIONES FCI]]) -> 2.0646171e+10 | J48: =IF($B47<=Tabla5[[#This Row],[INVERSIONES FCI]],+Tabla5[[#This Row],[INVERSIONES FCI]]-J47,Tabla5[[#This Row],[INVERSIONES FCI]]) -> 2.0646171e+10 | ... AV48: =IF($B47<=Tabla5[[#This Row],[INVERSIONES FCI]],+Tabla5[[#This Row],[INVERSIONES FCI]]-AV47,Tabla5[[#This Row],[INVERSIONES FCI]]) -> 2.0646171e+10 | AW48: {=IF(Tabla5[[#This Row],[FCI]]=0,0,_xlfn.XLOOKUP(TRUE,$B48:AV48>0,$B48:AV48,"",0,-1))} -> 2.0646171e+10
A49: 20-mar | B49: =HLOOKUP($A49,ESCENARIO[#All],7,FALSE) -> 2.3289441e+10 | C49: =IF($B48<=Tabla5[[#This Row],[INVERSIONES FCI]],+Tabla5[[#This Row],[INVERSIONES FCI]]-C48,Tabla5[[#This Row],[INVERSIONES FCI]]) -> 2.6432704e+09 | D49: =IF($B48<=Tabla5[[#This Row],[INVERSIONES FCI]],+Tabla5[[#This Row],[INVERSIONES FCI]]-D48,Tabla5[[#This Row],[INVERSIONES FCI]]) -> 2.6432704e+09 | E49: =IF($B48<=Tabla5[[#This Row],[INVERSIONES FCI]],+Tabla5[[#This Row],[INVERSIONES FCI]]-E48,Tabla5[[#This Row],[INVERSIONES FCI]]) -> 2.6432704e+09 | F49: =IF($B48<=Tabla5[[#This Row],[INVERSIONES FCI]],+Tabla5[[#This Row],[INVERSIONES FCI]]-F48,Tabla5[[#This Row],[INVERSIONES FCI]]) -> 2.6432704e+09 | G49: =IF($B48<=Tabla5[[#This Row],[INVERSIONES FCI]],+Tabla5[[#This Row],[INVERSIONES FCI]]-G48,Tabla5[[#This Row],[INVERSIONES FCI]]) -> 2.6432704e+09 | H49: =IF($B48<=Tabla5[[#This Row],[INVERSIONES FCI]],+Tabla5[[#This Row],[INVERSIONES FCI]]-H48,Tabla5[[#This Row],[INVERSIONES FCI]]) -> 2.6432704e+09 | I49: =IF($B48<=Tabla5[[#This Row],[INVERSIONES FCI]],+Tabla5[[#This Row],[INVERSIONES FCI]]-I48,Tabla5[[#This Row],[INVERSIONES FCI]]) -> 2.6432704e+09 | J49: =IF($B48<=Tabla5[[#This Row],[INVERSIONES FCI]],+Tabla5[[#This Row],[INVERSIONES FCI]]-J48,Tabla5[[#This Row],[INVERSIONES FCI]]) -> 2.6432704e+09 | ... AW49: =IF($B48<=Tabla5[[#This Row],[INVERSIONES FCI]],+Tabla5[[#This Row],[INVERSIONES FCI]]-AW48,Tabla5[[#This Row],[INVERSIONES FCI]]) -> 2.6432704e+09 | AX49: {=IF(Tabla5[[#This Row],[FCI]]=0,0,_xlfn.XLOOKUP(TRUE,$B49:AW49>0,$B49:AW49,"",0,-1))} -> 2.6432704e+09
A50: 21-mar | B50: =HLOOKUP($A50,ESCENARIO[#All],7,FALSE) -> 2.6028021e+10 | C50: =IF($B49<=Tabla5[[#This Row],[INVERSIONES FCI]],+Tabla5[[#This Row],[INVERSIONES FCI]]-C49,Tabla5[[#This Row],[INVERSIONES FCI]]) -> 2.3384751e+10 | D50: =IF($B49<=Tabla5[[#This Row],[INVERSIONES FCI]],+Tabla5[[#This Row],[INVERSIONES FCI]]-D49,Tabla5[[#This Row],[INVERSIONES FCI]]) -> 2.3384751e+10 | E50: =IF($B49<=Tabla5[[#This Row],[INVERSIONES FCI]],+Tabla5[[#This Row],[INVERSIONES FCI]]-E49,Tabla5[[#This Row],[INVERSIONES FCI]]) -> 2.3384751e+10 | F50: =IF($B49<=Tabla5[[#This Row],[INVERSIONES FCI]],+Tabla5[[#This Row],[INVERSIONES FCI]]-F49,Tabla5[[#This Row],[INVERSIONES FCI]]) -> 2.3384751e+10 | G50: =IF($B49<=Tabla5[[#This Row],[INVERSIONES FCI]],+Tabla5[[#This Row],[INVERSIONES FCI]]-G49,Tabla5[[#This Row],[INVERSIONES FCI]]) -> 2.3384751e+10 | H50: =IF($B49<=Tabla5[[#This Row],[INVERSIONES FCI]],+Tabla5[[#This Row],[INVERSIONES FCI]]-H49,Tabla5[[#This Row],[INVERSIONES FCI]]) -> 2.3384751e+10 | I50: =IF($B49<=Tabla5[[#This Row],[INVERSIONES FCI]],+Tabla5[[#This Row],[INVERSIONES FCI]]-I49,Tabla5[[#This Row],[INVERSIONES FCI]]) -> 2.3384751e+10 | J50: =IF($B49<=Tabla5[[#This Row],[INVERSIONES FCI]],+Tabla5[[#This Row],[INVERSIONES FCI]]-J49,Tabla5[[#This Row],[INVERSIONES FCI]]) -> 2.3384751e+10 | ... AX50: =IF($B49<=Tabla5[[#This Row],[INVERSIONES FCI]],+Tabla5[[#This Row],[INVERSIONES FCI]]-AX49,Tabla5[[#This Row],[INVERSIONES FCI]]) -> 2.3384751e+10 | AY50: {=IF(Tabla5[[#This Row],[FCI]]=0,0,_xlfn.XLOOKUP(TRUE,$B50:AX50>0,$B50:AX50,"",0,-1))} -> 2.3384751e+10
A51: 22-mar | B51: =HLOOKUP($A51,ESCENARIO[#All],7,FALSE) -> 2.7569155e+10 | C51: =IF($B50<=Tabla5[[#This Row],[INVERSIONES FCI]],+Tabla5[[#This Row],[INVERSIONES FCI]]-C50,Tabla5[[#This Row],[INVERSIONES FCI]]) -> 4.1844043e+09 | D51: =IF($B50<=Tabla5[[#This Row],[INVERSIONES FCI]],+Tabla5[[#This Row],[INVERSIONES FCI]]-D50,Tabla5[[#This Row],[INVERSIONES FCI]]) -> 4.1844043e+09 | E51: =IF($B50<=Tabla5[[#This Row],[INVERSIONES FCI]],+Tabla5[[#This Row],[INVERSIONES FCI]]-E50,Tabla5[[#This Row],[INVERSIONES FCI]]) -> 4.1844043e+09 | F51: =IF($B50<=Tabla5[[#This Row],[INVERSIONES FCI]],+Tabla5[[#This Row],[INVERSIONES FCI]]-F50,Tabla5[[#This Row],[INVERSIONES FCI]]) -> 4.1844043e+09 | G51: =IF($B50<=Tabla5[[#This Row],[INVERSIONES FCI]],+Tabla5[[#This Row],[INVERSIONES FCI]]-G50,Tabla5[[#This Row],[INVERSIONES FCI]]) -> 4.1844043e+09 | H51: =IF($B50<=Tabla5[[#This Row],[INVERSIONES FCI]],+Tabla5[[#This Row],[INVERSIONES FCI]]-H50,Tabla5[[#This Row],[INVERSIONES FCI]]) -> 4.1844043e+09 | I51: =IF($B50<=Tabla5[[#This Row],[INVERSIONES FCI]],+Tabla5[[#This Row],[INVERSIONES FCI]]-I50,Tabla5[[#This Row],[INVERSIONES FCI]]) -> 4.1844043e+09 | J51: =IF($B50<=Tabla5[[#This Row],[INVERSIONES FCI]],+Tabla5[[#This Row],[INVERSIONES FCI]]-J50,Tabla5[[#This Row],[INVERSIONES FCI]]) -> 4.1844043e+09 | ... AY51: =IF($B50<=Tabla5[[#This Row],[INVERSIONES FCI]],+Tabla5[[#This Row],[INVERSIONES FCI]]-AY50,Tabla5[[#This Row],[INVERSIONES FCI]]) -> 4.1844043e+09 | AZ51: {=IF(Tabla5[[#This Row],[FCI]]=0,0,_xlfn.XLOOKUP(TRUE,$B51:AY51>0,$B51:AY51,"",0,-1))} -> 4.1844043e+09
A52: 23-mar | B52: =HLOOKUP($A52,ESCENARIO[#All],7,FALSE) -> 3.0496688e+10 | C52: =IF($B51<=Tabla5[[#This Row],[INVERSIONES FCI]],+Tabla5[[#This Row],[INVERSIONES FCI]]-C51,Tabla5[[#This Row],[INVERSIONES FCI]]) -> 2.6312283e+10 | D52: =IF($B51<=Tabla5[[#This Row],[INVERSIONES FCI]],+Tabla5[[#This Row],[INVERSIONES FCI]]-D51,Tabla5[[#This Row],[INVERSIONES FCI]]) -> 2.6312283e+10 | E52: =IF($B51<=Tabla5[[#This Row],[INVERSIONES FCI]],+Tabla5[[#This Row],[INVERSIONES FCI]]-E51,Tabla5[[#This Row],[INVERSIONES FCI]]) -> 2.6312283e+10 | F52: =IF($B51<=Tabla5[[#This Row],[INVERSIONES FCI]],+Tabla5[[#This Row],[INVERSIONES FCI]]-F51,Tabla5[[#This Row],[INVERSIONES FCI]]) -> 2.6312283e+10 | G52: =IF($B51<=Tabla5[[#This Row],[INVERSIONES FCI]],+Tabla5[[#This Row],[INVERSIONES FCI]]-G51,Tabla5[[#This Row],[INVERSIONES FCI]]) -> 2.6312283e+10 | H52: =IF($B51<=Tabla5[[#This Row],[INVERSIONES FCI]],+Tabla5[[#This Row],[INVERSIONES FCI]]-H51,Tabla5[[#This Row],[INVERSIONES FCI]]) -> 2.6312283e+10 | I52: =IF($B51<=Tabla5[[#This Row],[INVERSIONES FCI]],+Tabla5[[#This Row],[INVERSIONES FCI]]-I51,Tabla5[[#This Row],[INVERSIONES FCI]]) -> 2.6312283e+10 | J52: =IF($B51<=Tabla5[[#This Row],[INVERSIONES FCI]],+Tabla5[[#This Row],[INVERSIONES FCI]]-J51,Tabla5[[#This Row],[INVERSIONES FCI]]) -> 2.6312283e+10 | ... AZ52: =IF($B51<=Tabla5[[#This Row],[INVERSIONES FCI]],+Tabla5[[#This Row],[INVERSIONES FCI]]-AZ51,Tabla5[[#This Row],[INVERSIONES FCI]]) -> 2.6312283e+10 | BA52: {=IF(Tabla5[[#This Row],[FCI]]=0,0,_xlfn.XLOOKUP(TRUE,$B52:AZ52>0,$B52:AZ52,"",0,-1))} -> 2.6312283e+10
A53: 24-mar | B53: =HLOOKUP($A53,ESCENARIO[#All],7,FALSE) -> 2.2815442e+10 | C53: =IF($B52<=Tabla5[[#This Row],[INVERSIONES FCI]],+Tabla5[[#This Row],[INVERSIONES FCI]]-C52,Tabla5[[#This Row],[INVERSIONES FCI]]) -> 2.2815442e+10 | D53: =IF($B52<=Tabla5[[#This Row],[INVERSIONES FCI]],+Tabla5[[#This Row],[INVERSIONES FCI]]-D52,Tabla5[[#This Row],[INVERSIONES FCI]]) -> 2.2815442e+10 | E53: =IF($B52<=Tabla5[[#This Row],[INVERSIONES FCI]],+Tabla5[[#This Row],[INVERSIONES FCI]]-E52,Tabla5[[#This Row],[INVERSIONES FCI]]) -> 2.2815442e+10 | F53: =IF($B52<=Tabla5[[#This Row],[INVERSIONES FCI]],+Tabla5[[#This Row],[INVERSIONES FCI]]-F52,Tabla5[[#This Row],[INVERSIONES FCI]]) -> 2.2815442e+10 | G53: =IF($B52<=Tabla5[[#This Row],[INVERSIONES FCI]],+Tabla5[[#This Row],[INVERSIONES FCI]]-G52,Tabla5[[#This Row],[INVERSIONES FCI]]) -> 2.2815442e+10 | H53: =IF($B52<=Tabla5[[#This Row],[INVERSIONES FCI]],+Tabla5[[#This Row],[INVERSIONES FCI]]-H52,Tabla5[[#This Row],[INVERSIONES FCI]]) -> 2.2815442e+10 | I53: =IF($B52<=Tabla5[[#This Row],[INVERSIONES FCI]],+Tabla5[[#This Row],[INVERSIONES FCI]]-I52,Tabla5[[#This Row],[INVERSIONES FCI]]) -> 2.2815442e+10 | J53: =IF($B52<=Tabla5[[#This Row],[INVERSIONES FCI]],+Tabla5[[#This Row],[INVERSIONES FCI]]-J52,Tabla5[[#This Row],[INVERSIONES FCI]]) -> 2.2815442e+10 | ... BA53: =IF($B52<=Tabla5[[#This Row],[INVERSIONES FCI]],+Tabla5[[#This Row],[INVERSIONES FCI]]-BA52,Tabla5[[#This Row],[INVERSIONES FCI]]) -> 2.2815442e+10 | BB53: {=IF(Tabla5[[#This Row],[FCI]]=0,0,_xlfn.XLOOKUP(TRUE,$B53:BA53>0,$B53:BA53,"",0,-1))} -> 2.2815442e+10
A54: 25-mar | B54: =HLOOKUP($A54,ESCENARIO[#All],7,FALSE) -> 2.282287e+10 | C54: =IF($B53<=Tabla5[[#This Row],[INVERSIONES FCI]],+Tabla5[[#This Row],[INVERSIONES FCI]]-C53,Tabla5[[#This Row],[INVERSIONES FCI]]) -> 7427764.4 | D54: =IF($B53<=Tabla5[[#This Row],[INVERSIONES FCI]],+Tabla5[[#This Row],[INVERSIONES FCI]]-D53,Tabla5[[#This Row],[INVERSIONES FCI]]) -> 7427764.4 | E54: =IF($B53<=Tabla5[[#This Row],[INVERSIONES FCI]],+Tabla5[[#This Row],[INVERSIONES FCI]]-E53,Tabla5[[#This Row],[INVERSIONES FCI]]) -> 7427764.4 | F54: =IF($B53<=Tabla5[[#This Row],[INVERSIONES FCI]],+Tabla5[[#This Row],[INVERSIONES FCI]]-F53,Tabla5[[#This Row],[INVERSIONES FCI]]) -> 7427764.4 | G54: =IF($B53<=Tabla5[[#This Row],[INVERSIONES FCI]],+Tabla5[[#This Row],[INVERSIONES FCI]]-G53,Tabla5[[#This Row],[INVERSIONES FCI]]) -> 7427764.4 | H54: =IF($B53<=Tabla5[[#This Row],[INVERSIONES FCI]],+Tabla5[[#This Row],[INVERSIONES FCI]]-H53,Tabla5[[#This Row],[INVERSIONES FCI]]) -> 7427764.4 | I54: =IF($B53<=Tabla5[[#This Row],[INVERSIONES FCI]],+Tabla5[[#This Row],[INVERSIONES FCI]]-I53,Tabla5[[#This Row],[INVERSIONES FCI]]) -> 7427764.4 | J54: =IF($B53<=Tabla5[[#This Row],[INVERSIONES FCI]],+Tabla5[[#This Row],[INVERSIONES FCI]]-J53,Tabla5[[#This Row],[INVERSIONES FCI]]) -> 7427764.4 | ... BB54: =IF($B53<=Tabla5[[#This Row],[INVERSIONES FCI]],+Tabla5[[#This Row],[INVERSIONES FCI]]-BB53,Tabla5[[#This Row],[INVERSIONES FCI]]) -> 7427764.4 | BC54: {=IF(Tabla5[[#This Row],[FCI]]=0,0,_xlfn.XLOOKUP(TRUE,$B54:BB54>0,$B54:BB54,"",0,-1))} -> 7427764.4
